Workbook
Name A_impresión_IM: #REF!
Name ANTONE1: #REF!
Name Calidad: #REF!
Name CD: #REF!
Name CDU: #REF!
Name CDV: #REF!
Name cesantia: #REF!
Name COMPANIA: #REF!
Name DD: #REF!
Name DDT: #REF!
Name desperdicio: #REF!
Name FECHA: #REF!
Name FlujoBanco: #REF!
Name formula: #REF!
Name formula1: #REF!
Name formula2: #REF!
Name herramientas: #REF!
Name idss: #REF!
Name INICIO: #REF!
Name itebis: #REF!
Name MmExcelLinker_B10F4F3A_688F_4097_8347_A703957170B8: DESGLOSE #REF!
Name MmExcelLinker_B10F4F3A_688F_4097_8347_A703957170B8: DESGLOSE #REF!
Name MmExcelLinker_B10F4F3A_688F_4097_8347_A703957170B8: DESGLOSE #REF!
Name MmExcelLinker_B10F4F3A_688F_4097_8347_A703957170B8: DESGLOSE #REF!
Name MmExcelLinker_D2E69CB0_417E_47FC_9054_C3A7FE3E45A0: CONDOMINIO #REF!
Name MmExcelLinker_D2E69CB0_417E_47FC_9054_C3A7FE3E45A0: CONDOMINIO #REF!
Name MmExcelLinker_D2E69CB0_417E_47FC_9054_C3A7FE3E45A0: CONDOMINIO #REF!
Name MmExcelLinker_D2E69CB0_417E_47FC_9054_C3A7FE3E45A0: CONDOMINIO #REF!
Name nn: #REF!
Name NO: #REF!
Name OBRA: #REF!
Name PARTIDABASE: #REF!
Name pensiones: #REF!
Name preaviso: #REF!
Name PROPIETARIO: #REF!
Name regalia: #REF!
Name RIF: #REF!
Name t.c.: #REF!
Name tasa: #REF!
Name TITULO: #REF!
Name TITULOPROPIETARIO: #REF!
Name totaladministracion: #REF!
Name totalgastosmedicos: #REF!
Name totalgeneral: #REF!
Name totalhhdirecta: #REF!
Name totalhhindirecta: #REF!
Name totalnominadirecta: #REF!
Name totalnominaindirecta: #REF!
Name totalseguridad: #REF!
Name totalutilidad: #REF!
Name transporte: #REF!
Name Unit_Type_D: #REF!
Name X: #REF!
Name yucatan: #REF!
Name yucatan1: #REF!

Sheet 1. RESUMEN EJECUTIVO
B2: FIDEICOMISO ARAYA — INFORME JUNIO 2026
B3: Control Presupuestal · Cuentas por Pagar · Anticipos | Corte: 30 de junio de 2026
B5: INGRESOS POR FUENTE — Valores en RD$ | H5: DISPONIBILIDAD
B6: INGRESOS POR FUENTE — Valores en RD$ | C6: PRESUPUESTO | D6: EJECUTADO | E6: POR EJECUTAR | H6: INGRESOS ACUM. RD$ | I6: % PART. | J6: Acum 2024 | K6: Ene-25 | L6: Feb-25 | M6: Mar-25 | N6: Abr-25 | O6: May-25 | P6: Jun-25 | Q6: Jul-25 | R6: Ago-25 | S6: Sep-25 | T6: Oct-25 | U6: Nov-25 | V6: Dic-25 | W6: Ene-26 | X6: Feb-26 | Y6: Mar-26 | Z6: Abr-26 | AA6: May-26 | AB6: Jun-26 | AC6: Jul-26 | AD6: Aug-26 | AE6: Sep-26 | AF6: Oct-26 | AG6: Nov-26 | AH6: Dec-26 | AI6: Jan-27 | AJ6: Feb-27 | AK6: Mar-27 | AL6: Apr-27 | AM6: May-27 | AN6: Jun-27 | AO6: Jul-27 | AP6: Aug-27 | AQ6: Sep-27 | AR6: Oct-27 | AS6: Nov-27 | AT6: Dec-27 | AU6: Jan-28 | AV6: Feb-28 | AW6: Mar-28 | AX6: Apr-28 | AY6: May-28 | AZ6: Jun-28 | BA6: Jul-28 | BB6: Aug-28 | BC6: Sep-28 | BD6: Oct-28 | BE6: Nov-28 | BF6: Dec-28 | BG6: Jan-29 | BH6: Feb-29 | BI6: Mar-29 | BJ6: Apr-29 | BK6: May-29 | BL6: Jun-29 | BM6: Jul-29 | BN6: Aug-29 | BO6: Sep-29 | BP6: Oct-29 | BQ6: Nov-29 | BR6: Dec-29 | BS6: Jan-30 | BT6: Feb-30 | BU6: TOTAL PROYECCIÓN | BZ6: Total
B7: ◆ DEPÓSITOS DE CLIENTES | C7: =+C13 -> 68213916 | D7: =+D13 -> 22621811 | E7: =+C7-D7 -> 45592105 | H7: =SUM(J7:AB7) -> 2.209977e+08 | I7: =IF(D24=0,0,D7/D24) -> 0 | J7: =SUM(J14) -> 597566.75 | K7: =SUM(K14) -> 303761.92 | L7: =SUM(L14) -> 0 | M7: =SUM(M14) -> 61261.19 | N7: =SUM(N14) -> 2943821.6 | O7: =SUM(O14) -> 6287923.9 | P7: =SUM(P14) -> 12847852 | Q7: =SUM(Q14) -> 18376057 | ... AA7: =SUM(AA14) -> 17029605 | AB7: =+AB14 -> 18301398 | AC7: =+AC14 -> 18000000 | AD7: =+AD14 -> 18000000 | AE7: =+AE14 -> 18000000 | AF7: =+AF14 -> 18000000 | AG7: =+AG14 -> 18000000 | AH7: =+AH14 -> 18000000 | AI7: =+AI14 -> 0 | ... BT7: =+BT14 -> 0 | BZ7: =+H7+AB7+AC7+AD7+AE7+AF7+AG7 -> 3.2929909e+08
B8: └ Unidades vendidas en el período | C8: 462 | D8: =+H8 -> 164 | E8: =+C8-D8 -> 298 | H8: =SUM(J8:AB8) -> 164 | I8: =IF(D24=0,0,D8/D24) -> 0 | P8: 3 | Q8: 29 | R8: 20 | S8: 24 | T8: 12 | U8: 9 | V8: 12 | W8: 2 | X8: 7 | Y8: 14 | Z8: 10 | AA8: 11 | AB8: 11 | AC8: 15 | AD8: 15 | AE8: 15 | AF8: 15 | AG8: 15 | AH8: 15
B9: └ Unidades desistidas en el período | D9: =+H9 -> -3 | E9: =+C9-D9 -> 3 | H9: =SUM(J9:AB9) -> -3 | I9: =IF(D24=0,0,D9/D24) -> 0 | X9: -2 | AA9: -1
B10: └ Unidades vinculadas en el período | C10: 462 | D10: =+H10 -> 161 | E10: =SUM(E8:E9) -> 301 | H10: =SUM(J10:AB10) -> 161 | I10: =IF(D24=0,0,D10/D24) -> 0 | J10: =+J8+J9 -> 0 | K10: =+K8+K9 -> 0 | L10: =+L8+L9 -> 0 | M10: =+M8+M9 -> 0 | N10: =+N8+N9 -> 0 | O10: =+O8+O9 -> 0 | P10: =+P8+P9 -> 3 | Q10: =+Q8+Q9 -> 29 | ... AH10: =+AH8+AH9 -> 15
B11: └ Monto vendido en el período | D11: =SUM(J11:AB11) -> 23071011 | I11: =IF(D24=0,0,D11/D24) -> 0 | P11: 390100 | Q11: 3803830 | R11: 2530870 | S11: 3264350 | T11: 1674700 | U11: 1263361 | V11: 1596100 | W11: 145350 | X11: 1375650 | Y11: 2067350 | Z11: 1504150 | AA11: 1797250 | AB11: 1657950 | AC11: 2250000 | AD11: 2250000 | AE11: 2250000 | AF11: 2250000 | AG11: 2250000 | AH11: 2250000
B12: └ Monto desistido en el período | D12: =SUM(J12:AB12) -> -449200 | I12: =IF(D24=0,0,D12/D24) -> 0 | X12: -309900 | AA12: -139300
B13: └ Total Monto vinculado en el período | C13: 68213916 | D13: =SUM(J13:AB13) -> 22621811 | E13: =+C13-D13 -> 45592105 | I13: =IF(D24=0,0,D13/D24) -> 0 | J13: =+J11+J12 -> 0 | K13: =+K11+K12 -> 0 | L13: =+L11+L12 -> 0 | M13: =+M11+M12 -> 0 | N13: =+N11+N12 -> 0 | O13: =+O11+O12 -> 0 | P13: =+P11+P12 -> 390100 | Q13: =+Q11+Q12 -> 3803830 | ... AH13: =+AH11+AH12 -> 2250000
B14: └ Monto depósitos recibidos (RD$) | H14: =SUM(J14:AB14) -> 2.209977e+08 | I14: =IF(D24=0,0,D14/D24) -> 0 | J14: 597566.75 | K14: 303761.92 | M14: 61261.19 | N14: 2943821.6 | O14: 6287923.9 | P14: 12847852 | Q14: 18376057 | R14: 16465116 | S14: 19518073 | T14: 21677599 | U14: 10776009 | V14: 15186373 | W14: 9131873.1 | X14: 16575280 | Y14: 17317936 | Z14: 17600190 | AA14: 17029605 | AB14: =17095509.97+1205887.79 -> 18301398 | AC14: 18000000 | AD14: 18000000 | AE14: 18000000 | AF14: 18000000 | AG14: 18000000 | AH14: 18000000
B15: ◆ APORTES DE SOCIOS | H15: =SUM(J15:AB15) -> 3.2291773e+08 | I15: =IF(D24=0,0,D15/D24) -> 0 | J15: =SUM(J16) -> 1.5969577e+08 | K15: =SUM(K16) -> 0 | L15: =SUM(L16) -> 0 | M15: =SUM(M16) -> 0 | N15: =SUM(N16) -> 0 | O15: =SUM(O16) -> 0 | P15: =SUM(P16) -> 0 | Q15: =SUM(Q16) -> 0 | ... AA15: =SUM(AA16) -> 0 | BZ15: =+H15+AB15+AC15+AD15+AE15+AF15+AG15 -> 3.2291773e+08
B16: └ AFI Universal — Fideicomitente | H16: =SUM(J16:AA16) -> 3.2291773e+08 | I16: =IF(D24=0,0,D16/D24) -> 0 | J16: 1.5969577e+08 | R16: 1.7025268e+08 | Z16: -7030718.2
B17: ◆ PRÉSTAMOS RECIBIDOS | H17: =SUM(J17:AB17) -> 200000000 | I17: =IF(D24=0,0,D17/D24) -> 0 | J17: =SUM(J18:J20) -> 0 | K17: =SUM(K18:K20) -> 0 | L17: =SUM(L18:L20) -> 0 | M17: =SUM(M18:M20) -> 0 | N17: =SUM(N18:N20) -> 15000000 | O17: =SUM(O18:O20) -> 7200000 | P17: =SUM(P18:P20) -> 12000000 | Q17: =SUM(Q18:Q20) -> 15000000 | ... AA17: =SUM(AA18:AA20) -> 20000000 | AB17: =SUM(AB18:AB21) -> 40000000 | AC17: =SUM(AC18:AC21) -> 100000000 | AD17: =SUM(AD18:AD21) -> 100000000 | AE17: =SUM(AE18:AE21) -> -10000000 | AF17: =SUM(AF18:AF21) -> 0 | AG17: =SUM(AG18:AG21) -> 160000000 | AH17: =SUM(AH18:AH21) -> 0 | AI17: =SUM(AI18:AI21) -> 0 | ... BT17: =SUM(BT18:BT21) -> 0 | BZ17: =+H17+AB17+AC17+AD17+AE17+AF17+AG17 -> 590000000
B18: └ Grupo BAK | H18: =SUM(J18:AA18) -> 0 | I18: =IF(D24=0,0,D18/D24) -> 0 | N18: 15000000 | O18: 7200000 | P18: 12000000 | Q18: 15000000 | T18: -5000000 | V18: -44200000
B19: └ AFI Universal (Crédito Puente) | C19: 100000000 | D19: =+H190 -> 0 | E19: =+C19-D19 -> 100000000 | H19: =SUM(J19:AB19) -> 0 | I19: =IF(D24=0,0,D19/D24) -> 0 | S19: 55184227 | U19: 44815773 | Y19: -100000000 | AC19: 100000000 | AE19: -100000000
B20: └ Banco Alaver | C20: 300000000 | D20: =+H20 -> 200000000 | E20: =+C20-D20 -> 100000000 | H20: =SUM(J20:AB20) -> 200000000 | I20: =IF(D24=0,0,D20/D24) -> 0 | Y20: 100000000 | Z20: 40000000 | AA20: 20000000 | AB20: 40000000 | AD20: 100000000 | AE20: -150000000 | AG20: -20000000 | BZ20: =+H20+AB20+AC20+AD20+AE20+AF20+AG20 -> 170000000
B21: └ IFC | C21: 420000000 | D21: =+H21 -> 0 | E21: =+C21-D21 -> 420000000 | I21: =IF(D24=0,0,D21/D24) -> 0 | AE21: 240000000 | AG21: 180000000 | BZ21: =+H21+AB21+AC21+AD21+AE21+AF21+AG21 -> 420000000
B22: ◆ INTERESES GENERADOS POR INVERSIONES | H22: =SUM(J22:AB22) -> 2442157.6 | I22: =IF(D24=0,0,D22/D24) -> 0 | J22: =SUM(J23) -> 157571.37 | K22: =SUM(K23) -> 12060.79 | L22: =SUM(L23) -> 5956.62 | M22: =SUM(M23) -> 1903.68 | N22: =SUM(N23) -> 13709.55 | O22: =SUM(O23) -> 14582.39 | P22: =SUM(P23) -> 23991.28 | Q22: =SUM(Q23) -> 92565.03 | ... AA22: =SUM(AA23) -> 39828.59 | AB22: 24807.75 | BZ22: =+H22+AB22+AC22+AD22+AE22+AF22+AG22 -> 2466965.3
B23: └ Cuentas de ahorro y Fondos de inversión | H23: =SUM(J23:AA23) -> 2417349.8 | I23: =IF(D24=0,0,D23/D24) -> 0 | J23: 157571.37 | K23: 12060.79 | L23: 5956.62 | M23: 1903.68 | N23: 13709.55 | O23: 14582.39 | P23: 23991.28 | Q23: 92565.03 | R23: 173774.27 | S23: 260138.61 | T23: 332815.92 | U23: 328847.65 | V23: 529575.76 | W23: 144258.21 | X23: 134169.93 | Y23: 129606.28 | Z23: 21993.88 | AA23: 39828.59
B24: TOTAL INGRESOS RD$ | H24: =SUM(J24:AB24) -> 7.4635759e+08 | I24: 1 | J24: =+J7+J15+J17+J22 -> 1.6045091e+08 | K24: =+K7+K15+K17+K22 -> 315822.71 | L24: =+L7+L15+L17+L22 -> 5956.62 | M24: =+M7+M15+M17+M22 -> 63164.87 | N24: =+N7+N15+N17+N22 -> 17957531 | O24: =+O7+O15+O17+O22 -> 13502506 | P24: =+P7+P15+P17+P22 -> 24871844 | Q24: =+Q7+Q15+Q17+Q22 -> 33468622 | ... BT24: =+BT7+BT15+BT17+BT22 -> 0 | BZ24: =+H24+AB24+AC24+AD24+AE24+AF24+AG24 -> 1.2446838e+09
B25: TOTAL INGRESOS ACUMULADOS RD$ | H25: =+H7+H15+H17+H22 -> 7.4635759e+08 | J25: =+J24 -> 1.6045091e+08 | K25: =+J25+K24 -> 1.6076673e+08 | L25: =+K25+L24 -> 1.6077269e+08 | M25: =+L25+M24 -> 1.6083586e+08 | N25: =+M25+N24 -> 1.7879339e+08 | O25: =+N25+O24 -> 1.9229589e+08 | P25: =+O25+P24 -> 2.1716774e+08 | Q25: =+P25+Q24 -> 2.5063636e+08 | R25: =+Q25+R24 -> 4.3752793e+08 | ... BU25: =+BT25+BU24 -> 1.2043576e+09 | BZ25: =+BZ24 -> 1.2446838e+09
B27: CONTROL PRESUPUESTAL | C27: Valores en RD$
B28: CENTRO DE COSTO / AUXILIAR | C28: PRESUPUESTO TOTAL | D28: EJECUTADO | E28: POR EJECUTAR | F28: ANTICIPOS ACUM. | G28: CXP AL CORTE | H28: PAGOS ACUMULADOS | I28: % EJEC. | J28: Acum 2024 | K28: Ene-25 | L28: Feb-25 | M28: Mar-25 | N28: Abr-25 | O28: May-25 | P28: Jun-25 | Q28: Jul-25 | R28: Ago-25 | S28: Sep-25 | T28: Oct-25 | U28: Nov-25 | V28: Dic-25 | W28: Ene-26 | X28: Feb-26 | Y28: Mar-26 | Z28: Abr-26 | AA28: May-26 | AB28: Jun-26 | AC28: Jul-26 | AD28: Aug-26 | AE28: Sep-26 | AF28: Oct-26 | AG28: Nov-26 | AH28: Dec-26 | AI28: Jan-27 | AJ28: Feb-27 | AK28: Mar-27 | AL28: Apr-27 | AM28: May-27 | AN28: Jun-27 | AO28: Jul-27 | AP28: Aug-27 | AQ28: Sep-27 | AR28: Oct-27 | AS28: Nov-27 | AT28: Dec-27 | AU28: Jan-28 | AV28: Feb-28 | AW28: Mar-28 | AX28: Apr-28 | AY28: May-28 | AZ28: Jun-28 | BA28: Jul-28 | BB28: Aug-28 | BC28: Sep-28 | BD28: Oct-28 | BE28: Nov-28 | BF28: Dec-28 | BG28: Jan-29 | BH28: Feb-29 | BI28: Mar-29 | BJ28: Apr-29 | BK28: May-29 | BL28: Jun-29 | BM28: Jul-29 | BN28: Aug-29 | BO28: Sep-29 | BP28: Oct-29 | BQ28: Nov-29 | BR28: Dec-29 | BS28: Jan-30 | BT28: Feb-30 | BU28: TOTAL PROYECCIÓN | BZ28: Total
B29: ◆ CONSTRUCCIÓN
B30: 1-1 Terreno | C30: =266773709.05+AC30+AD30 -> 2.6968516e+08 | D30: =SUM(J30:AB30) -> 2.6677371e+08 | E30: =+C30-D30 -> 2911447.4 | H30: =+D30+F30-G30 -> 2.6677371e+08 | I30: =IF(H$45=0,0,H30/H$45) -> 0.55466589 | J30: 94172342 | O30: 18880 | R30: 1.7025268e+08 | S30: 1179 | V30: 1 | Z30: -7030718.2 | AA30: 9359346.1 | AC30: 1625472.4 | AD30: 1285975 | BU30: =SUM(AB30:BT30) -> 2911447.4 | BZ30: =+H30+AB30+AC30+AD30+AE30+AF30+AG30 -> 2.6968516e+08
B31: 1-2 Diseño y Proyecto | C31: 25000000 | D31: =SUM(J31:AB31) -> 24159807 | E31: =+C31-D31 -> 840192.64 | F31: 273000 | H31: =+D31+F31-G31 -> 24432807 | I31: =IF(H$45=0,0,H31/H$45) -> 0.050799777 | J31: 20979516 | K31: 428149.75 | M31: 146320 | N31: 108350.26 | O31: 53100 | Q31: 278099.52 | R31: 1595686.8 | S31: -190307.52 | T31: 310669.15 | V31: 273687.19 | X31: 416685.22 | Y31: 31433.41 | Z31: -271582.08 | BU31: =SUM(AB31:BT31) -> 0 | BW31: Urbanismo | BX31: Edificaciones | BZ31: =+H31+AB31+AC31+AD31+AE31+AF31+AG31 -> 24432807
B32: 1-4 Urbanismo | C32: 4.6917367e+08 | D32: =SUM(J32:AB32) -> 50777443 | E32: =+C32-D32 -> 4.1839622e+08 | F32: 3201292.2 | G32: =2409540.07+31179.21 -> 2440719.3 | H32: =+D32+F32-G32 -> 51538016 | I32: =IF(H$45=0,0,H32/H$45) -> 0.10715591 | J32: 9219083.6 | N32: 353433.2 | O32: 93563.38 | P32: 401816.36 | Q32: 17765977 | R32: 2900560.5 | S32: -13949178 | T32: 201871.48 | U32: 1617336.1 | V32: 15407307 | W32: 222844.91 | X32: 2449569.8 | Y32: 1844423.4 | Z32: 2432002.3 | AA32: 4340947.8 | AB32: 5475884.7 | AC32: =2233363.79-BW38 -> 9945082.1 | AD32: 25883233 | AE32: 19023863 | AF32: 30184986 | AG32: 22131186 | AH32: 27733359 | AI32: 9994863 | AJ32: 12921923 | AK32: 13067198 | AL32: 7358492 | AM32: 14828592 | AN32: 12874976 | AO32: 14527005 | AP32: 20554545 | AQ32: 12799482 | AR32: 12013658 | AS32: 13823208 | AT32: 13482346 | AU32: 12131034 | AV32: 13811771 | AW32: 18464279 | AX32: 14290217 | AY32: 11114566 | AZ32: 5972630 | BA32: 2180738 | BB32: 2907651 | BC32: 2180738 | BD32: 2696366 | BU32: =SUM(AB32:BT32) -> 3.8437387e+08 | BV32: Ejecutado de dic-25 a jun-26 | BW32: =+D32-33504463 -> 17272980 | BX32: =+D33 -> 91014535 | BY32: =+BW32+BX32 -> 1.0828751e+08 | BZ32: =+H32+AB32+AC32+AD32+AE32+AF32+AG32 -> 1.6418225e+08
B33: 1-5 Edificaciones | C33: 1517166651 | D33: =SUM(J33:AB33) -> 91014535 | E33: =+C33-D33 -> 1.4261521e+09 | F33: 4044252 | G33: 9079360.7 | H33: =+D33+F33-G33 -> 85979426 | I33: =IF(H$45=0,0,H33/H$45) -> 0.1787652 | V33: 991237.18 | W33: 2132656.5 | X33: 6421897.4 | Y33: 23710126 | Z33: 17366039 | AA33: 17043612 | AB33: 23348966 | AC33: =41619451.81-BX38 -> 1.0967745e+08 | AD33: 50615128 | AE33: 58724023 | AF33: 41829222 | AG33: 47927697 | AH33: 31472733 | AI33: 68830255 | AJ33: 106468694 | AK33: 56788924 | AL33: 54650319 | AM33: 61097688 | AN33: 49492842 | AO33: 21864246 | AP33: 52347351 | AQ33: 49990554 | AR33: 42428902 | AS33: 74826189 | AT33: 38421250 | AU33: 34420885 | AV33: 101104251 | AW33: 53636125 | AX33: 38678782 | AY33: 45511341 | AZ33: 33619379 | BA33: 37777967 | BB33: 48464991 | BC33: 24826641 | BD33: 24008933 | BE33: 21480215 | BF33: 6678810 | BG33: 1109066 | BU33: =SUM(AB33:BT33) -> 1.5121198e+09 | BV33: CXP | BW33: =+G32 -> 2440719.3 | BX33: =+G33 -> 9079360.7 | BY33: =+BW33+BX33 -> 11520080 | BZ33: =+H33+AB33+AC33+AD33+AE33+AF33+AG33 -> 4.1810191e+08
B34: 1-6 Gerencia de Construcción | C34: 2.3438816e+08 | D34: =SUM(J34:AB34) -> 40247270 | E34: =+C34-D34 -> 1.9414089e+08 | G34: 86313.8 | H34: =+D34+F34-G34 -> 40160957 | I34: =IF(H$45=0,0,H34/H$45) -> 0.083501155 | J34: 1644662 | K34: 1770000 | M34: 885000 | N34: 2455806.5 | O34: 2360000 | P34: 2417857.3 | Q34: 2664755.2 | R34: 4720000 | T34: 2360000 | U34: 2783225.3 | V34: 1770000 | W34: 2360000 | X34: 2862845.2 | Y34: 2175899.8 | Z34: 2400227.5 | AA34: 2341111.1 | AB34: 2275880.4 | AC34: 2360000 | AD34: 2360000 | AE34: 2360000 | AF34: 2360000 | AG34: 2360000 | AH34: 5283637 | AI34: 7882512 | AJ34: 11939062 | AK34: 6985612 | AL34: 6200881 | AM34: 7592628 | AN34: 6236782 | AO34: 3639125 | AP34: 7290190 | AQ34: 6279004 | AR34: 5444256 | AS34: 8864940 | AT34: 5190360 | AU34: 4655192 | AV34: 11491602 | AW34: 7210040 | AX34: 5296900 | AY34: 5662591 | AZ34: 3959201 | BA34: 3995870 | BB34: 5137264 | BC34: 2700738 | BD34: 2670530 | BE34: 2148021 | BF34: 667881 | BG34: 110907 | BU34: =SUM(AB34:BT34) -> 1.5861161e+08 | BV34: Pagado | BW34: =+BW32-BW33 -> 14832260 | BX34: =+BX32-BX33 -> 81935174 | BY34: =+BW34+BX34 -> 96767434 | BZ34: =+H34+AB34+AC34+AD34+AE34+AF34+AG34 -> 54236837
B35: 1-7 Indirectos de Obra | C35: 47672168 | D35: =SUM(J35:AB35) -> 8294845.7 | E35: =+C35-D35 -> 39377322 | G35: =SUM(G36:G41) -> 779549.45 | H35: =+D35+F35-G35 -> 7515296.3 | I35: =IF(H$45=0,0,H35/H$45) -> 0.015625522 | P35: 147108.54 | Q35: 92700.8 | R35: 96854.4 | S35: 90246.4 | T35: 92700.8 | U35: 332688.71 | V35: 92700.8 | W35: 102858.24 | X35: 3036943.5 | Y35: 2022959.1 | Z35: 729930.47 | AA35: 731956.76 | AB35: =SUM(AB36:AB42) -> 725197.25 | AC35: =1600000 -> 1600000 | AD35: 1600000 | AE35: 1600000 | AF35: 1600000 | AG35: 1600000 | AH35: 755081 | AI35: 755081 | AJ35: 755081 | AK35: 755081 | AL35: 755081 | AM35: 755081 | AN35: 755081 | AO35: 755081 | AP35: 755081 | AQ35: 755081 | AR35: 755081 | AS35: 755081 | AT35: 755081 | AU35: 755081 | AV35: 755081 | AW35: 755081 | AX35: 755081 | AY35: 755081 | AZ35: 755081 | BA35: 755081 | BB35: 755081 | BC35: 755081 | BD35: 755081 | BE35: 755081 | BF35: 755081 | BG35: 755081 | BH35: 755081 | BI35: 755081 | BJ35: 755081 | BK35: 755081 | BL35: 755081 | BM35: 50045 | BU35: =SUM(AB35:BT35) -> 32182753 | BV35: Anticipos | BW35: =+F32 -> 3201292.2 | BX35: =+F33 -> 4044252 | BY35: =+BW35+BX35 -> 7245544.2 | BZ35: =+H35+AB35+AC35+AD35+AE35+AF35+AG35 -> 16240494
B36: └ 1-7-1 Gastos Personal Adm. de Obra | D36: =SUM(J36:AB36) -> 312900 | G36: 52150 | H36: 260750 | I36: =IF(H$45=0,0,H36/H$45) -> 0.00054214162 | X36: 104300 | Y36: 52150 | Z36: 52150 | AA36: 52150 | AB36: 52150 | BU36: =SUM(AB36:BT36) -> 52150 | BV36: Pagado | BW36: =+BW34+BW35 -> 18033553 | BX36: =+BX34+BX35 -> 85979426 | BY36: =+BW36+BX36 -> 1.0401298e+08 | BZ36: =+H36+AB36+AC36+AD36+AE36+AF36+AG36 -> 312900 | CD36: =+CB36-CC36 -> 0
B37: └ 1-7-2 Gastos Operativos Generales | D37: =SUM(J37:AB37) -> 624071.78 | G37: 46500 | H37: 569970.93 | I37: =IF(H$45=0,0,H37/H$45) -> 0.0011850622 | U37: 191502.06 | W37: 8080.64 | X37: 207605.89 | Y37: 54227.11 | Z37: 54302.87 | AA37: 54252.36 | AB37: 54100.85 | BU37: =SUM(AB37:BT37) -> 54100.85 | BV37: Según Flujo | BW37: 25745271 | BX37: 1.5403742e+08 | BY37: =+BW37+BX37 -> 1.7978269e+08 | BZ37: =+H37+AB37+AC37+AD37+AE37+AF37+AG37 -> 624071.78 | CD37: =+CB37-CC37 -> 0
B38: └ 1-7-3 Equipos y Transporte | D38: =SUM(J38:AB38) -> 3790569 | G38: 427200 | H38: 3363369 | I38: =IF(H$45=0,0,H38/H$45) -> 0.0069929907 | U38: 52569 | X38: 2029200 | Y38: 427200 | Z38: 427200 | AA38: 427200 | AB38: 427200 | BU38: =SUM(AB38:BT38) -> 427200 | BV38: Pendiente de Pagar a jun-26 | BW38: =+BW36-BW37 -> -7711718.3 | BX38: =+BX36-BX37 -> -68057996 | BY38: =+BW38+BX38 -> -75769715 | BZ38: =+H38+AB38+AC38+AD38+AE38+AF38+AG38 -> 3790569 | CD38: =+CB38-CC38 -> 0
B39: └ 1-7-4 Vigilancia | D39: =SUM(J39:AB39) -> 1113920 | G39: 90246.4 | H39: 1023673.6 | I39: =IF(H$45=0,0,H39/H$45) -> 0.0021283838 | P39: 92323.2 | Q39: 92700.8 | R39: 96854.4 | S39: 90246.4 | T39: 92700.8 | U39: 94400 | V39: 92700.8 | W39: 94777.6 | X39: 85337.6 | Z39: 94777.6 | AA39: 96854.4 | AB39: 90246.4 | BU39: =SUM(AB39:BT39) -> 90246.4 | BZ39: =+H39+AB39+AC39+AD39+AE39+AF39+AG39 -> 1113920 | CD39: =+CB39-CC39 -> 0
B40: └ 1-7-5 Póliza TRC | D40: =SUM(J40:AB40) -> 1387882 | G40: 61953.05 | H40: 1387882 | I40: =IF(H$45=0,0,H40/H$45) -> 0.0028856321 | Y40: 1387882 | BU40: =SUM(AB40:BT40) -> 0 | BZ40: =+H40+AB40+AC40+AD40+AE40+AF40+AG40 -> 1387882 | CD40: =+CB40-CC40 -> 0
B41: └ 1-7-6 Campamento | D41: =SUM(J41:AB41) -> 1065503 | G41: 101500 | H41: 964002.99 | I41: =IF(H$45=0,0,H41/H$45) -> 0.0020043189 | P41: 54785.34 | U41: -5782.35 | X41: 610500 | Y41: 101500 | Z41: 101500 | AA41: 101500 | AB41: 101500 | BU41: =SUM(AB41:BT41) -> 101500 | BZ41: =+H41+AB41+AC41+AD41+AE41+AF41+AG41 -> 1065503 | CD41: =+CB41-CC41 -> 0
B42: └ 1-7-7 Otros Gastos | D42: =SUM(J42:AB42) -> 0 | I42: =IF(H$45=0,0,H42/H$45) -> 0 | BU42: =SUM(AB42:BT42) -> 0 | BZ42: =+H42+AB42+AC42+AD42+AE42+AF42+AG42 -> 0 | CD42: =+CB42-CC42 -> 0
B43: 1-8 Fondo de Contingencia | C43: 39726806 | D43: =SUM(J43:AB43) -> 0 | E43: =+C43-D43 -> 39726806 | H43: =+D43+F43-G43 -> 0 | I43: =IF(H$45=0,0,H43/H$45) -> 0 | BU43: =SUM(AB43:BT43) -> 0 | BZ43: =+H43+AB43+AC43+AD43+AE43+AF43+AG43 -> 0
B44: 1-9 Inspección Técnica | C44: 19264643 | D44: =SUM(J44:AB44) -> 5069643 | E44: =+C44-D44 -> 14195000 | G44: 506964.3 | H44: =+D44+F44-G44 -> 4562678.7 | I44: =IF(H$45=0,0,H44/H$45) -> 0.0094865504 | T44: 1013928.6 | U44: 506964.3 | V44: 506964.3 | W44: 506964.3 | X44: 506964.3 | Y44: 506964.3 | Z44: 506964.3 | AA44: 506964.3 | AB44: 506964.3 | AC44: 506964.3 | AD44: 506964.3 | AE44: 506964.3 | AF44: 506964.3 | AG44: 506964.3 | AH44: 506964.3 | AI44: 506964.3 | AJ44: 506964.3 | AK44: 506964.3 | AL44: 506964.3 | AM44: 506964.3 | AN44: 506964.3 | AO44: 506964.3 | AP44: 506964.3 | AQ44: 506964.3 | AR44: 506964.3 | AS44: 506964.3 | AT44: 506964.3 | AU44: 506964.3 | AV44: 506964.3 | AW44: 506964.3 | AX44: 506964.3 | AY44: 506964.3 | AZ44: 506964.3 | BA44: 506964.3 | BB44: 506964.3 | BC44: 506964.3 | BD44: 506964.3 | BU44: =SUM(AB44:BT44) -> 14701965 | BZ44: =+H44+AB44+AC44+AD44+AE44+AF44+AG44 -> 7604464.5
B45: Subtotal CONSTRUCCIÓN | C45: =+C30+C31+C32+C33+C34+C35+C43+C44 -> 2.6220772e+09 | D45: =+D30+D31+D32+D33+D34+D35+D43+D44 -> 4.8633725e+08 | E45: =+E30+E31+E32+E33+E34+E35+E43+E44 -> 2.13574e+09 | F45: 7518544.2 | G45: 12086111 | H45: =+H30+H31+H32+H33+H34+H35+H43+H44 -> 4.8096289e+08 | I45: =IF(H$75=0,0,H45/H$75) -> 0.68418826 | J45: =+J30+J31+J32+J33+J34+J35+J43+J44 -> 1.260156e+08 | K45: =+K30+K31+K32+K33+K34+K35+K43+K44 -> 2198149.8 | L45: =+L30+L31+L32+L33+L34+L35+L43+L44 -> 0 | M45: =+M30+M31+M32+M33+M34+M35+M43+M44 -> 1031320 | N45: =+N30+N31+N32+N33+N34+N35+N43+N44 -> 2917590 | O45: =+O30+O31+O32+O33+O34+O35+O43+O44 -> 2525543.4 | P45: =+P30+P31+P32+P33+P34+P35+P43+P44 -> 2966782.2 | Q45: =+Q30+Q31+Q32+Q33+Q34+Q35+Q43+Q44 -> 20801532 | ... BU45: =+BU30+BU31+BU32+BU33+BU34+BU35+BU43+BU44 -> 2.1049015e+09 | BZ45: =+BZ30+BZ31+BZ32+BZ33+BZ34+BZ35+BZ43+BZ44 -> 9.5448392e+08
B46: ◆ GASTOS OPERATIVOS
B47: 2-1 Gerencia de la Promotora | C47: 1.8751053e+08 | D47: =SUM(J47:AB47) -> 26835783 | E47: =+C47-D47 -> 1.6067474e+08 | H47: =+D47+F47-G47 -> 26835783 | I47: =IF(H$68=0,0,H47/H$68) -> 0.14905683 | J47: 161175.97 | N47: 1770000 | O47: 1770000 | P47: 1770000 | Q47: 1770000 | R47: 1770000 | S47: 1770000 | T47: 1770000 | U47: 1770000 | V47: 1770000 | W47: 1770000 | X47: 1770000 | Y47: 1770000 | Z47: 1833058 | AA47: 1818545.2 | AB47: 1783003.6 | AC47: 1764604 | AD47: 1764604 | AE47: 3529209 | AF47: 3529209 | AG47: 3529209 | AH47: 4736487 | AI47: 6306009 | AJ47: 9551249 | AK47: 5588490 | AL47: 4960705 | AM47: 6074102 | AN47: 4989425 | AO47: 2911300 | AP47: 5832152 | AQ47: 5023203 | AR47: 4355405 | AS47: 7091952 | AT47: 4152288 | AU47: 3724154 | AV47: 9193282 | AW47: 5768032 | AX47: 4237520 | AY47: 4530073 | AZ47: 3167361 | BA47: 3196696 | BB47: 4109811 | BC47: 2160590 | BD47: 2136424 | BE47: 1718417 | BF47: 577471 | BU47: =SUM(AB47:BT47) -> 1.3199244e+08 | BZ47: =+H47+AB47+AC47+AD47+AE47+AF47+AG47 -> 42735621
B48: 2-2 Gerencia de Ventas | C48: 3.2774615e+08 | D48: =SUM(J48:AB48) -> 1.1724832e+08 | E48: =+C48-D48 -> 2.1049783e+08 | G48: 4213466.9 | H48: =+D48+F48-G48 -> 1.1303485e+08 | I48: =IF(H$68=0,0,H48/H$68) -> 0.62784145 | J48: 559355.54 | L48: 645765.21 | M48: 595001.35 | N48: 1549872.5 | O48: 1423527.6 | P48: 1733909.8 | Q48: 7890097.2 | R48: 16166710 | S48: 11886550 | T48: 12659941 | U48: 15204798 | V48: 5614678.3 | W48: 5336475.7 | X48: 3557189.5 | Y48: 9528645.2 | Z48: 5807715.2 | AA48: 7569317.1 | AB48: =SUM(AB49:AB52) -> 9518771 | AC48: 10573141 | AD48: 10573141 | AE48: 10573141 | AF48: 10573141 | AG48: 10573141 | AH48: 10573141 | AI48: 10573141 | AJ48: 10573141 | AK48: 10573141 | AL48: 10573141 | AM48: 10573141 | AN48: 10573141 | AO48: 10573141 | AP48: 10573141 | AQ48: 10573141 | AR48: 10573141 | AS48: 10573141 | AT48: 10573141 | AU48: 10573141 | AV48: 8809848 | AW48: 7634319 | AX48: 1756676 | AY48: 1756676 | AZ48: 1756676 | BA48: 1756676 | BB48: 1756676 | BC48: 1756676 | BD48: 1756676 | BE48: 1756676 | BF48: 1756676 | BG48: 1756676 | BH48: 1756676 | BI48: 1756676 | BJ48: 1756676 | BK48: 1756676 | BL48: 1756676 | BM48: 1756676 | BN48: 1713916 | BO48: 1390836 | BP48: 1390836 | BQ48: 1390836 | BR48: 1145486 | BS48: 1123688 | BT48: 1123688 | BU48: =SUM(AB48:BT48) -> 2.6423872e+08 | BZ48: =+H48+AB48+AC48+AD48+AE48+AF48+AG48 -> 1.7541933e+08
B49: └ 2-2-1 Comisiones por Venta | D49: =SUM(J49:AB49) -> 86405575 | G49: 4011222.4 | H49: 79374170 | I49: =IF(H$68=0,0,H49/H$68) -> 0.44087636 | Q49: 6290641.7 | R49: 14391880 | S49: 9799035.5 | T49: 10674167 | U49: 12853060 | V49: 3427746.4 | W49: 3349220.4 | X49: 1786576.2 | Y49: 7825189.7 | Z49: 3904479.1 | AA49: 5072174.2 | AB49: 7031404.5 | BU49: =SUM(AB49:BT49) -> 7031404.5 | BZ49: =+H49+AB49+AC49+AD49+AE49+AF49+AG49 -> 86405575
B50: └ 2-2-2 Administración de la Venta | D50: =SUM(J50:AB50) -> 11539314 | H50: 10782128 | I50: =IF(H$68=0,0,H50/H$68) -> 0.059888317 | N50: 767000 | O50: 767000 | P50: 767000 | Q50: 767000 | R50: 767000 | S50: 767000 | T50: 767000 | U50: 767000 | V50: 767000 | W50: 767000 | X50: 767000 | Y50: 783295.8 | Z50: 770819.66 | AA50: 791013 | AB50: 757185.94 | BU50: =SUM(AB50:BT50) -> 757185.94 | BZ50: =+H50+AB50+AC50+AD50+AE50+AF50+AG50 -> 11539314
B51: └ 2-2-3 Equipo de Trabajo Oficina de Ventas | D51: =SUM(J51:AB51) -> 17858976 | H51: 16260807 | I51: =IF(H$68=0,0,H51/H$68) -> 0.090319121 | J51: 559355.54 | L51: 645765.21 | M51: 595001.35 | N51: 677173.63 | O51: 620535.91 | P51: 825710.8 | Q51: 832455.53 | R51: 941719.5 | S51: 1237302.5 | T51: 1132936.9 | U51: 1276808.7 | V51: 1311409.7 | W51: 1120340.3 | X51: 924788.11 | Y51: 905264.29 | Z51: 1047302.9 | AA51: 1606936 | AB51: 1598169.6 | BU51: =SUM(AB51:BT51) -> 1598169.6 | BZ51: =+H51+AB51+AC51+AD51+AE51+AF51+AG51 -> 17858976
B52: └ 2-2-4 Gastos Operativos Oficina de Ventas | D52: =SUM(J52:AB52) -> 1444454.4 | G52: 202244.53 | H52: 1312443.5 | I52: =IF(H$68=0,0,H52/H$68) -> 0.0072898438 | N52: 105698.84 | O52: 35991.7 | P52: 141199.04 | R52: 66110.39 | S52: 83212.27 | T52: 85836.93 | U52: 307928.98 | V52: 108522.24 | W52: 99915.09 | X52: 78825.18 | Y52: 14895.35 | Z52: 85113.54 | AA52: 99193.94 | AB52: 132010.93 | BU52: =SUM(AB52:BT52) -> 132010.93 | BZ52: =+H52+AB52+AC52+AD52+AE52+AF52+AG52 -> 1444454.4
B53: 2-3 Administración Fiduciaria | C53: 81458723 | D53: =SUM(J53:AB53) -> 6982961.1 | E53: =+C53-D53 -> 74475762 | G53: 293802.58 | H53: =+D53+F53-G53 -> 6689158.5 | I53: =IF(H$68=0,0,H53/H$68) -> 0.037154301 | J53: 373034.61 | K53: 43563.47 | L53: 36723.13 | M53: 37034.89 | N53: 51335.37 | O53: 125971.53 | P53: 205035.01 | Q53: 193826.15 | R53: 228402.98 | S53: 824240.62 | T53: 143558.05 | U53: 111569.53 | V53: 187644.31 | W53: 111272.46 | X53: 1296067.7 | Y53: 578468.84 | Z53: 596002.47 | AA53: 770633.69 | AB53: =SUM(AB54:AB55) -> 1068576.3 | AC53: 800000 | AD53: 800000 | AE53: 800000 | AF53: 800000 | AG53: 800000 | AH53: 1358750 | AI53: 1358750 | AJ53: 1358750 | AK53: 1358750 | AL53: 1358750 | AM53: 1358750 | AN53: 1358750 | AO53: 1358750 | AP53: 1358750 | AQ53: 1358750 | AR53: 1358750 | AS53: 1358750 | AT53: 1358750 | AU53: 1358750 | AV53: 1358750 | AW53: 1358750 | AX53: 1358750 | AY53: 1358750 | AZ53: 1358750 | BA53: 1358750 | BB53: 1358750 | BC53: 1358750 | BD53: 1358750 | BE53: 1358750 | BF53: 1358750 | BG53: 1358750 | BH53: 1358750 | BI53: 1358750 | BJ53: 1358750 | BK53: 1358750 | BL53: 1358750 | BM53: 1358750 | BN53: 1358750 | BO53: 1358750 | BP53: 1358750 | BQ53: 1358750 | BR53: 1358750 | BS53: 1358750 | BT53: 1358750 | BU53: =SUM(AB53:BT53) -> 58059826 | BZ53: =+H53+AB53+AC53+AD53+AE53+AF53+AG53 -> 11757735
B54: └ 2-3-1 Adm. General de la Fiduciaria | D54: =SUM(J54:AB54) -> 5022538.1 | H54: 4247764.4 | I54: =IF(H$68=0,0,H54/H$68) -> 0.023593807 | J54: 344499.26 | K54: 36279.57 | L54: 36723.13 | M54: 37034.89 | N54: 37423.76 | O54: 34807.29 | P54: 35695 | Q54: 35546.73 | R54: 36234.2 | S54: 627694.69 | T54: 37152.89 | U54: 37296.32 | V54: 113391.16 | W54: 37257.67 | X54: 1216866.4 | Y54: 486278.51 | Z54: 498144.27 | AA54: 559438.58 | AB54: 774773.75 | BU54: =SUM(AB54:BT54) -> 774773.75 | BZ54: =+H54+AB54+AC54+AD54+AE54+AF54+AG54 -> 5022538.1
B55: └ 2-3-2 Debida Diligencia / Fiduciaria | D55: =SUM(J55:AB55) -> 1960423 | G55: 293802.58 | H55: 1666620.4 | I55: =IF(H$68=0,0,H55/H$68) -> 0.0092570862 | J55: 28535.35 | K55: 7283.9 | N55: 13911.61 | O55: 91164.24 | P55: 169340.01 | Q55: 158279.42 | R55: 192168.78 | S55: 196545.93 | T55: 106405.16 | U55: 74273.21 | V55: 74253.15 | W55: 74014.79 | X55: 79201.23 | Y55: 92190.33 | Z55: 97858.2 | AA55: 211195.11 | AB55: 293802.58 | BU55: =SUM(AB55:BT55) -> 293802.58 | BZ55: =+H55+AB55+AC55+AD55+AE55+AF55+AG55 -> 1960423
B56: 2-4 Promoción y Publicidad | C56: 69521911 | D56: =SUM(J56:AB56) -> 34333891 | E56: =+C56-D56 -> 35188020 | G56: 856426.95 | H56: =+D56+F56-G56 -> 33477464 | I56: =IF(H$68=0,0,H56/H$68) -> 0.18594742 | J56: 11066720 | K56: 915790.08 | L56: 1931201.9 | M56: 1103623.2 | N56: 807731.34 | O56: 740040.2 | P56: 1412884.7 | Q56: 3494146.4 | R56: 184710.13 | S56: 551935.68 | T56: 1245788.4 | U56: 949800.34 | V56: 984721.38 | W56: 938693.31 | X56: 882717.03 | Y56: 1443186.7 | Z56: 1372155.5 | AA56: 1943642.6 | AB56: =SUM(AB57:AB64) -> 2364401.5 | AC56: 1600000 | AD56: 1600000 | AE56: 1600000 | AF56: 1600000 | AG56: 1600000 | AH56: 1170905 | AI56: 1170905 | AJ56: 1170905 | AK56: 1170905 | AL56: 1170905 | AM56: 1170905 | AN56: 1170905 | AO56: 1170905 | AP56: 1170905 | AQ56: 1170905 | AR56: 1170905 | AS56: 1170905 | AT56: 1170905 | AU56: 1170905 | AV56: 1170905 | AW56: 1170905 | AX56: 490452 | BU56: =SUM(AB56:BT56) -> 29589334 | BZ56: =+H56+AB56+AC56+AD56+AE56+AF56+AG56 -> 43841865
B57: └ 2-4-1 Apartamento Modelo / Show Room | D57: =SUM(J57:AB57) -> 5143605.2 | H57: 5143605.2 | I57: =IF(H$68=0,0,H57/H$68) -> 0.028569671 | J57: 5993469.7 | K57: 292040.78 | M57: 149662.62 | N57: 167745.43 | P57: 258175.66 | R57: -1537035 | U57: -180453.94 | BU57: =SUM(AB57:BT57) -> 0 | BZ57: =+H57+AB57+AC57+AD57+AE57+AF57+AG57 -> 5143605.2
B58: └ 2-4-2 Inversión Inicial Promoción y Mercadeo | D58: =SUM(J58:AB58) -> 11245197 | G58: -14760.54 | H58: 11245197 | I58: =IF(H$68=0,0,H58/H$68) -> 0.062460389 | J58: 4481135.7 | K58: 57400.51 | L58: 1795826.4 | M58: 187959.76 | N58: 188099.53 | O58: 192037.45 | P58: 179220.89 | Q58: 2902845.2 | R58: 1207725.2 | S58: 52946.6 | BU58: =SUM(AB58:BT58) -> 0 | BZ58: =+H58+AB58+AC58+AD58+AE58+AF58+AG58 -> 11245197
B59: └ 2-4-3 Medios Digitales (Campaña y Redes) | D59: =SUM(J59:AB59) -> 4000132.3 | G59: 99358.92 | H59: 3632136.3 | I59: =IF(H$68=0,0,H59/H$68) -> 0.020174359 | M59: 74992.79 | N59: 52091.04 | O59: 129162.79 | P59: 186272.04 | Q59: 234473.14 | R59: 259817.28 | S59: 122677.4 | T59: 196734.06 | U59: 257568.44 | V59: 176353.58 | W59: 337884.2 | X59: 114023.92 | Y59: 472859.2 | Z59: 366567.64 | AA59: 650658.78 | AB59: 367996.01 | BU59: =SUM(AB59:BT59) -> 367996.01 | BZ59: =+H59+AB59+AC59+AD59+AE59+AF59+AG59 -> 4000132.3
B60: └ 2-4-4 Community Management | D60: =SUM(J60:AB60) -> 4772335.5 | G60: 299997 | H60: 4194472.1 | I60: =IF(H$68=0,0,H60/H$68) -> 0.0232978 | K60: 435604.79 | M60: 147972 | N60: 149742 | O60: 142190 | P60: 142190 | Q60: 144432 | R60: 144698.68 | S60: 245567.68 | T60: 316570.4 | U60: 325416.5 | V60: 319751.11 | W60: 318842.61 | X60: 245440 | Y60: 384208 | Z60: 328204.02 | AA60: 403642.3 | AB60: 577863.4 | BU60: =SUM(AB60:BT60) -> 577863.4 | BZ60: =+H60+AB60+AC60+AD60+AE60+AF60+AG60 -> 4772335.5
B61: └ 2-4-5 Vallas Publicitarias | D61: =SUM(J61:AB61) -> 3275050.5 | G61: 232709.5 | H61: 3042341 | I61: =IF(H$68=0,0,H61/H$68) -> 0.016898397 | J61: 559615 | K61: 130744 | L61: 130744 | M61: 130744 | N61: 130744 | O61: 109504 | P61: 109504 | Q61: 88264 | R61: 109504 | S61: 130744 | T61: 70800 | U61: 21240 | V61: 278729.5 | W61: 281966.5 | X61: 146325.5 | Y61: 190229.5 | Z61: 232709.5 | AA61: 190229.5 | AB61: 232709.5 | BU61: =SUM(AB61:BT61) -> 232709.5 | BZ61: =+H61+AB61+AC61+AD61+AE61+AF61+AG61 -> 3275050.5
B62: └ 2-4-6 Materiales POP | D62: =SUM(J62:AB62) -> 1777671.1 | H62: 1777671.1 | I62: =IF(H$68=0,0,H62/H$68) -> 0.0098739068 | J62: 32500 | L62: 4631.5 | M62: 826 | N62: 138130.34 | O62: 167145.96 | P62: 537522.12 | Q62: 124132 | T62: 216162.42 | U62: 12555.41 | V62: 208600 | Z62: 335465.36 | BU62: =SUM(AB62:BT62) -> 0 | BZ62: =+H62+AB62+AC62+AD62+AE62+AF62+AG62 -> 1777671.1
B63: └ 2-4-7 Feria y Eventos Publicitarios | D63: =SUM(J63:AB63) -> 3633762.2 | G63: 239122.07 | H63: 2447929.6 | I63: =IF(H$68=0,0,H63/H$68) -> 0.013596794 | M63: 411466 | N63: -18821 | T63: 445521.5 | U63: 513473.93 | V63: 1287.19 | Y63: 395890 | AA63: 699111.98 | AB63: 1185832.6 | BU63: =SUM(AB63:BT63) -> 1185832.6 | BZ63: =+H63+AB63+AC63+AD63+AE63+AF63+AG63 -> 3633762.2
B64: └ 2-4-8 Programa de Referidos | D64: =SUM(J64:AB64) -> 486136.61 | H64: 486136.61 | I64: =IF(H$68=0,0,H64/H$68) -> 0.0027002 | X64: 376927.61 | Z64: 109209 | BU64: =SUM(AB64:BT64) -> 0 | BZ64: =+H64+AB64+AC64+AD64+AE64+AF64+AG64 -> 486136.61
B65: 2-5 Post Ventas | C65: 19863403 | D65: =SUM(J65:AB65) -> 0 | E65: =+C65-D65 -> 19863403 | H65: =+D65+F65-G65 -> 0 | I65: =IF(H$68=0,0,H65/H$68) -> 0 | AO65: 541413 | AP65: 541413 | AQ65: 541413 | AR65: 541413 | AS65: 541413 | AT65: 541413 | AU65: 541413 | AV65: 541413 | AW65: 541413 | AX65: 541413 | AY65: 541413 | AZ65: 541413 | BA65: 541413 | BB65: 541413 | BC65: 541413 | BD65: 541413 | BE65: 541413 | BF65: 541413 | BG65: 541413 | BH65: 541413 | BI65: 541413 | BJ65: 541413 | BK65: 541413 | BL65: 541413 | BM65: 541413 | BN65: 541413 | BO65: 541413 | BP65: 541413 | BQ65: 541413 | BR65: 541413 | BS65: 541413 | BT65: 541413 | BU65: =SUM(AB65:BT65) -> 17325216 | BZ65: =+H65+AB65+AC65+AD65+AE65+AF65+AG65 -> 0
B66: └ 2-5-1 Administración Condominio | D66: =SUM(J66:AB66) -> 0 | I66: =IF(C66=0,0,D66/C66) -> 0 | BZ66: =+H66+AB66+AC66+AD66+AE66+AF66+AG66 -> 0
B67: └ 2-5-2 Gastos Operativos Post-Venta | D67: =SUM(J67:AB67) -> 0 | I67: =IF(C67=0,0,D67/C67) -> 0 | BZ67: =+H67+AB67+AC67+AD67+AE67+AF67+AG67 -> 0
B68: Subtotal GASTOS OPERATIVOS | C68: =+C47+C48+C53+C56+C65 -> 6.8610072e+08 | D68: =+D47+D48+D53+D56+D65 -> 1.8540095e+08 | E68: =+E47+E48+E53+E56+E65 -> 5.0069976e+08 | G68: 5363696.4 | H68: =+H47+H48+H53+H56+H65 -> 1.8003726e+08 | I68: =IF(H$75=0,0,H68/H$75) -> 0.25610994 | J68: =+J47+J48+J53+J56+J65 -> 12160286 | K68: =+K47+K48+K53+K56+K65 -> 959353.55 | L68: =+L47+L48+L53+L56+L65 -> 2613690.2 | M68: =+M47+M48+M53+M56+M65 -> 1735659.4 | N68: =+N47+N48+N53+N56+N65 -> 4178939.2 | O68: =+O47+O48+O53+O56+O65 -> 4059539.3 | P68: =+P47+P48+P53+P56+P65 -> 5121829.6 | Q68: =+Q47+Q48+Q53+Q56+Q65 -> 13348070 | ... BZ68: =+BZ47+BZ48+BZ53+BZ56+BZ65 -> 2.7375455e+08
B69: ◆ OTROS GASTOS
B70: 3-1 Permisos y Preliminares | C70: 30500000 | D70: =SUM(J70:AB70) -> 23156922 | E70: =+C70-D70 -> 7343078.1 | F70: 1691904.6 | G70: 311364.64 | H70: =+D70+F70-G70 -> 24537462 | I70: =IF(H$73=0,0,H70/H$73) -> 0.58466385 | J70: 12715384 | M70: 128745.38 | N70: 552632.58 | O70: 120006 | P70: 535636 | Q70: 3007800 | R70: 223322.53 | S70: -405849.76 | T70: 842419.7 | U70: 339222.22 | V70: 2552697.4 | W70: 517341.31 | Y70: 347884.07 | Z70: 1360886.6 | AA70: 190305.57 | AB70: =118333.33+10154.66 -> 128487.99 | AC70: 800000 | AE70: 400000 | BU70: =SUM(AB70:BT70) -> 1328488 | BZ70: =+H70+AB70+AC70+AD70+AE70+AF70+AG70 -> 25865950
B71: 3-2 Imprevistos | C71: 19863403 | D71: =SUM(J71:AB71) -> 0 | E71: =+C71-D71 -> 19863403 | H71: =+D71+F71-G71 -> 0 | I71: =IF(H$73=0,0,H71/H$73) -> 0 | AO71: 541413 | AP71: 541413 | AQ71: 541413 | AR71: 541413 | AS71: 541413 | AT71: 541413 | AU71: 541413 | AV71: 541413 | AW71: 541413 | AX71: 541413 | AY71: 541413 | AZ71: 541413 | BA71: 541413 | BB71: 541413 | BC71: 541413 | BD71: 541413 | BE71: 541413 | BF71: 541413 | BG71: 541413 | BH71: 541413 | BI71: 541413 | BJ71: 541413 | BK71: 541413 | BL71: 541413 | BM71: 541413 | BN71: 541413 | BO71: 541413 | BP71: 541413 | BQ71: 541413 | BR71: 541413 | BS71: 541413 | BT71: 541413 | BU71: =SUM(AB71:BT71) -> 17325216 | BZ71: =+H71+AB71+AC71+AD71+AE71+AF71+AG71 -> 0
B72: 3-3 Gastos Financieros | C72: 2.3273921e+08 | D72: =SUM(J72:AB72) -> 17431033 | E72: =+C72-D72 -> 2.1530818e+08 | H72: =+D72+F72-G72 -> 17431033 | I72: =IF(H$73=0,0,H72/H$73) -> 0.41533615 | Q72: 1169797.6 | R72: -1169797.6 | U72: 5900 | V72: 4408448 | Y72: 8473629.7 | Z72: -9722.22 | AA72: 2750000 | AB72: 1802777.8 | AC72: =+'Intereses 06-26'!Z39 -> 2447916.7 | AD72: =+'Intereses 06-26'!AA39 -> 4937500 | AE72: =+'Intereses 06-26'!AB39 -> 6937500 | AF72: =+'Intereses 06-26'!AC39 -> 3718750 | AG72: =+'Intereses 06-26'!AD39 -> 4989583.3 | AH72: 4403333.3 | AI72: 5623333.3 | AJ72: 5623333.3 | AK72: 6843333.3 | AL72: 7093333.3 | AM72: 8313333.3 | AN72: 7946925.2 | AO72: 7810515.6 | AP72: 7567852 | AQ72: 7093109.6 | AR72: 6537145.7 | AS72: 6661326.5 | AT72: 5761400.1 | AU72: 5179332.1 | AV72: 3849727.2 | AW72: 3531419.4 | AX72: 3531419.4 | AY72: 3449257.7 | AZ72: 2947499.6 | BA72: 2527292.5 | BB72: 2159596.3 | BC72: 1799282.9 | BD72: 1555421.2 | BU72: =SUM(AB72:BT72) -> 1.4264255e+08 | BZ72: =+H72+AB72+AC72+AD72+AE72+AF72+AG72 -> 42265061
B73: Subtotal OTROS GASTOS | C73: =+C70+C71+C72 -> 2.8310261e+08 | D73: =+D70+D71+D72 -> 40587955 | E73: =+E70+E71+E72 -> 2.4251466e+08 | F73: 1691904.6 | G73: 311364.64 | H73: =+H70+H71+H72 -> 41968495 | I73: =IF(H$75=0,0,H73/H$75) -> 0.059701803 | J73: =+J70+J71+J72 -> 12715384 | K73: =+K70+K71+K72 -> 0 | L73: =+L70+L71+L72 -> 0 | M73: =+M70+M71+M72 -> 128745.38 | N73: =+N70+N71+N72 -> 552632.58 | O73: =+O70+O71+O72 -> 120006 | P73: =+P70+P71+P72 -> 535636 | Q73: =+Q70+Q71+Q72 -> 4177597.5 | ... AA73: =+AA70+AA71+AA72 -> 2940305.6 | AB73: =SUM(AB70:AB72) -> 1931265.8 | AC73: =SUM(AC70:AC72) -> 3247916.7 | AD73: =SUM(AD70:AD72) -> 4937500 | AE73: =SUM(AE70:AE72) -> 7337500 | AF73: =SUM(AF70:AF72) -> 3718750 | AG73: =SUM(AG70:AG72) -> 4989583.3 | AH73: =SUM(AH70:AH72) -> 4403333.3 | AI73: =SUM(AI70:AI72) -> 5623333.3 | ... BZ73: =SUM(BZ70:BZ72) -> 68131011
B75: TOTALES GENERALES RD$ | C75: =+C45+C68+C73 -> 3.5912806e+09 | D75: =+D45+D68+D73 -> 7.1232616e+08 | E75: =+E45+E68+E73 -> 2.8789544e+09 | F75: 9210448.9 | G75: 18627535 | H75: =+H45+H68+H73 -> 7.0296864e+08 | I75: =+I45+I68+I73 -> 1 | J75: =+J45+J68+J73 -> 1.5089127e+08 | K75: =+K45+K68+K73 -> 3157503.3 | L75: =+L45+L68+L73 -> 2613690.2 | M75: =+M45+M68+M73 -> 2895724.8 | N75: =+N45+N68+N73 -> 7649161.8 | O75: =+O45+O68+O73 -> 6705088.7 | ... BZ75: =+BZ45+BZ68+BZ73 -> 1.2963695e+09
B76: TOTALES GENERALES ACUMULADOS RD$ | C76: =+C46+C69+C74 -> 0 | D76: =+D46+D69+D74 -> 0 | E76: =+E46+E69+E74 -> 0 | F76: =+F46+F69+F74 -> 0 | G76: =+G46+G69+G74 -> 0 | H76: =+H46+H69+H74 -> 0 | I76: =IF(C76=0,0,D76/C76) -> 0 | J76: =+J75 -> 1.5089127e+08 | K76: =+J76+K75 -> 1.5404878e+08 | L76: =+K76+L75 -> 1.5666247e+08 | M76: =+L76+M75 -> 1.5955819e+08 | N76: =+M76+N75 -> 1.6720735e+08 | O76: =+N76+O75 -> 1.7391244e+08 | P76: =+O76+P75 -> 1.8253669e+08 | Q76: =+P76+Q75 -> 2.2086389e+08 | R76: =+Q76+R75 -> 4.1783302e+08 | ... Z76: =+Y76+Z75 -> 6.1396087e+08 | AA76: =+Z76+AA75-G75+F75 -> 6.5391017e+08 | AB76: =+AA76+AB75 -> 7.0290908e+08 | AC76: =+AB76+AC75 -> 8.4660971e+08 | AD76: =+AC76+AD75 -> 9.4853625e+08 | AE76: =+AD76+AE75 -> 1.054591e+09 | AF76: =+AE76+AF75 -> 1.1512932e+09 | AG76: =+AF76+AG75 -> 1.247311e+09 | AH76: =+AG76+AH75 -> 1.3353054e+09 | AI76: =+AH76+AI75 -> 1.4483072e+09 | ... BY76: =+BX76+BY75 -> 6.1887167e+09 | BZ76: =+BZ75 -> 1.2963695e+09
B77: Gastos Bancarios | H77: =-273569.56-484512.22-2128.68 -> -760210.46
B78: Retenciones Varias | H78: =3942456+431409+56826 -> 4430691
B79: Fondo Rotatorio | H79: 2021249.3
B80: Desistimientos por pagar | H80: 59566.36
B81: Otras cuentas por pagar | H81: =SUM(H77:H80) -> 5751296.2
B82: NETO (Ingresos − Costos) RD$ | H82: =+AB83 -> 49199807 | AB82: =+AB24-AB75 -> 9327295 | AC82: =+AC24-AC75 -> -25700628 | AD82: =+AD24-AD75 -> 16073455 | AE82: =+AE24-AE75 -> -98054700 | AF82: =+AF24-AF75 -> -78702273 | AG82: =+AG24-AG75 -> 81982219 | AH82: =+AH24-AH75 -> -69994391 | AI82: =+AI24-AI75 -> -1.1300181e+08 | ... BT82: =+BT24-BT75 -> -3565264 | BU82: =+BU25-BU76 -> -4.9843591e+09 | BV82: =+BV25-BV76 -> -6.1887167e+09 | BW82: =+BW25-BW76 -> -6.1887167e+09 | BX82: =+BX25-BX76 -> -6.1887167e+09 | BY82: =+BY25-BY76 -> -6.1887167e+09 | BZ82: =+BZ25-BZ76 -> -51685688
B83: NETO (Ingresos − Costos) RD$ Acumulados | AB83: =+AB25-AB76+H81 -> 49199807 | AC83: =+AB83+AC82 -> 23499178 | AD83: =+AC83+AD82 -> 39572633 | AE83: =+AD83+AE82 -> -58482067 | AF83: =+AE83+AF82 -> -1.3718434e+08 | AG83: =+AF83+AG82 -> -55202121 | AH83: =+AG83+AH82 -> -1.2519651e+08 | AI83: =+AH83+AI82 -> -2.3819832e+08 | AJ83: =+AI83+AJ82 -> -3.9906743e+08 | ... BT83: =+BS83+BT82 -> -2.2112045e+09

Sheet 2. COSTOS JUN-26
B1: FIDEICOMISO ARAYA — COSTOS DEL PROYECTO | Jun 2026 | Valores en RD$
B2: Acumulado May-26 + Ejecutado Jun-26 = Acumulado Jun-26
B4: AUXILIAR / CENTRO DE COSTO | C4: ACUM. MAY-26 | D4: JUN-26 (Mes) | E4: ACUM. JUN-26 | F4: % VAR. MES
B5: ◆ CONSTRUCCIÓN
B6: 1-1-1 Terreno | C6: 2.6677371e+08 | E6: 2.6677371e+08
B7: 1-2-1 Diseno y Proyecto | C7: 24159807 | E7: 24159807
B8: 1-4-1 Urbanismo | C8: 45301558 | D8: 5475884.7 | E8: 50777443 | F8: =IF(C8=0,"",D8/C8) -> 0.1208763
B9: 1-5-1 Edificaciones | C9: 67665569 | D9: 23348966 | E9: 91014535 | F9: =IF(C9=0,"",D9/C9) -> 0.3450642
B10: 1-6-1 Gerencia de Construccion | C10: 37971390 | D10: 2275880.4 | E10: 40247270 | F10: =IF(C10=0,"",D10/C10) -> 0.059936714
B11: 1-7-1 Gastos Personal Administrativo de Obra | C11: 260750 | D11: 52150 | E11: 312900 | F11: =IF(C11=0,"",D11/C11) -> 0.2
B12: 1-7-2 Gastos Operativos Generales | C12: 569970.93 | D12: 54100.85 | E12: 624071.78 | F12: =IF(C12=0,"",D12/C12) -> 0.094918613
B13: 1-7-3 Equipos y Transporte | C13: 3363369 | D13: 427200 | E13: 3790569 | F13: =IF(C13=0,"",D13/C13) -> 0.1270155
B14: 1-7-4 Vigilancia | C14: 1023673.6 | D14: 90246.4 | E14: 1113920 | F14: =IF(C14=0,"",D14/C14) -> 0.088159351
B15: 1-7-5 Poliza TRC | C15: 1387882 | E15: 1387882
B16: 1-7-6 Campamento | C16: 964002.99 | D16: 101500 | E16: 1065503 | F16: =IF(C16=0,"",D16/C16) -> 0.10529013
B17: 1-9-1 Inspeccion Tecnica | C17: 4562678.7 | D17: 506964.3 | E17: 5069643 | F17: =IF(C17=0,"",D17/C17) -> 0.11111111
B18: Subtotal CONSTRUCCIÓN | C18: =SUM(C6:C17) -> 4.5400436e+08 | D18: =SUM(D6:D17) -> 32332892 | E18: =SUM(E6:E17) -> 4.8633725e+08
B19: ◆ GASTOS OPERATIVOS
B20: 2-1-1 Gerencia de la Promotora | C20: 25052779 | D20: 1783003.6 | E20: 26835783 | F20: =IF(C20=0,"",D20/C20) -> 0.071169892
B21: 2-2-1 Comisiones por Venta | C21: 79374170 | D21: 7031404.5 | E21: 86405575 | F21: =IF(C21=0,"",D21/C21) -> 0.08858555
B22: 2-2-2 Administracion de la Venta | C22: 10782128 | D22: 757185.94 | E22: 11539314 | F22: =IF(C22=0,"",D22/C22) -> 0.070226017
B23: 2-2-3 Equipo de Trabajo Oficina de Ventas | C23: 16260807 | D23: 1598169.6 | E23: 17858976 | F23: =IF(C23=0,"",D23/C23) -> 0.098283534
B24: 2-2-4 Gastos Operativos Oficina de ventas | C24: 1312443.5 | D24: 132010.93 | E24: 1444454.4 | F24: =IF(C24=0,"",D24/C24) -> 0.10058409
B25: 2-3-1 Adm General de la Fiduciaria (Estruc. Post y Prev. Adm. Garantia) | C25: 4247764.4 | D25: 774773.75 | E25: 5022538.1 | F25: =IF(C25=0,"",D25/C25) -> 0.18239565
B26: 2-3-2 Debida Diligencia/Desvinculacion-Fiduciaria | C26: 1666620.4 | D26: 293802.58 | E26: 1960423 | F26: =IF(C26=0,"",D26/C26) -> 0.17628644
B27: 2-4-1 Apartamento Modelo (Equipamiento)/Show Room | C27: 5143605.2 | E27: 5143605.2
B28: 2-4-2 Inversion Inicial Promocion y Mercadeo | C28: 11245197 | E28: 11245197
B29: 2-4-3 Medios Digitales (Campana y Redes Sociales) | C29: 3632136.3 | D29: 367996.01 | E29: 4000132.3 | F29: =IF(C29=0,"",D29/C29) -> 0.10131669
B30: 2-4-4 Community Management | C30: 4194472.1 | D30: 577863.4 | E30: 4772335.5 | F30: =IF(C30=0,"",D30/C30) -> 0.13776785
B31: 2-4-5 Vallas Publicitarias | C31: 3042341 | D31: 232709.5 | E31: 3275050.5 | F31: =IF(C31=0,"",D31/C31) -> 0.076490275
B32: 2-4-6 Materiales POP | C32: 1777671.1 | E32: 1777671.1
B33: 2-4-7 Feria y Eventos Publicitarios | C33: 2447929.6 | D33: 1185832.6 | E33: 3633762.2 | F33: =IF(C33=0,"",D33/C33) -> 0.48442268
B34: 2-4-8 Programa de Referidos | C34: 486136.61 | E34: 486136.61
B35: Subtotal GASTOS OPERATIVOS | C35: =SUM(C20:C34) -> 1.706662e+08 | D35: =SUM(D20:D34) -> 14734752 | E35: =SUM(E20:E34) -> 1.8540095e+08
B36: ◆ OTROS GASTOS
B37: 3-1-1 Permisos Legales y Preliminares | C37: 23038589 | D37: =118333.33+10154.66 -> 128487.99 | E37: 23156922 | F37: =IF(C37=0,"",D37/C37) -> 0.0055770773
B38: 3-3-1 Interes Prestamo | C38: 15628255 | D38: 1802777.8 | E38: 17431033 | F38: =IF(C38=0,"",D38/C38) -> 0.11535374
B39: Subtotal OTROS GASTOS | C39: =SUM(C37:C38) -> 38666844 | D39: =SUM(D37:D38) -> 1931265.8 | E39: =SUM(E37:E38) -> 40587955
B40: TOTAL GENERAL | C40: =+C18+C35+C39 -> 6.6333741e+08 | D40: =+D18+D35+D39 -> 48998911 | E40: =+E18+E35+E39 -> 7.1232616e+08

Sheet 4. CUENTAS POR PAGAR
B1: CUENTAS POR PAGAR — CORTE 30 DE JUNIO 2026 | Valores en RD$
E2: Corriente | F2: < 1 Mes | G2: 1 Mes | H2: 2+ Meses | I2: TOTAL
E3: 11183495 | F3: 7140113 | G3: 147770.75 | H3: 126110.5 | I3: 18597490
E4: =E3/$I3 -> 0.60134435 | F4: =F3/$I3 -> 0.38392886 | G4: =G3/I3 -> 0.0079457364 | H4: =H3/$I3 -> 0.0067810496
B5: AUXILIAR / PROVEEDOR | C5: REFERENCIA | D5: VENCE | E5: CORRIENTE | F5: < 1 MES | G5: 1 MES | H5: 2 MESES | I5: 3 MESES | J5: TOTAL
B6: ▸ 1-4-1 Urbanismo | E6: 232477.36 | F6: 2162882.7 | G6: 14180 | J6: 2409540.1
B7: ALMACENES UNIDOS SAS | C7: E310002285181 | D7: 22/05/26 | G7: 14180 | J7: 14180
B8: TALLER INDUSTRIAL J NIVAR SRL | C8: B0100000004 | D8: 20/06/26 | F8: 14580 | J8: 14580
B9: BELLON SAS | C9: E310000989574 | D9: 13/07/26 | E9: 4120 | J9: 4120
B10: BELLON SAS | C10: E310000989869 | D10: 15/07/26 | E10: 14500.5 | J10: 14500.5
B11: CONSTRUCTORA FELIX CAMPOS SRL | C11: B0100000111 | D11: 26/06/26 | F11: 173355.6 | J11: 173355.6
B12: CONSTRUCTORA FELIX CAMPOS SRL | C12: B0100000113 | D12: 26/06/26 | F12: 111980 | J12: 111980
B13: INVERSIONES ROMUR SRL | C13: B0100000161 | D13: 26/06/26 | F13: 1862967.1 | J13: 1862967.1
B14: BLUE WAVE AGREGADOS SRL | C14: E310000000590 | D14: 02/07/26 | E14: 58796 | J14: 58796
B15: FERRETERIA DETALLISTA SA | C15: E310000273424 | D15: 08/07/26 | E15: 485 | J15: 485
B16: FERRETERIA DETALLISTA SA | C16: E310000273448 | D16: 09/07/26 | E16: 24705 | J16: 24705
B17: FERRETERIA DETALLISTA SA | C17: E310000273450 | D17: 10/07/26 | E17: 8652.51 | J17: 8652.51
B18: BLUE WAVE AGREGADOS SRL | C18: E310000000632 | D18: 15/07/26 | E18: 48833.31 | J18: 48833.31
B19: BELLON SAS | C19: E310000991806 | D19: 18/07/26 | E19: 35 | J19: 35
B20: BELLON SAS | C20: E310000991646 | D20: 17/07/26 | E20: 13861 | J20: 13861
B21: SUPLIDORES ELECTRICOS DEL CARI | C21: E310000026687 | D21: 24/07/26 | E21: 40324.68 | J21: 40324.68
B22: BELLON SAS | C22: E310001389213 | D22: 26/07/26 | E22: 17834 | J22: 17834
B23: BELLON SAS | C23: E310001390031 | D23: 29/07/26 | E23: 330.36 | J23: 330.36
B24: ▸ 1-5-1 Edificaciones | E24: 7965249.4 | F24: 1114061.9 | I24: 49.4 | J24: 9079360.7
B25: BLUE WAVE AGREGADOS SRL | C25: E310000000590 | D25: 02/07/26 | E25: 2070805.5 | J25: 2070805.5
B26: FERRETERIA DETALLISTA SA | C26: E310000273424 | D26: 08/07/26 | E26: 5045.3 | J26: 5045.3
B27: FERRETERIA DETALLISTA SA | C27: E310000273448 | D27: 09/07/26 | E27: 1730 | J27: 1730
B28: FERRETERIA DETALLISTA SA | C28: E310000273450 | D28: 10/07/26 | E28: 599.44 | J28: 599.44
B29: BLUE WAVE AGREGADOS SRL | C29: E310000000632 | D29: 15/07/26 | E29: 588820.28 | J29: 588820.28
B30: BELLON SAS | C30: E310000991806 | D30: 18/07/26 | E30: 396019.76 | J30: 396019.76
B31: BELLON SAS | C31: E310000991646 | D31: 17/07/26 | E31: 62403.76 | J31: 62403.76
B32: SUPLIDORES ELECTRICOS DEL CARI | C32: E310000026687 | D32: 24/07/26 | E32: 25488 | J32: 25488
B33: BELLON SAS | C33: E310001389213 | D33: 26/07/26 | E33: 5434.49 | J33: 5434.49
B34: BELLON SAS | C34: E310001390031 | D34: 29/07/26 | E34: 3696 | J34: 3696
B35: BELLON SAS | C35: E310000989046 | D35: 11/07/26 | E35: 15289 | J35: 15289
B36: RODFOR TEAM S R L | C36: E310000013333 | D36: 27/03/26 | I36: 49.4 | J36: 49.4
B37: FERRETERIA DETALLISTA SA | C37: E310000273292 | D37: 25/06/26 | F37: 47200 | J37: 47200
B38: FERRETERIA DETALLISTA SA | C38: E310000373345 | D38: 28/06/26 | F38: 16249.17 | J38: 16249.17
B39: FERRETERIA DETALLISTA SA | C39: E310000273381 | D39: 03/07/26 | E39: 37500.4 | J39: 37500.4
B40: FERRETERIA DETALLISTA SA | C40: E310000273379 | D40: 03/07/26 | E40: 86580.05 | J40: 86580.05
B41: TYRVAL DOMINICANA SRL | C41: B0100000213 | D41: 03/07/26 | E41: 287209.23 | J41: 287209.23
B42: BLUE WAVE AGREGADOS SRL | C42: E310000000601 | D42: 05/07/26 | E42: 542620.88 | J42: 542620.88
B43: BLUE WAVE AGREGADOS SRL | C43: E310000000604 | D43: 05/07/26 | E43: 325572.53 | J43: 325572.53
B44: BELLON SAS | C44: E310000987739 | D44: 09/07/26 | E44: 22761 | J44: 22761
B45: FERRETERIA DETALLISTA SA | C45: E310000273441 | D45: 09/07/26 | E45: 19300.5 | J45: 19300.5
B46: BLUE WAVE AGREGADOS SRL | C46: E310000000623 | D46: 10/07/26 | E46: 570931.53 | J46: 570931.53
B47: BLUE WAVE AGREGADOS SRL | C47: E310000000622 | D47: 10/07/26 | E47: 326563.11 | J47: 326563.11
B48: ENCOFRADOS VERSATEC SRL | C48: B0100000422 | D48: 11/06/26 | F48: 125606.28 | J48: 125606.28
B49: ENCOFRADOS VERSATEC SRL | C49: B0100000424 | D49: 11/06/26 | F49: 33317.35 | J49: 33317.35
B50: BELLON SAS | C50: E310000989651 | D50: 13/07/26 | E50: 122940 | J50: 122940
B51: ENCOFRADOS VERSATEC SRL | C51: B0100000427 | D51: 13/06/26 | F51: 32295.88 | J51: 32295.88
B52: ENCOFRADOS VERSATEC SRL | C52: B0100000428 | D52: 13/06/26 | F52: 50133.96 | J52: 50133.96
B53: FERRETERIA DETALLISTA SA | C53: E310000273508 | D53: 13/07/26 | E53: 7249.92 | J53: 7249.92
B54: BLUE WAVE AGREGADOS SRL | C54: E310000000636 | D54: 15/07/26 | E54: 61339.75 | J54: 61339.75
B55: FERRETERIA DETALLISTA SA | C55: E310000273514 | D55: 15/07/26 | E55: 64621.14 | J55: 64621.14
B56: IBEROCOMERCIAL DEL CARIBE S. A | C56: E310000039186 | D56: 16/07/26 | E56: 2125.07 | J56: 2125.07
B57: TYRVAL DOMINICANA SRL | C57: B0100000214 | D57: 17/07/26 | E57: 152775.81 | J57: 152775.81
B58: BELLON SAS | C58: E310000991649 | D58: 17/07/26 | E58: 517.8 | J58: 517.8
B59: GERDAU METALDOM SA | C59: E310000184761 | D59: 17/07/26 | E59: 262723.22 | J59: 262723.22
B60: BELLON SAS | C60: E310000992369 | D60: 19/07/26 | E60: 46824 | J60: 46824
B61: PREVENTIONART J&C SRL | C61: E310000000038 | D61: 30/06/26 | F61: 129800 | J61: 129800
B62: BLUE WAVE AGREGADOS SRL | C62: E310000000646 | D62: 22/07/26 | E62: 194443.61 | J62: 194443.61
B63: BLUE WAVE AGREGADOS SRL | C63: E310000000645 | D63: 22/07/26 | E63: 577531.74 | J63: 577531.74
B64: KINNOX S A | C64: E310000016534 | D64: 07/07/26 | E64: 715000 | J64: 715000
B65: RODFOR TEAM S R L | C65: E310000017814 | D65: 22/07/26 | E65: 146911.49 | J65: 146911.49
B66: TECNICA MMHB SRL | C66: E310000000004 | D66: 26/06/26 | F66: 645239.26 | J66: 645239.26
B67: TORRANCE DEVELOPMENT GROUP SRL | C67: B0100000651 | D67: 23/07/26 | E67: 124100 | J67: 124100
B68: BELLON SAS | C68: E310000994496 | D68: 24/07/26 | E68: 43560 | J68: 43560
B69: EMPRESA GALACTICA SRL | C69: E310000003525 | D69: 26/06/26 | F69: 34220 | J69: 34220
B70: CONTE DIRECTO INTERNACIONAL M | C70: B0100005325 | D70: 10/07/26 | E70: 33100 | J70: 33100
B71: BELLON SAS | C71: E310001390422 | D71: 30/07/26 | E71: 15115 | J71: 15115
B72: ▸ 1-7 Indirectos (grupo) | F72: 806796.06 | J72: 806796.06
B73: TECNICA MMHB SRL | C73: E310000000003 | D73: 12/06/26 | F73: 806796.06 | J73: 806796.06
B74: ▸ 1-7-4 Vigilancia | E74: 90246.4 | J74: 90246.4
B75: SEGURIDAD INVESTIGACIONES Y PR | C75: B0100006074 | D75: 30/07/26 | E75: 90246.4 | J75: 90246.4
B76: ▸ 1-9-1 Inspección Técnica | F76: 506964.3 | J76: 506964.3
B77: ING OMAR CORDERO & ASOCIADOS S | C77: E310000000007 | D77: 30/06/26 | F77: 506964.3 | J77: 506964.3
B78: ▸ 2-2-1 Comisiones Venta | E78: 2351087.4 | F78: 1660135 | J78: 4011222.4
B79: KISWER INVESTMENTS SRL | C79: B0100001086 | D79: 03/07/26 | E79: 704746.92 | J79: 704746.92
B80: INVERSIONES SERACINI SRL | C80: E310000000102 | D80: 26/06/26 | F80: 581828.5 | J80: 581828.5
B81: PPCRE PARADISE PUNTA CANA REAL | C81: B0100000253 | D81: 26/06/26 | F81: 468623.25 | J81: 468623.25
B82: PPCRE PARADISE PUNTA CANA REAL | C82: B0100000254 | D82: 26/06/26 | F82: 609683.23 | J82: 609683.23
B83: KISWER INVESTMENTS SRL | C83: B0100001111 | D83: 03/07/26 | E83: 628777.8 | J83: 628777.8
B84: NAVIA REAL ESTATE SRL | C84: B0100000038 | D84: 10/07/26 | E84: 530812.67 | J84: 530812.67
B85: COACHING 360 SRL REMAX | C85: B0100000809 | D85: 10/07/26 | E85: 486750 | J85: 486750
B86: ▸ 2-2-4 Gastos Oficina Ventas | E86: 82528.34 | F86: 119716.19 | J86: 202244.53
B87: SEGURIDAD INVESTIGACIONES Y PR | C87: B0100006021 | D87: 30/06/26 | F87: 70233.6 | J87: 70233.6
B88: ENCOFRADOS VERSATEC SRL | C88: B0100000423 | D88: 11/06/26 | F88: 26928.31 | J88: 26928.31
B89: ENCOFRADOS VERSATEC SRL | C89: B0100000426 | D89: 13/06/26 | F89: 22554.28 | J89: 22554.28
B90: COSFREYCAM TROPICAL S A S | C90: B0100002968 | D90: 16/07/26 | E90: 14560.34 | J90: 14560.34
B91: SEGURIDAD INVESTIGACIONES Y PR | C91: B0100006080 | D91: 30/07/26 | E91: 67968 | J91: 67968
B92: ▸ 2-3-2 Debida Diligencia | F92: 293802.58 | J92: 293802.58
B93: FIDUCIARIA UNIVERSAL S A | C93: E310000001063 | D93: 26/06/26 | F93: 293802.58 | J93: 293802.58
B94: ▸ 2-4-2 Inversión Inicial | J94: -14760.54
B95: LMCAD ESTUDIO DE ANIMACION SRL | C95: nan | D95: 17/10/25 | J95: -14760.54
B96: ▸ 2-4-3 Medios Digitales | F96: 99358.92 | J96: 99358.92
B97: REDES SOCIALES -FB-GOOGLE- | C97: REDES SOCIALES MAY-26 | D97: 18/06/26 | F97: 99358.92 | J97: 99358.92
B98: ▸ 2-4-4 Community Mgmt | E98: 229197 | F98: 70800 | J98: 299997
B99: JONATHAN JOHANSER DIAZ SOTO - | C99: B0100000107 | D99: 30/06/26 | F99: 70800 | J99: 70800
B100: CANVAS DESIGN & MEDIA GROUP SR | C100: E310000000179 | D100: 02/07/26 | E100: 94400 | J100: 94400
...

Sheet Intereses 06-26
A3: PRESTAMOS PARA ARAYA
A6: Empresa | B6: Banco | C6: Desembolsos | D6: Amortización | E6: Capital actual | F6: Tasa | G6: Intereses mensual | H6: Fecha | I6: Transf. Araya | J6: Primer mes | K6: Dias | L6: 45748 | M6: 45778 | N6: 45809 | O6: 45839 | P6: 45870 | Q6: 45901 | R6: 45931 | S6: 45962 | T6: 45992 | U6: Acum a Dic-25 | V6: 46023 | W6: 46054 | X6: 46082 | Y6: 46143 | Z6: 46204 | AA6: 46235 | AB6: 46266 | AC6: 46296 | AD6: 46327 | AE6: 46357 | AF6: A pagar | AG6: Vencimiento de Facilidad
A7: Grupo Bak | B7: ALNAP | C7: 15000000 | D7: 15000000 | E7: 0 | F7: 0.1595 | G7: =+E7*F7/360*30 -> 0 | H7: 45757 | I7: 45761 | J7: 45777 | K7: =+J7-I7 -> 16 | L7: =+E7*F7/360*K7 -> 0 | M7: =+G7 -> 0 | N7: =+M7 -> 0 | O7: =+N7 -> 0 | P7: =+O7 -> 0 | Q7: =+P7 -> 0 | R7: =+Q7 -> 0 | S7: 199375 | T7: =((+(E7*F7)/12)/30)*22 -> 0 | U7: =SUM(L7:T7) -> 199375 | AF7: =SUM(U7:X7) -> 199375 | AG7: 45939
A8: Grupo Bak | B8: ALNAP | C8: 7200000 | D8: 7200000 | E8: 0 | F8: 0.1595 | G8: =+E8*F8/360*30 -> 0 | H8: 45792 | I8: 45792 | J8: 45808 | K8: =+J8-I8 -> 16 | M8: =+E8*F8/360*K8 -> 0 | N8: =+G8 -> 0 | O8: =+G8 -> 0 | P8: =+G8 -> 0 | Q8: =+P8 -> 0 | R8: =+Q8 -> 0 | S8: 95700 | T8: =((+(E8*F8)/12)/30)*22 -> 0 | U8: =SUM(L8:T8) -> 95700 | AF8: =SUM(U8:X8) -> 95700 | AG8: 45939 | AJ8: =250-85 -> 165
A9: Grupo Bak | B9: ALNAP | C9: 12000000 | D9: 12000000 | E9: 0 | F9: 0.1595 | G9: =+E9*F9/360*30 -> 0 | H9: 45820 | I9: 45820 | J9: 45838 | K9: =+J9-I9 -> 18 | N9: =+E9*F9/360*K9 -> 0 | O9: =+E9*F9/360*31 -> 0 | P9: =+O9 -> 0 | Q9: =+P9 -> 0 | R9: =+Q9 -> 0 | S9: 164816.67 | T9: =((+(E9*F9)/12)/30)*22 -> 0 | U9: =SUM(L9:T9) -> 164816.67 | AF9: =SUM(U9:X9) -> 164816.67 | AG9: 45939 | AJ9: =320-160 -> 160
A10: Grupo Bak | B10: Optima | C10: =11000000 -> 11000000 | D10: 11000000 | E10: 0 | F10: 0.19 | G10: =+E10*F10/360*30 -> 0 | H10: 45847 | I10: 45854 | J10: 45869 | K10: =+J10-I10 -> 15 | O10: 87083.33 | P10: 174166.67 | Q10: 174166.67 | R10: =((11000000*19%)/360)*7+((6000000*19%)/360)*23 -> 113472.22 | S10: =+E10*F10/12 -> 0 | T10: =((+(E10*F10)/12)/30)*22 -> 0 | U10: =SUM(L10:T10) -> 548888.89 | AF10: =SUM(U10:X10) -> 548888.89 | AG10: 45923 | AJ10: =250-85 -> 165
A11: Grupo Bak | B11: Optima | C11: 2815000 | D11: 2815000 | E11: 0 | F11: 0.19 | G11: =+E11*F11/360*30 -> 0 | H11: 45847 | I11: 45862 | J11: 45869 | K11: =+J11-I11 -> 7 | O11: =+E11*F11/360*K11 -> 0 | P11: =+G11 -> 0 | Q11: =+P11 -> 0 | R11: =+Q11 -> 0 | S11: 44570.833 | T11: =((+(E11*F11)/12)/30)*22 -> 0 | U11: =SUM(L11:T11) -> 44570.833 | AF11: =SUM(U11:X11) -> 44570.833 | AG11: 45923
A12: Grupo Bak | B12: Optima | C12: 1185000 | D12: 1185000 | E12: 0 | F12: 0.19 | G12: =+E12*F12/360*30 -> 0 | H12: 45847 | I12: 45862 | J12: 45869 | K12: =+J12-I12 -> 7 | O12: =+E12*F12/360*K12 -> 0 | P12: =+G12 -> 0 | Q12: =+P12 -> 0 | R12: =+Q12 -> 0 | S12: 18762.5 | T12: =((+(E12*F12)/12)/30)*22 -> 0 | U12: =SUM(L12:T12) -> 18762.5 | AF12: =SUM(U12:X12) -> 18762.5
A13: Total Grupo Bak | C13: =SUM(C7:C12) -> 49200000 | D13: =SUM(D7:D12) -> 49200000 | E13: =SUM(E7:E12) -> 0 | G13: =SUM(G7:G12) -> 0 | L13: =SUM(L7:L12) -> 0 | M13: =SUM(M7:M12) -> 0 | N13: =SUM(N7:N12) -> 0 | O13: =SUM(O7:O12) -> 87083.33 | P13: =SUM(P7:P12) -> 174166.67 | Q13: =SUM(Q7:Q12) -> 174166.67 | R13: =SUM(R7:R12) -> 113472.22 | S13: =SUM(S7:S12) -> 523225 | T13: =SUM(T7:T12) -> 0 | V13: =SUM(V7:V12) -> 0 | W13: =SUM(W7:W12) -> 0 | X13: =SUM(X7:X12) -> 0 | Y13: =SUM(Y7:Y12) -> 0 | Z13: =SUM(Z7:Z12) -> 0 | AA13: =SUM(AA7:AA12) -> 0 | AB13: =SUM(AB7:AB12) -> 0 | AC13: =SUM(AC7:AC12) -> 0 | ... AE13: =SUM(AE7:AE12) -> 0
A14: Fondo Inversión | C14: 25000000 | E14: =+C14-D14 -> 25000000 | F14: 0.18 | I14: 45905 | Q14: =(($C14*$F14)/360)*25 -> 312500 | R14: =(($C14*$F14)/360)*30 -> 375000 | S14: =(($C14*$F14)/360)*30 -> 375000 | T14: =(($C14*$F14)/360)*30 -> 375000 | U14: =SUM(Q14:T14) -> 1437500 | V14: =(($C14*$F14)/360)*31 -> 387500 | W14: =(($C14*$F14)/360)*30 -> 375000 | X14: =(($C14*$F14)/360)*5 -> 62500 | AF14: =SUM(U14:AA14) -> 2262500
A15: Fondo Inversión | C15: 30184227 | E15: =+C15-D15 -> 30184227 | F15: 0.18 | I15: 45926 | Q15: =(($C15*$F15)/360)*4 -> 60368.455 | R15: =(($C15*$F15)/360)*30 -> 452763.41 | S15: =(($C15*$F15)/360)*30 -> 452763.41 | T15: =(($C15*$F15)/360)*30 -> 452763.41 | U15: =SUM(Q15:T15) -> 1418658.7 | V15: =(($C15*$F15)/360)*31 -> 467855.52 | W15: =(($C15*$F15)/360)*30 -> 452763.41 | X15: =(($C15*$F15)/360)*21 -> 316934.39 | AF15: =SUM(U15:AA15) -> 2656212
AF16: =SUM(U16:AA16) -> 0 | AH16: Acumulado a feb-26
AF17: =SUM(U17:AA17) -> 0
A18: Fondo Inversión | C18: 22000000 | E18: =+C18-D18 -> 22000000 | F18: 0.18 | I18: 45966 | S18: =(($C18*$F18)/360)*25 -> 275000 | T18: =(($C18*$F18)/360)*30 -> 330000 | U18: =SUM(Q18:T18) -> 605000 | V18: =(($C18*$F18)/360)*31 -> 341000 | W18: =(($C18*$F18)/360)*30 -> 330000 | X18: =(($C18*$F18)/360)*21 -> 231000 | AF18: =SUM(U18:AA18) -> 1507000
A19: Fondo Inversión | C19: 22815773 | E19: =+C19-D19 -> 22815773 | F19: 0.18 | I19: 45989 | S19: =(($C19*$F19)/360)*2 -> 22815.773 | T19: =(($C19*$F19)/360)*30 -> 342236.59 | U19: =SUM(Q19:T19) -> 365052.37 | V19: =(($C19*$F19)/360)*31 -> 353644.48 | W19: =(($C19*$F19)/360)*30 -> 342236.59 | X19: =(($C19*$F19)/360)*20.712867 -> 236290.04 | AF19: =SUM(U19:AA19) -> 1297223.5
A20: Fondo Inversión | E20: =+C20-D20 -> 0 | AF20: =SUM(U20:AA20) -> 0 | AH20: Acumulado a feb-26
A21: Fondo Inversión | C21: 100000000 | E21: =+C21-D21 -> 100000000 | F21: 0.18 | I21: 46223 | Z21: =(($C21*$F21)/360)*30/30*10 -> 500000 | AA21: =(($C21*$F21)/360)*30 -> 1500000 | AB21: =(($C21*$F21)/360)*30 -> 1500000 | AC21: =(($C21*$F21)/360)*30 -> 1500000 | AF21: =SUM(Z21:AE21) -> 5000000
A22: Fondo Inversión | D22: -100000000 | E22: =+C22+D22 -> -100000000 | F22: 0.18 | I22: 46295 | AA22: =(($C22*$F22)/360)*30 -> 0 | AC22: =(($E22*$F22)/360)*30 -> -1500000 | AD22: =(($C22*$F22)/360)*30 -> 0 | AE22: =(($C22*$F22)/360)*30 -> 0 | AF22: =SUM(Z22:AE22) -> -1500000
A23: Total Fondo Inversión | C23: =+C21+C22 -> 100000000 | D23: =+D21+D22 -> -100000000 | E23: =+E21+E22 -> 0 | G23: =SUM(G14:G21) -> 0 | H23: =SUM(H14:H21) -> 0 | J23: =SUM(J14:J21) -> 0 | K23: =SUM(K14:K21) -> 0 | L23: =SUM(L14:L21) -> 0 | M23: =SUM(M14:M21) -> 0 | N23: =SUM(N14:N21) -> 0 | O23: =SUM(O14:O21) -> 0 | P23: =SUM(P14:P21) -> 0 | Q23: =SUM(Q14:Q21) -> 372868.45 | ... T23: =SUM(T14:T21) -> 1500000 | U23: =SUM(U14:U22) -> 3826211.1 | V23: =SUM(V14:V22) -> 1550000 | W23: =SUM(W14:W22) -> 1500000 | X23: =SUM(X14:X22) -> 846724.42 | Y23: =SUM(Y14:Y22) -> 0 | Z23: =SUM(Z14:Z22) -> 500000 | AA23: =SUM(AA14:AA22) -> 1500000 | AB23: =SUM(AB14:AB22) -> 1500000 | ... AE23: =SUM(AE14:AE22) -> 0 | AF23: =+AF21+AF22 -> 3500000
A25: Banco Alaver | C25: 100000000 | E25: =+C25-D25 -> 100000000 | F25: 0.1375 | I25: 46087 | X25: =(($C25*$F25)/360)*19 -> 725694.44 | Y25: =(($C25*$F25)/360)*30*2 -> 2291666.7 | Z25: =(($C25*$F25)/360)*31 -> 1184027.8 | AA25: =(($C25*$F25)/360)*30 -> 1145833.3 | AB25: =(($C25*$F25)/360)*30 -> 1145833.3 | AC25: =(($C25*$F25)/360)*30 -> 1145833.3 | AD25: =(($C25*$F25)/360)*30 -> 1145833.3 | AE25: =(($C25*$F25)/360)*30 -> 1145833.3 | AF25: =SUM(X25:AE25) -> 9930555.6
A26: Banco Alaver | C26: =+'[1]FLUJO 03-26'!D26 -> 40000000 | E26: =+C26-D26 -> 40000000 | F26: 0.1375 | I26: 46113 | Y26: =(($C26*$F26)/360)*30 -> 458333.33 | Z26: =(($C26*$F26)/360)*30 -> 458333.33 | AA26: =(($C26*$F26)/360)*30 -> 458333.33 | AB26: =(($C26*$F26)/360)*30 -> 458333.33 | AC26: =(($C26*$F26)/360)*30 -> 458333.33 | AD26: =(($C26*$F26)/360)*30 -> 458333.33 | AE26: =(($C26*$F26)/360)*30 -> 458333.33 | AF26: =SUM(X26:AE26) -> 3208333.3
A27: Banco Alaver | C27: 20000000 | E27: =+C27-D27 -> 20000000 | F27: 0.1375 | I27: 46143 | Y27: =(($E27*$F27)/360)*15 -> 114583.33 | Z27: =(($E27*$F27)/360)*30 -> 229166.67 | AA27: =(($E27*$F27)/360)*30 -> 229166.67 | AB27: =(($E27*$F27)/360)*30 -> 229166.67 | AC27: =(($E27*$F27)/360)*30 -> 229166.67 | AD27: =(($E27*$F27)/360)*30 -> 229166.67 | AE27: =(($E27*$F27)/360)*30 -> 229166.67 | AF27: =SUM(X27:AE27) -> 1489583.3
A28: Banco Alaver | C28: =+'1. RESUMEN EJECUTIVO'!AB20 -> 40000000 | E28: =+C28-D28 -> 40000000 | F28: 0.1375 | I28: 46174 | Z28: =(($E28*$F28)/360)*30/(30)*5 -> 76388.889 | AA28: =(($E28*$F28)/360)*30 -> 458333.33 | AB28: =(($E28*$F28)/360)*30 -> 458333.33 | AC28: =(($E28*$F28)/360)*30 -> 458333.33 | AD28: =(($E28*$F28)/360)*30 -> 458333.33 | AE28: =(($E28*$F28)/360)*30 -> 458333.33 | AF28: =SUM(X28:AE28) -> 2368055.6
A29: Banco Alaver | E29: =+C29-D29 -> 0 | F29: 0.1375 | I29: 46204 | AA29: =(($E29*$F29)/360)*30 -> 0 | AB29: =(($E29*$F29)/360)*30 -> 0 | AC29: =(($E29*$F29)/360)*30 -> 0 | AD29: =(($E29*$F29)/360)*30 -> 0 | AE29: =(($E29*$F29)/360)*30 -> 0 | AF29: =SUM(X29:AE29) -> 0
A30: Banco Alaver | C30: 100000000 | D30: =+'1. RESUMEN EJECUTIVO'!AC20 -> 0 | E30: =+C30+D30 -> 100000000 | F30: 0.1375 | I30: 46235 | AA30: =(($E30*$F30)/360)*30 -> 1145833.3 | AB30: =(($E30*$F30)/360)*30 -> 1145833.3 | AC30: =(($E30*$F30)/360)*30 -> 1145833.3 | AD30: =(($E30*$F30)/360)*30 -> 1145833.3 | AE30: =(($E30*$F30)/360)*30 -> 1145833.3 | AF30: =SUM(X30:AE30) -> 5729166.7
A31: Banco Alaver | D31: =+'1. RESUMEN EJECUTIVO'!AE20 -> -150000000 | E31: =+C31+D31 -> -150000000 | F31: 0.1375 | I31: 46266 | AC31: =(($E31*$F31)/360)*30 -> -1718750 | AD31: =(($E31*$F31)/360)*30 -> -1718750 | AE31: =(($E31*$F31)/360)*30 -> -1718750 | AF31: =SUM(X31:AE31) -> -5156250
A32: Banco Alaver | D32: =+'1. RESUMEN EJECUTIVO'!AG20 -> -20000000 | E32: =+C32+D32 -> -20000000 | F32: 0.1375 | I32: 46327 | AD32: =(($E32*$F32)/360)*30 -> -229166.67 | AE32: =(($E32*$F32)/360)*30 -> -229166.67 | AF32: =SUM(X32:AE32) -> -458333.33
A33: Total Banco Alaver | C33: =SUM(C25:C31) -> 300000000 | D33: =SUM(D25:D31) -> -150000000 | E33: =SUM(E25:E31) -> 150000000 | U33: =SUM(U25:U27) -> 0 | V33: =SUM(V25:V27) -> 0 | W33: =SUM(W25:W27) -> 0 | X33: =SUM(X25:X27) -> 725694.44 | Y33: =SUM(Y25:Y31) -> 2864583.3 | Z33: =SUM(Z25:Z32) -> 1947916.7 | AA33: =SUM(AA25:AA32) -> 3437500 | AB33: =SUM(AB25:AB32) -> 3437500 | AC33: =SUM(AC25:AC32) -> 1718750 | AD33: =SUM(AD25:AD32) -> 1489583.3 | AE33: =SUM(AE25:AE32) -> 1489583.3 | AF33: =SUM(AF25:AF32) -> 17111111
A35: Crédito Interino | C35: =+'1. RESUMEN EJECUTIVO'!AE21 -> 240000000 | E35: =+C35-D35 -> 240000000 | F35: 0.1 | I35: 46266 | AB35: =(($C35*$F35)/360)*30 -> 2000000 | AC35: =(($C35*$F35)/360)*30 -> 2000000 | AD35: =(($C35*$F35)/360)*30 -> 2000000 | AE35: =(($C35*$F35)/360)*30 -> 2000000 | AF35: =SUM(Z35:AE35) -> 8000000
A36: Crédito Interino | C36: 180000000 | E36: =+C36-D36 -> 180000000 | F36: 0.1 | I36: 46327 | AD36: =(($C36*$F36)/360)*30 -> 1500000 | AE36: =(($C36*$F36)/360)*30 -> 1500000 | AF36: =SUM(Z36:AE36) -> 3000000
A37: Total Crédito interino | C37: =SUM(C35:C35) -> 240000000 | D37: =SUM(D35:D35) -> 0 | E37: =SUM(E35:E35) -> 240000000 | U37: =SUM(#REF!) -> #REF! | V37: =SUM(#REF!) -> #REF! | W37: =SUM(#REF!) -> #REF! | X37: =SUM(X35:X35) -> 0 | Y37: =SUM(Y35:Y35) -> 0 | Z37: =SUM(Z35:Z36) -> 0 | AA37: =SUM(AA35:AA36) -> 0 | AB37: =SUM(AB35:AB36) -> 2000000 | AC37: =SUM(AC35:AC36) -> 2000000 | AD37: =SUM(AD35:AD36) -> 3500000 | AE37: =SUM(AE35:AE36) -> 3500000 | AF37: =SUM(AF35:AF36) -> 11000000
A39: Total Intereses Proyectados | C39: =+C23+C33+C37 -> 640000000 | D39: =+D23+D33+D37 -> -250000000 | E39: =+E23+E33+E37 -> 390000000 | G39: =+G13+G23 -> 0 | H39: =+H13+H23 -> 0 | J39: =+J13+J23 -> 0 | K39: =+K13+K23 -> 0 | L39: =+L13+L23 -> 0 | M39: =+M13+M23 -> 0 | N39: =+N13+N23 -> 0 | O39: =+O13+O23 -> 87083.33 | P39: =+P13+P23 -> 174166.67 | Q39: =+Q13+Q23 -> 547035.12 | ... T39: =+T13+T23 -> 1500000 | U39: =+U13+U23+U33 -> 3826211.1 | V39: =+V13+V23+V33 -> 1550000 | W39: =+W13+W23+W33 -> 1500000 | X39: =+X13+X23+X33 -> 1572418.9 | Y39: =+Y33+Y37 -> 2864583.3 | Z39: =+Z23+Z33+Z37 -> 2447916.7 | AA39: =+AA23+AA33+AA37 -> 4937500 | AB39: =+AB23+AB33+AB37 -> 6937500 | AC39: =+AC23+AC33+AC37 -> 3718750 | AD39: =+AD23+AD33+AD37 -> 4989583.3 | AE39: =+AE23+AE33+AE37 -> 4989583.3 | AF39: =+AF23+AF33+AF37 -> 31611111

Sheet 5. ANTICIPOS
B1: ANTICIPOS OTORGADOS — CORTE 30 DE JUNIO 2026 | Valores en RD$
B2: PROVEEDOR | C2: REFERENCIA | D2: F. EMISIÓN | E2: MONTO TOTAL | F2: SALDO PEND. | G2: AUXILIAR | H2: DESCRIPCIÓN
B3: HIDROPOZO SRL | C3: ANTICIPO HIDROPOZOS | D3: 2023-12-06 | E3: 273000 | F3: 273000 | G3: 1-2-1 Diseno y Proye | H3: ANTICIPO COT 94 PRUEBA DE IN
B4: CONSTRUCTORA FELIX CAMPOS SRL | C4: ANTICIPO 40%-SC--147 | D4: 2026-06-30 | E4: 567718.8 | F4: 567718.8 | G4: 1-4-1 Urbanismo | H4: ANTICIPO 40%-SC--147 Contrac
B5: GRUPO ALUGAV SAS | C5: ANTICIPO--SC--144 | D5: 2026-06-17 | E5: 27010.57 | F5: 27010.57 | G5: 1-4-1 Urbanismo | H5: ANTICIPO--SC--144 Contract #
B6: CONSTRUCTORA FELIX CAMPOS SRL | C6: ANTICIPO 40%-SC--146 | D6: 2026-06-30 | E6: 625800 | F6: 625800 | G6: 1-4-1 Urbanismo | H6: ANTICIPO 40%-SC--146 Contrac
B7: INVERSIONES ROMUR SRL | C7: ANTICIPO SC--115 | D7: 2026-05-27 | E7: 2351900.8 | F7: 1532229 | G7: 1-4-1 Urbanismo | H7: Anticipo del 20% SC--115 par
B8: TALLER INDUSTRIAL J NIVAR SRL | C8: ANTICIPO SC--114 | D8: 2026-05-15 | E8: 64000 | F8: 64000 | G8: 1-4-1 Urbanismo | H8: ANTICIPO-SC--114 Contract #S
B9: GERENCIA INMOBILIARIA PROACTIVA | C9: ANTICIPO SC--145 | D9: 2026-06-26 | E9: 111300 | F9: 111300 | G9: 1-4-1 Urbanismo | H9: ANTICIPO SC--145 Contract #S
B10: MICARGO SRL | C10: ANTICIPO PO--528 | D10: 2026-05-08 | E10: 26350 | F10: 26350 | G10: 1-4-1 Urbanismo | H10: ANTICIPO PO--528 Purchase Or
B11: MULTISERVICIOS 24 SEVEN JM EIRL | C11: ANTICIPO PO--702 | D11: 2026-06-30 | E11: 160430 | F11: 160430 | G11: 1-4-1 Urbanismo | H11: ANTICIPO PO--702 Purchase Or
B12: FUSIONTECH SRL | C12: ANTICIPO-SC--143 | D12: 2026-06-29 | E12: 86453.88 | F12: 86453.88 | G12: 1-4-1 Urbanismo | H12: ANTICIPO-SC--143 Contract #S
B13: ROCAENCA SRL | C13: ANTICIPO-PO--513 | D13: 2026-06-18 | E13: 13216 | F13: 13216 | G13: 1-5-1 Edificaciones | H13: ANTICIPO-PO--513 Purchase Or
B14: OZONO QUIMICOS Y ESPECIALIDADES | C14: ANTICIPO PO--704 | D14: 2026-06-30 | E14: 51587.64 | F14: 51587.64 | G14: 1-5-1 Edificaciones | H14: ANTICIPO PO--704 Purchase Or
... B28: RIOS & ASOCIADOS ABOGADOS CONSUL | C28: ANTICIPO RIOS | D28: 2025-10-06 | E28: 6671.88 | F28: 6671.88 | G28: 3-1-1 Permisos Legal | H28: Anticipo PO--137 Confotur De
B29: TOTAL ANTICIPOS | E29: =SUM(E3:E28) -> 10035121 | F29: =SUM(F3:F28) -> 9210448.9

Sheet BCE-06-26
A1: Balance Sheet
A2: Fideicomiso Irrevocable de Desarrollo Inmobiliario y Administración Araya
A3: As at 30 June 2026
B5: Account | C5: 30 Jun 2026
A7: Assets
B8: Bank
B9: Banco Alaver Cta de Ahorro en DOP | C9: 20485844
B10: Banesco DOP -Cta. Corriente No.99100010856 | C10: 16604331
B11: Banesco USA No. 1500192677 | C11: 2615906 | D11: [FX]
B12: Banesco USD -Cta. Ahorro No.99200013780 | C12: 5003923 | D12: [FX]
B13: Fondo de Inversión Abierto Plazo Mensual USD | C13: 254058.85 | D13: [FX]
B14: Fondo de Inversión Abierto Universal Liquidez DOP | C14: 23157.58
B15: Popular Cta Ahorro No. 845567916 | C15: 3207819.9 | D15: [FX]
B16: Popular Cta Corriente No. 845567809 | C16: 39249.18
B17: Total Bank | C17: =SUM(C9:C16) -> 48234289
B18: Current Assets
B19: Anticipos a Proveedores | C19: 9210448.9
B20: Total Current Assets | C20: =C19 -> 9210448.9
B21: Non-current Assets
B22: 1% Impuesto Retenido a Intereses Norma 13-11 | C22: 551
B23: Costos de Construcción | C23: 4.8346606e+08
B24: Costos Operativos | C24: 1.7824902e+08
B25: Otros Costos | C25: 40554300
B26: Total Non-current Assets | C26: =SUM(C22:C25) -> 7.0226994e+08
A27: Total Assets | C27: =(0 + ((C17 + C20) + C26)) -> 7.5971467e+08
A29: Liabilities
B30: Current Liabilities
B31: Créditos en Instituciones Financieras | C31: 200000000
B32: Cuentas por Cobrar Compañía Relacionada USD | C32: 148022.4 | D32: [FX]
B33: Cuentas por Pagar Comerciales | C33: 18612246 | D33: [FX]
B34: Depósitos Diferidos de Clientes | C34: 2.209977e+08
B35: Fondo Rotatorio Tecnica MMHB | C35: 2021249.3
B36: Otras Cuentas por Pagar Tecnica MMHB | C36: 56826
B37: Retención 100% ITBIS. Personas Físicas | C37: 48349.66
B38: Retención 100% ITBIS. Personas Jurídicas | C38: 93522.55
B39: Retención 30% ITBIS Jurídica | C39: 412309.11
B40: Retención de Derecho Laboral | C40: 1107484.9
B41: Retención de Fiel Cumplimiento | C41: 706625.52
B42: Retención ISR Exterior 27% | C42: 1411944.5
B43: Retención ISR Personas Físicas 10% | C43: 23983.14
B44: Retención ISR Personas Físicas 2% | C44: 138233.08
B45: Rounding | C45: 3.41
B46: Total Current Liabilities | C46: =SUM(C31:C45) -> 4.457785e+08
B47: Non-current Liabilities
B48: Otros créditos - No corriente | C48: 431409.34
B49: Total Non-current Liabilities | C49: =C48 -> 431409.34
A50: Total Liabilities | C50: =(0 + (C46 + C49)) -> 4.462099e+08
B52: Net Assets | C52: =(C27 - C50) -> 3.1350477e+08
A54: Equity
B55: Aporte Fideicomitente AFI Universal | C55: 3.2291773e+08
B56: Current Year Earnings | C56: -5939941.9
B57: Resultado del Ejercicio | C57: -3473021.6
A58: Total Equity | C58: =SUM(C55:C57) -> 3.1350477e+08
A61: [FX] Exchange rates used to convert foreign currency into DOP are shown below. Rates are provided by XE.com unless otherwise stated.
A62: 30 Jun 2026
A63: 0.0167880 USD (United States Dollar)

Sheet 1. RESUMEN EJECUTIVO (2)
B2: FIDEICOMISO ARAYA — INFORME JUNIO 2026
B3: Control Presupuestal · Cuentas por Pagar · Anticipos | Corte: 30 de junio de 2026
B5: INGRESOS POR FUENTE — Valores en RD$ | H5: DISPONIBILIDAD
B6: INGRESOS POR FUENTE — Valores en RD$ | C6: PRESUPUESTO | D6: EJECUTADO | E6: POR EJECUTAR | H6: INGRESOS ACUM. RD$ | I6: % PART. | J6: Acum 2024 | K6: Ene-25 | L6: Feb-25 | M6: Mar-25 | N6: Abr-25 | O6: May-25 | P6: Jun-25 | Q6: Jul-25 | R6: Ago-25 | S6: Sep-25 | T6: Oct-25 | U6: Nov-25 | V6: Dic-25 | W6: Ene-26 | X6: Feb-26 | Y6: Mar-26 | Z6: Abr-26 | AA6: May-26 | AB6: Jun-26 | AC6: Jul-26 | AD6: Aug-26 | AE6: Sep-26 | AF6: Oct-26 | AG6: Nov-26 | AH6: Dec-26 | AI6: Total | AJ6: Jan-27 | AK6: Feb-27 | AL6: Mar-27 | AM6: Apr-27 | AN6: May-27 | AO6: Jun-27 | AP6: Jul-27 | AQ6: Aug-27 | AR6: Sep-27 | AS6: Oct-27 | AT6: Nov-27 | AU6: Dec-27 | AV6: Jan-28 | AW6: Feb-28 | AX6: Mar-28 | AY6: Apr-28 | AZ6: May-28 | BA6: Jun-28 | BB6: Jul-28 | BC6: Aug-28 | BD6: Sep-28 | BE6: Oct-28 | BF6: Nov-28 | BG6: Dec-28 | BH6: Jan-29 | BI6: Feb-29 | BJ6: Mar-29 | BK6: Apr-29 | BL6: May-29 | BM6: Jun-29 | BN6: Jul-29 | BO6: Aug-29 | BP6: Sep-29 | BQ6: Oct-29 | BR6: Nov-29 | BS6: Dec-29 | BT6: Jan-30 | BU6: Feb-30 | BV6: TOTAL PROYECCIÓN | CA6: Total
B7: ◆ DEPÓSITOS DE CLIENTES | C7: =+C13 -> 68213916 | D7: =+D13 -> 22621811 | E7: =+C7-D7 -> 45592105 | H7: =SUM(J7:AB7) -> 2.209977e+08 | I7: =IF(D24=0,0,D7/D24) -> 0 | J7: =SUM(J14) -> 597566.75 | K7: =SUM(K14) -> 303761.92 | L7: =SUM(L14) -> 0 | M7: =SUM(M14) -> 61261.19 | N7: =SUM(N14) -> 2943821.6 | O7: =SUM(O14) -> 6287923.9 | P7: =SUM(P14) -> 12847852 | Q7: =SUM(Q14) -> 18376057 | ... AA7: =SUM(AA14) -> 17029605 | AB7: =+AB14 -> 18301398 | AC7: =+AC14 -> 18000000 | AD7: =+AD14 -> 18000000 | AE7: =+AE14 -> 18000000 | AF7: =+AF14 -> 18000000 | AG7: =+AG14 -> 18000000 | AH7: =+AH14 -> 18000000 | AI7: =SUM(AB7:AH7)+H7 -> 3.4729909e+08 | AJ7: =+AJ14 -> 0 | AK7: =+AK14 -> 0 | AL7: =+AL14 -> 0 | AM7: =+AM14 -> 0 | AN7: =+AN14 -> 0 | AO7: =+AO14 -> 0 | AP7: =+AP14 -> 0 | AQ7: =+AQ14 -> 0 | ... BU7: =+BU14 -> 0 | CA7: =+H7+AB7+AC7+AD7+AE7+AF7+AG7 -> 3.2929909e+08
B8: └ Unidades vendidas en el período | C8: 462 | D8: =+H8 -> 164 | E8: =+C8-D8 -> 298 | H8: =SUM(J8:AB8) -> 164 | I8: =IF(D24=0,0,D8/D24) -> 0 | P8: 3 | Q8: 29 | R8: 20 | S8: 24 | T8: 12 | U8: 9 | V8: 12 | W8: 2 | X8: 7 | Y8: 14 | Z8: 10 | AA8: 11 | AB8: 11 | AC8: 15 | AD8: 15 | AE8: 15 | AF8: 15 | AG8: 15 | AH8: 15
B9: └ Unidades desistidas en el período | D9: =+H9 -> -3 | E9: =+C9-D9 -> 3 | H9: =SUM(J9:AB9) -> -3 | I9: =IF(D24=0,0,D9/D24) -> 0 | X9: -2 | AA9: -1
B10: └ Unidades vinculadas en el período | C10: 462 | D10: =+H10 -> 161 | E10: =SUM(E8:E9) -> 301 | H10: =SUM(J10:AB10) -> 161 | I10: =IF(D24=0,0,D10/D24) -> 0 | J10: =+J8+J9 -> 0 | K10: =+K8+K9 -> 0 | L10: =+L8+L9 -> 0 | M10: =+M8+M9 -> 0 | N10: =+N8+N9 -> 0 | O10: =+O8+O9 -> 0 | P10: =+P8+P9 -> 3 | Q10: =+Q8+Q9 -> 29 | ... AH10: =+AH8+AH9 -> 15
B11: └ Monto vendido en el período | D11: =SUM(J11:AB11) -> 23071011 | I11: =IF(D24=0,0,D11/D24) -> 0 | P11: 390100 | Q11: 3803830 | R11: 2530870 | S11: 3264350 | T11: 1674700 | U11: 1263361 | V11: 1596100 | W11: 145350 | X11: 1375650 | Y11: 2067350 | Z11: 1504150 | AA11: 1797250 | AB11: 1657950 | AC11: 2250000 | AD11: 2250000 | AE11: 2250000 | AF11: 2250000 | AG11: 2250000 | AH11: 2250000
B12: └ Monto desistido en el período | D12: =SUM(J12:AB12) -> -449200 | I12: =IF(D24=0,0,D12/D24) -> 0 | X12: -309900 | AA12: -139300
B13: └ Total Monto vinculado en el período | C13: 68213916 | D13: =SUM(J13:AB13) -> 22621811 | E13: =+C13-D13 -> 45592105 | I13: =IF(D24=0,0,D13/D24) -> 0 | J13: =+J11+J12 -> 0 | K13: =+K11+K12 -> 0 | L13: =+L11+L12 -> 0 | M13: =+M11+M12 -> 0 | N13: =+N11+N12 -> 0 | O13: =+O11+O12 -> 0 | P13: =+P11+P12 -> 390100 | Q13: =+Q11+Q12 -> 3803830 | ... AH13: =+AH11+AH12 -> 2250000
B14: └ Monto depósitos recibidos (RD$) | H14: =SUM(J14:AB14) -> 2.209977e+08 | I14: =IF(D24=0,0,D14/D24) -> 0 | J14: 597566.75 | K14: 303761.92 | M14: 61261.19 | N14: 2943821.6 | O14: 6287923.9 | P14: 12847852 | Q14: 18376057 | R14: 16465116 | S14: 19518073 | T14: 21677599 | U14: 10776009 | V14: 15186373 | W14: 9131873.1 | X14: 16575280 | Y14: 17317936 | Z14: 17600190 | AA14: 17029605 | AB14: =17095509.97+1205887.79 -> 18301398 | AC14: 18000000 | AD14: 18000000 | AE14: 18000000 | AF14: 18000000 | AG14: 18000000 | AH14: 18000000
B15: ◆ APORTES DE SOCIOS | H15: =SUM(J15:AB15) -> 3.2291773e+08 | I15: =IF(D24=0,0,D15/D24) -> 0 | J15: =SUM(J16) -> 1.5969577e+08 | K15: =SUM(K16) -> 0 | L15: =SUM(L16) -> 0 | M15: =SUM(M16) -> 0 | N15: =SUM(N16) -> 0 | O15: =SUM(O16) -> 0 | P15: =SUM(P16) -> 0 | Q15: =SUM(Q16) -> 0 | ... AA15: =SUM(AA16) -> 0 | AI15: =SUM(AB15:AH15)+H15 -> 3.2291773e+08 | CA15: =+H15+AB15+AC15+AD15+AE15+AF15+AG15 -> 3.2291773e+08
B16: └ AFI Universal — Fideicomitente | H16: =SUM(J16:AA16) -> 3.2291773e+08 | I16: =IF(D24=0,0,D16/D24) -> 0 | J16: 1.5969577e+08 | R16: 1.7025268e+08 | Z16: -7030718.2 | AI16: =SUM(AB16:AH16)+H16 -> 3.2291773e+08
B17: ◆ PRÉSTAMOS RECIBIDOS | H17: =SUM(J17:AB17) -> 200000000 | I17: =IF(D24=0,0,D17/D24) -> 0 | J17: =SUM(J18:J20) -> 0 | K17: =SUM(K18:K20) -> 0 | L17: =SUM(L18:L20) -> 0 | M17: =SUM(M18:M20) -> 0 | N17: =SUM(N18:N20) -> 15000000 | O17: =SUM(O18:O20) -> 7200000 | P17: =SUM(P18:P20) -> 12000000 | Q17: =SUM(Q18:Q20) -> 15000000 | ... AA17: =SUM(AA18:AA20) -> 20000000 | AB17: =SUM(AB18:AB21) -> 40000000 | AC17: =SUM(AC18:AC21) -> 100000000 | AD17: =SUM(AD18:AD21) -> 100000000 | AE17: =SUM(AE18:AE21) -> -10000000 | AF17: =SUM(AF18:AF21) -> 0 | AG17: =SUM(AG18:AG21) -> 160000000 | AH17: =SUM(AH18:AH21) -> 0 | AI17: =SUM(AB17:AH17)+H17 -> 590000000 | AJ17: =SUM(AJ18:AJ21) -> 0 | AK17: =SUM(AK18:AK21) -> 0 | AL17: =SUM(AL18:AL21) -> 0 | AM17: =SUM(AM18:AM21) -> 0 | AN17: =SUM(AN18:AN21) -> 0 | AO17: =SUM(AO18:AO21) -> 0 | AP17: =SUM(AP18:AP21) -> 0 | AQ17: =SUM(AQ18:AQ21) -> 0 | ... BU17: =SUM(BU18:BU21) -> 0 | CA17: =+H17+AB17+AC17+AD17+AE17+AF17+AG17 -> 590000000
B18: └ Grupo BAK | H18: =SUM(J18:AA18) -> 0 | I18: =IF(D24=0,0,D18/D24) -> 0 | N18: 15000000 | O18: 7200000 | P18: 12000000 | Q18: 15000000 | T18: -5000000 | V18: -44200000 | AI18: =SUM(AB18:AH18)+H18 -> 0
B19: └ AFI Universal (Crédito Puente) | C19: 100000000 | D19: =+H190 -> 0 | E19: =+C19-D19 -> 100000000 | H19: =SUM(J19:AB19) -> 0 | I19: =IF(D24=0,0,D19/D24) -> 0 | S19: 55184227 | U19: 44815773 | Y19: -100000000 | AC19: 100000000 | AE19: -100000000 | AI19: =SUM(AB19:AH19)+H19 -> 0
B20: └ Banco Alaver | C20: 300000000 | D20: =+H20 -> 200000000 | E20: =+C20-D20 -> 100000000 | H20: =SUM(J20:AB20) -> 200000000 | I20: =IF(D24=0,0,D20/D24) -> 0 | Y20: 100000000 | Z20: 40000000 | AA20: 20000000 | AB20: 40000000 | AD20: 100000000 | AE20: -150000000 | AG20: -20000000 | AI20: =SUM(AB20:AH20)+H20 -> 170000000 | CA20: =+H20+AB20+AC20+AD20+AE20+AF20+AG20 -> 170000000
B21: └ IFC | C21: 420000000 | D21: =+H21 -> 0 | E21: =+C21-D21 -> 420000000 | I21: =IF(D24=0,0,D21/D24) -> 0 | AE21: 240000000 | AG21: 180000000 | AI21: =SUM(AB21:AH21)+H21 -> 420000000 | CA21: =+H21+AB21+AC21+AD21+AE21+AF21+AG21 -> 420000000
B22: ◆ INTERESES GENERADOS POR INVERSIONES | H22: =SUM(J22:AB22) -> 2442157.6 | I22: =IF(D24=0,0,D22/D24) -> 0 | J22: =SUM(J23) -> 157571.37 | K22: =SUM(K23) -> 12060.79 | L22: =SUM(L23) -> 5956.62 | M22: =SUM(M23) -> 1903.68 | N22: =SUM(N23) -> 13709.55 | O22: =SUM(O23) -> 14582.39 | P22: =SUM(P23) -> 23991.28 | Q22: =SUM(Q23) -> 92565.03 | ... AA22: =SUM(AA23) -> 39828.59 | AB22: 24807.75 | AI22: =SUM(AB22:AH22)+H22 -> 2466965.3 | CA22: =+H22+AB22+AC22+AD22+AE22+AF22+AG22 -> 2466965.3
B23: └ Cuentas de ahorro y Fondos de inversión | H23: =SUM(J23:AA23) -> 2417349.8 | I23: =IF(D24=0,0,D23/D24) -> 0 | J23: 157571.37 | K23: 12060.79 | L23: 5956.62 | M23: 1903.68 | N23: 13709.55 | O23: 14582.39 | P23: 23991.28 | Q23: 92565.03 | R23: 173774.27 | S23: 260138.61 | T23: 332815.92 | U23: 328847.65 | V23: 529575.76 | W23: 144258.21 | X23: 134169.93 | Y23: 129606.28 | Z23: 21993.88 | AA23: 39828.59 | AI23: =SUM(AB23:AH23)+H23 -> 2417349.8
B24: TOTAL INGRESOS RD$ | H24: =SUM(J24:AB24) -> 7.4635759e+08 | I24: 1 | J24: =+J7+J15+J17+J22 -> 1.6045091e+08 | K24: =+K7+K15+K17+K22 -> 315822.71 | L24: =+L7+L15+L17+L22 -> 5956.62 | M24: =+M7+M15+M17+M22 -> 63164.87 | N24: =+N7+N15+N17+N22 -> 17957531 | O24: =+O7+O15+O17+O22 -> 13502506 | P24: =+P7+P15+P17+P22 -> 24871844 | Q24: =+Q7+Q15+Q17+Q22 -> 33468622 | ... AH24: =+AH7+AH15+AH17+AH22 -> 18000000 | AI24: =SUM(AB24:AH24)+H24 -> 1.2626838e+09 | AJ24: =+AJ7+AJ15+AJ17+AJ22 -> 0 | AK24: =+AK7+AK15+AK17+AK22 -> 0 | AL24: =+AL7+AL15+AL17+AL22 -> 0 | AM24: =+AM7+AM15+AM17+AM22 -> 0 | AN24: =+AN7+AN15+AN17+AN22 -> 0 | AO24: =+AO7+AO15+AO17+AO22 -> 0 | AP24: =+AP7+AP15+AP17+AP22 -> 0 | AQ24: =+AQ7+AQ15+AQ17+AQ22 -> 0 | ... BU24: =+BU7+BU15+BU17+BU22 -> 0 | CA24: =+H24+AB24+AC24+AD24+AE24+AF24+AG24 -> 1.2446838e+09
B25: TOTAL INGRESOS ACUMULADOS RD$ | H25: =+H7+H15+H17+H22 -> 7.4635759e+08 | J25: =+J24 -> 1.6045091e+08 | K25: =+J25+K24 -> 1.6076673e+08 | L25: =+K25+L24 -> 1.6077269e+08 | M25: =+L25+M24 -> 1.6083586e+08 | N25: =+M25+N24 -> 1.7879339e+08 | O25: =+N25+O24 -> 1.9229589e+08 | P25: =+O25+P24 -> 2.1716774e+08 | Q25: =+P25+Q24 -> 2.5063636e+08 | R25: =+Q25+R24 -> 4.3752793e+08 | ... AH25: =+AG25+AH24 -> 1.2043576e+09 | AJ25: =+AH25+AJ24 -> 1.2043576e+09 | AK25: =+AJ25+AK24 -> 1.2043576e+09 | AL25: =+AK25+AL24 -> 1.2043576e+09 | AM25: =+AL25+AM24 -> 1.2043576e+09 | AN25: =+AM25+AN24 -> 1.2043576e+09 | AO25: =+AN25+AO24 -> 1.2043576e+09 | AP25: =+AO25+AP24 -> 1.2043576e+09 | AQ25: =+AP25+AQ24 -> 1.2043576e+09 | AR25: =+AQ25+AR24 -> 1.2043576e+09 | ... BV25: =+BU25+BV24 -> 1.2043576e+09 | CA25: =+CA24 -> 1.2446838e+09
B27: CONTROL PRESUPUESTAL | C27: Valores en RD$
B28: CENTRO DE COSTO / AUXILIAR | C28: PRESUPUESTO TOTAL | D28: EJECUTADO | E28: POR EJECUTAR | F28: ANTICIPOS ACUM. | G28: CXP AL CORTE | H28: PAGOS ACUMULADOS | I28: % EJEC. | J28: Acum 2024 | K28: Ene-25 | L28: Feb-25 | M28: Mar-25 | N28: Abr-25 | O28: May-25 | P28: Jun-25 | Q28: Jul-25 | R28: Ago-25 | S28: Sep-25 | T28: Oct-25 | U28: Nov-25 | V28: Dic-25 | W28: Ene-26 | X28: Feb-26 | Y28: Mar-26 | Z28: Abr-26 | AA28: May-26 | AB28: Jun-26 | AC28: Jul-26 | AD28: Aug-26 | AE28: Sep-26 | AF28: Oct-26 | AG28: Nov-26 | AH28: Dec-26 | AI28: Total | AJ28: Jan-27 | AK28: Feb-27 | AL28: Mar-27 | AM28: Apr-27 | AN28: May-27 | AO28: Jun-27 | AP28: Jul-27 | AQ28: Aug-27 | AR28: Sep-27 | AS28: Oct-27 | AT28: Nov-27 | AU28: Dec-27 | AV28: Jan-28 | AW28: Feb-28 | AX28: Mar-28 | AY28: Apr-28 | AZ28: May-28 | BA28: Jun-28 | BB28: Jul-28 | BC28: Aug-28 | BD28: Sep-28 | BE28: Oct-28 | BF28: Nov-28 | BG28: Dec-28 | BH28: Jan-29 | BI28: Feb-29 | BJ28: Mar-29 | BK28: Apr-29 | BL28: May-29 | BM28: Jun-29 | BN28: Jul-29 | BO28: Aug-29 | BP28: Sep-29 | BQ28: Oct-29 | BR28: Nov-29 | BS28: Dec-29 | BT28: Jan-30 | BU28: Feb-30 | BV28: TOTAL PROYECCIÓN | CA28: Total
B29: ◆ CONSTRUCCIÓN
B30: 1-1 Terreno | C30: 106933000 | D30: =SUM(J30:AB30) -> 2.6677371e+08 | E30: =+C30-D30 -> -1.5984071e+08 | H30: =+D30+F30-G30 -> 2.6677371e+08 | I30: =IF(H$45=0,0,H30/H$45) -> 0.55466589 | J30: 94172342 | O30: 18880 | R30: 1.7025268e+08 | S30: 1179 | V30: 1 | Z30: -7030718.2 | AA30: 9359346.1 | AC30: 1625472.4 | AD30: 1285975 | BV30: =SUM(AB30:BU30) -> 2911447.4 | CA30: =+H30+AB30+AC30+AD30+AE30+AF30+AG30 -> 2.6968516e+08
B31: 1-2 Diseño y Proyecto | C31: 25000000 | D31: =SUM(J31:AB31) -> 24159807 | E31: =+C31-D31 -> 840192.64 | F31: 273000 | H31: =+D31+F31-G31 -> 24432807 | I31: =IF(H$45=0,0,H31/H$45) -> 0.050799777 | J31: 20979516 | K31: 428149.75 | M31: 146320 | N31: 108350.26 | O31: 53100 | Q31: 278099.52 | R31: 1595686.8 | S31: -190307.52 | T31: 310669.15 | V31: 273687.19 | X31: 416685.22 | Y31: 31433.41 | Z31: -271582.08 | BV31: =SUM(AB31:BU31) -> 0 | BX31: Urbanismo | BY31: Edificaciones | CA31: =+H31+AB31+AC31+AD31+AE31+AF31+AG31 -> 24432807
B32: 1-4 Urbanismo | C32: 4.6917367e+08 | D32: =SUM(J32:AB32) -> 50777443 | E32: =+C32-D32 -> 4.1839622e+08 | F32: 3201292.2 | G32: =2409540.07+31179.21 -> 2440719.3 | H32: =+D32+F32-G32 -> 51538016 | I32: =IF(H$45=0,0,H32/H$45) -> 0.10715591 | J32: 9219083.6 | N32: 353433.2 | O32: 93563.38 | P32: 401816.36 | Q32: 17765977 | R32: 2900560.5 | S32: -13949178 | T32: 201871.48 | U32: 1617336.1 | V32: 15407307 | W32: 222844.91 | X32: 2449569.8 | Y32: 1844423.4 | Z32: 2432002.3 | AA32: 4340947.8 | AB32: 5475884.7 | AC32: =2233363.79-BX38 -> 9945082.1 | AD32: 25883233 | AE32: 19023863 | AF32: 30184986 | AG32: 22131186 | AH32: 27733359 | AJ32: 9994863 | AK32: 12921923 | AL32: 13067198 | AM32: 7358492 | AN32: 14828592 | AO32: 12874976 | AP32: 14527005 | AQ32: 20554545 | AR32: 12799482 | AS32: 12013658 | AT32: 13823208 | AU32: 13482346 | AV32: 12131034 | AW32: 13811771 | AX32: 18464279 | AY32: 14290217 | AZ32: 11114566 | BA32: 5972630 | BB32: 2180738 | BC32: 2907651 | BD32: 2180738 | BE32: 2696366 | BV32: =SUM(AB32:BU32) -> 3.8437387e+08 | BW32: Ejecutado de dic-25 a jun-26 | BX32: =+D32-33504463 -> 17272980 | BY32: =+D33 -> 91014535 | BZ32: =+BX32+BY32 -> 1.0828751e+08 | CA32: =+H32+AB32+AC32+AD32+AE32+AF32+AG32 -> 1.6418225e+08
B33: 1-5 Edificaciones | C33: 1517166651 | D33: =SUM(J33:AB33) -> 91014535 | E33: =+C33-D33 -> 1.4261521e+09 | F33: 4044252 | G33: 9079360.7 | H33: =+D33+F33-G33 -> 85979426 | I33: =IF(H$45=0,0,H33/H$45) -> 0.1787652 | V33: 991237.18 | W33: 2132656.5 | X33: 6421897.4 | Y33: 23710126 | Z33: 17366039 | AA33: 17043612 | AB33: 23348966 | AC33: =41619451.81-BY38 -> 1.0967745e+08 | AD33: 50615128 | AE33: 58724023 | AF33: 41829222 | AG33: 47927697 | AH33: 31472733 | AJ33: 68830255 | AK33: 106468694 | AL33: 56788924 | AM33: 54650319 | AN33: 61097688 | AO33: 49492842 | AP33: 21864246 | AQ33: 52347351 | AR33: 49990554 | AS33: 42428902 | AT33: 74826189 | AU33: 38421250 | AV33: 34420885 | AW33: 101104251 | AX33: 53636125 | AY33: 38678782 | AZ33: 45511341 | BA33: 33619379 | BB33: 37777967 | BC33: 48464991 | BD33: 24826641 | BE33: 24008933 | BF33: 21480215 | BG33: 6678810 | BH33: 1109066 | BV33: =SUM(AB33:BU33) -> 1.5121198e+09 | BW33: CXP | BX33: =+G32 -> 2440719.3 | BY33: =+G33 -> 9079360.7 | BZ33: =+BX33+BY33 -> 11520080 | CA33: =+H33+AB33+AC33+AD33+AE33+AF33+AG33 -> 4.1810191e+08
B34: 1-6 Gerencia de Construcción | C34: 2.3438816e+08 | D34: =SUM(J34:AB34) -> 40247270 | E34: =+C34-D34 -> 1.9414089e+08 | G34: 86313.8 | H34: =+D34+F34-G34 -> 40160957 | I34: =IF(H$45=0,0,H34/H$45) -> 0.083501155 | J34: 1644662 | K34: 1770000 | M34: 885000 | N34: 2455806.5 | O34: 2360000 | P34: 2417857.3 | Q34: 2664755.2 | R34: 4720000 | T34: 2360000 | U34: 2783225.3 | V34: 1770000 | W34: 2360000 | X34: 2862845.2 | Y34: 2175899.8 | Z34: 2400227.5 | AA34: 2341111.1 | AB34: 2275880.4 | AC34: 2360000 | AD34: 2360000 | AE34: 2360000 | AF34: 2360000 | AG34: 2360000 | AH34: 5283637 | AJ34: 7882512 | AK34: 11939062 | AL34: 6985612 | AM34: 6200881 | AN34: 7592628 | AO34: 6236782 | AP34: 3639125 | AQ34: 7290190 | AR34: 6279004 | AS34: 5444256 | AT34: 8864940 | AU34: 5190360 | AV34: 4655192 | AW34: 11491602 | AX34: 7210040 | AY34: 5296900 | AZ34: 5662591 | BA34: 3959201 | BB34: 3995870 | BC34: 5137264 | BD34: 2700738 | BE34: 2670530 | BF34: 2148021 | BG34: 667881 | BH34: 110907 | BV34: =SUM(AB34:BU34) -> 1.5861161e+08 | BW34: Pagado | BX34: =+BX32-BX33 -> 14832260 | BY34: =+BY32-BY33 -> 81935174 | BZ34: =+BX34+BY34 -> 96767434 | CA34: =+H34+AB34+AC34+AD34+AE34+AF34+AG34 -> 54236837
B35: 1-7 Indirectos de Obra | C35: 47672168 | D35: =SUM(J35:AB35) -> 8294845.7 | E35: =+C35-D35 -> 39377322 | G35: =SUM(G36:G41) -> 779549.45 | H35: =+D35+F35-G35 -> 7515296.3 | I35: =IF(H$45=0,0,H35/H$45) -> 0.015625522 | P35: 147108.54 | Q35: 92700.8 | R35: 96854.4 | S35: 90246.4 | T35: 92700.8 | U35: 332688.71 | V35: 92700.8 | W35: 102858.24 | X35: 3036943.5 | Y35: 2022959.1 | Z35: 729930.47 | AA35: 731956.76 | AB35: =SUM(AB36:AB42) -> 725197.25 | AC35: =1600000 -> 1600000 | AD35: 1600000 | AE35: 1600000 | AF35: 1600000 | AG35: 1600000 | AH35: 755081 | AJ35: 755081 | AK35: 755081 | AL35: 755081 | AM35: 755081 | AN35: 755081 | AO35: 755081 | AP35: 755081 | AQ35: 755081 | AR35: 755081 | AS35: 755081 | AT35: 755081 | AU35: 755081 | AV35: 755081 | AW35: 755081 | AX35: 755081 | AY35: 755081 | AZ35: 755081 | BA35: 755081 | BB35: 755081 | BC35: 755081 | BD35: 755081 | BE35: 755081 | BF35: 755081 | BG35: 755081 | BH35: 755081 | BI35: 755081 | BJ35: 755081 | BK35: 755081 | BL35: 755081 | BM35: 755081 | BN35: 50045 | BV35: =SUM(AB35:BU35) -> 32182753 | BW35: Anticipos | BX35: =+F32 -> 3201292.2 | BY35: =+F33 -> 4044252 | BZ35: =+BX35+BY35 -> 7245544.2 | CA35: =+H35+AB35+AC35+AD35+AE35+AF35+AG35 -> 16240494
B36: └ 1-7-1 Gastos Personal Adm. de Obra | D36: =SUM(J36:AB36) -> 312900 | G36: 52150 | H36: 260750 | I36: =IF(H$45=0,0,H36/H$45) -> 0.00054214162 | X36: 104300 | Y36: 52150 | Z36: 52150 | AA36: 52150 | AB36: 52150 | BV36: =SUM(AB36:BU36) -> 52150 | BW36: Pagado | BX36: =+BX34+BX35 -> 18033553 | BY36: =+BY34+BY35 -> 85979426 | BZ36: =+BX36+BY36 -> 1.0401298e+08 | CA36: =+H36+AB36+AC36+AD36+AE36+AF36+AG36 -> 312900 | CE36: =+CC36-CD36 -> 0
B37: └ 1-7-2 Gastos Operativos Generales | D37: =SUM(J37:AB37) -> 624071.78 | G37: 46500 | H37: 569970.93 | I37: =IF(H$45=0,0,H37/H$45) -> 0.0011850622 | U37: 191502.06 | W37: 8080.64 | X37: 207605.89 | Y37: 54227.11 | Z37: 54302.87 | AA37: 54252.36 | AB37: 54100.85 | BV37: =SUM(AB37:BU37) -> 54100.85 | BW37: Según Flujo | BX37: 25745271 | BY37: 1.5403742e+08 | BZ37: =+BX37+BY37 -> 1.7978269e+08 | CA37: =+H37+AB37+AC37+AD37+AE37+AF37+AG37 -> 624071.78 | CE37: =+CC37-CD37 -> 0
B38: └ 1-7-3 Equipos y Transporte | D38: =SUM(J38:AB38) -> 3790569 | G38: 427200 | H38: 3363369 | I38: =IF(H$45=0,0,H38/H$45) -> 0.0069929907 | U38: 52569 | X38: 2029200 | Y38: 427200 | Z38: 427200 | AA38: 427200 | AB38: 427200 | BV38: =SUM(AB38:BU38) -> 427200 | BW38: Pendiente de Pagar a jun-26 | BX38: =+BX36-BX37 -> -7711718.3 | BY38: =+BY36-BY37 -> -68057996 | BZ38: =+BX38+BY38 -> -75769715 | CA38: =+H38+AB38+AC38+AD38+AE38+AF38+AG38 -> 3790569 | CE38: =+CC38-CD38 -> 0
B39: └ 1-7-4 Vigilancia | D39: =SUM(J39:AB39) -> 1113920 | G39: 90246.4 | H39: 1023673.6 | I39: =IF(H$45=0,0,H39/H$45) -> 0.0021283838 | P39: 92323.2 | Q39: 92700.8 | R39: 96854.4 | S39: 90246.4 | T39: 92700.8 | U39: 94400 | V39: 92700.8 | W39: 94777.6 | X39: 85337.6 | Z39: 94777.6 | AA39: 96854.4 | AB39: 90246.4 | BV39: =SUM(AB39:BU39) -> 90246.4 | CA39: =+H39+AB39+AC39+AD39+AE39+AF39+AG39 -> 1113920 | CE39: =+CC39-CD39 -> 0
B40: └ 1-7-5 Póliza TRC | D40: =SUM(J40:AB40) -> 1387882 | G40: 61953.05 | H40: 1387882 | I40: =IF(H$45=0,0,H40/H$45) -> 0.0028856321 | Y40: 1387882 | BV40: =SUM(AB40:BU40) -> 0 | CA40: =+H40+AB40+AC40+AD40+AE40+AF40+AG40 -> 1387882 | CE40: =+CC40-CD40 -> 0
B41: └ 1-7-6 Campamento | D41: =SUM(J41:AB41) -> 1065503 | G41: 101500 | H41: 964002.99 | I41: =IF(H$45=0,0,H41/H$45) -> 0.0020043189 | P41: 54785.34 | U41: -5782.35 | X41: 610500 | Y41: 101500 | Z41: 101500 | AA41: 101500 | AB41: 101500 | BV41: =SUM(AB41:BU41) -> 101500 | CA41: =+H41+AB41+AC41+AD41+AE41+AF41+AG41 -> 1065503 | CE41: =+CC41-CD41 -> 0
B42: └ 1-7-7 Otros Gastos | D42: =SUM(J42:AB42) -> 0 | I42: =IF(H$45=0,0,H42/H$45) -> 0 | BV42: =SUM(AB42:BU42) -> 0 | CA42: =+H42+AB42+AC42+AD42+AE42+AF42+AG42 -> 0 | CE42: =+CC42-CD42 -> 0
B43: 1-8 Fondo de Contingencia | C43: 39726806 | D43: =SUM(J43:AB43) -> 0 | E43: =+C43-D43 -> 39726806 | H43: =+D43+F43-G43 -> 0 | I43: =IF(H$45=0,0,H43/H$45) -> 0 | BV43: =SUM(AB43:BU43) -> 0 | CA43: =+H43+AB43+AC43+AD43+AE43+AF43+AG43 -> 0
B44: 1-9 Inspección Técnica | C44: 19264643 | D44: =SUM(J44:AB44) -> 5069643 | E44: =+C44-D44 -> 14195000 | G44: 506964.3 | H44: =+D44+F44-G44 -> 4562678.7 | I44: =IF(H$45=0,0,H44/H$45) -> 0.0094865504 | T44: 1013928.6 | U44: 506964.3 | V44: 506964.3 | W44: 506964.3 | X44: 506964.3 | Y44: 506964.3 | Z44: 506964.3 | AA44: 506964.3 | AB44: 506964.3 | AC44: 506964.3 | AD44: 506964.3 | AE44: 506964.3 | AF44: 506964.3 | AG44: 506964.3 | AH44: 506964.3 | AJ44: 506964.3 | AK44: 506964.3 | AL44: 506964.3 | AM44: 506964.3 | AN44: 506964.3 | AO44: 506964.3 | AP44: 506964.3 | AQ44: 506964.3 | AR44: 506964.3 | AS44: 506964.3 | AT44: 506964.3 | AU44: 506964.3 | AV44: 506964.3 | AW44: 506964.3 | AX44: 506964.3 | AY44: 506964.3 | AZ44: 506964.3 | BA44: 506964.3 | BB44: 506964.3 | BC44: 506964.3 | BD44: 506964.3 | BE44: 506964.3 | BV44: =SUM(AB44:BU44) -> 14701965 | CA44: =+H44+AB44+AC44+AD44+AE44+AF44+AG44 -> 7604464.5
B45: COSTOS DE CONSTRUCCIÓN | C45: =+C30+C31+C32+C33+C34+C35+C43+C44 -> 2.4593251e+09 | D45: =+D30+D31+D32+D33+D34+D35+D43+D44 -> 4.8633725e+08 | E45: =+E30+E31+E32+E33+E34+E35+E43+E44 -> 1.9729878e+09 | F45: 7518544.2 | G45: 12086111 | H45: =+H30+H31+H32+H33+H34+H35+H43+H44 -> 4.8096289e+08 | I45: =IF(H$75=0,0,H45/H$75) -> 0.68418826 | J45: =+J30+J31+J32+J33+J34+J35+J43+J44 -> 1.260156e+08 | K45: =+K30+K31+K32+K33+K34+K35+K43+K44 -> 2198149.8 | L45: =+L30+L31+L32+L33+L34+L35+L43+L44 -> 0 | M45: =+M30+M31+M32+M33+M34+M35+M43+M44 -> 1031320 | N45: =+N30+N31+N32+N33+N34+N35+N43+N44 -> 2917590 | O45: =+O30+O31+O32+O33+O34+O35+O43+O44 -> 2525543.4 | P45: =+P30+P31+P32+P33+P34+P35+P43+P44 -> 2966782.2 | Q45: =+Q30+Q31+Q32+Q33+Q34+Q35+Q43+Q44 -> 20801532 | ... AH45: =+AH30+AH31+AH32+AH33+AH34+AH35+AH43+AH44 -> 65751774 | AI45: =SUM(AB45:AH45)+H45 -> 1.0202357e+09 | AJ45: =+AJ30+AJ31+AJ32+AJ33+AJ34+AJ35+AJ43+AJ44 -> 87969675 | AK45: =+AK30+AK31+AK32+AK33+AK34+AK35+AK43+AK44 -> 1.3259172e+08 | AL45: =+AL30+AL31+AL32+AL33+AL34+AL35+AL43+AL44 -> 78103779 | AM45: =+AM30+AM31+AM32+AM33+AM34+AM35+AM43+AM44 -> 69471737 | AN45: =+AN30+AN31+AN32+AN33+AN34+AN35+AN43+AN44 -> 84780953 | AO45: =+AO30+AO31+AO32+AO33+AO34+AO35+AO43+AO44 -> 69866645 | AP45: =+AP30+AP31+AP32+AP33+AP34+AP35+AP43+AP44 -> 41292421 | AQ45: =+AQ30+AQ31+AQ32+AQ33+AQ34+AQ35+AQ43+AQ44 -> 81454131 | ... BV45: =+BV30+BV31+BV32+BV33+BV34+BV35+BV43+BV44 -> 2.1049015e+09 | CA45: =+CA30+CA31+CA32+CA33+CA34+CA35+CA43+CA44 -> 9.5448392e+08
B46: ◆ GASTOS OPERATIVOS
B47: 2-1 Gerencia de la Promotora | C47: 1.8751053e+08 | D47: =SUM(J47:AB47) -> 26835783 | E47: =+C47-D47 -> 1.6067474e+08 | H47: =+D47+F47-G47 -> 26835783 | I47: =IF(H$68=0,0,H47/H$68) -> 0.14905683 | J47: 161175.97 | N47: 1770000 | O47: 1770000 | P47: 1770000 | Q47: 1770000 | R47: 1770000 | S47: 1770000 | T47: 1770000 | U47: 1770000 | V47: 1770000 | W47: 1770000 | X47: 1770000 | Y47: 1770000 | Z47: 1833058 | AA47: 1818545.2 | AB47: 1783003.6 | AC47: 1764604 | AD47: 1764604 | AE47: 3529209 | AF47: 3529209 | AG47: 3529209 | AH47: 4736487 | AJ47: 6306009 | AK47: 9551249 | AL47: 5588490 | AM47: 4960705 | AN47: 6074102 | AO47: 4989425 | AP47: 2911300 | AQ47: 5832152 | AR47: 5023203 | AS47: 4355405 | AT47: 7091952 | AU47: 4152288 | AV47: 3724154 | AW47: 9193282 | AX47: 5768032 | AY47: 4237520 | AZ47: 4530073 | BA47: 3167361 | BB47: 3196696 | BC47: 4109811 | BD47: 2160590 | BE47: 2136424 | BF47: 1718417 | BG47: 577471 | BV47: =SUM(AB47:BU47) -> 1.3199244e+08 | CA47: =+H47+AB47+AC47+AD47+AE47+AF47+AG47 -> 42735621
B48: 2-2 Gerencia de Ventas | C48: 3.2774615e+08 | D48: =SUM(J48:AB48) -> 1.1724832e+08 | E48: =+C48-D48 -> 2.1049783e+08 | G48: 4213466.9 | H48: =+D48+F48-G48 -> 1.1303485e+08 | I48: =IF(H$68=0,0,H48/H$68) -> 0.62784145 | J48: 559355.54 | L48: 645765.21 | M48: 595001.35 | N48: 1549872.5 | O48: 1423527.6 | P48: 1733909.8 | Q48: 7890097.2 | R48: 16166710 | S48: 11886550 | T48: 12659941 | U48: 15204798 | V48: 5614678.3 | W48: 5336475.7 | X48: 3557189.5 | Y48: 9528645.2 | Z48: 5807715.2 | AA48: 7569317.1 | AB48: =SUM(AB49:AB52) -> 9518771 | AC48: 10573141 | AD48: 10573141 | AE48: 10573141 | AF48: 10573141 | AG48: 10573141 | AH48: 10573141 | AJ48: 10573141 | AK48: 10573141 | AL48: 10573141 | AM48: 10573141 | AN48: 10573141 | AO48: 10573141 | AP48: 10573141 | AQ48: 10573141 | AR48: 10573141 | AS48: 10573141 | AT48: 10573141 | AU48: 10573141 | AV48: 10573141 | AW48: 8809848 | AX48: 7634319 | AY48: 1756676 | AZ48: 1756676 | BA48: 1756676 | BB48: 1756676 | BC48: 1756676 | BD48: 1756676 | BE48: 1756676 | BF48: 1756676 | BG48: 1756676 | BH48: 1756676 | BI48: 1756676 | BJ48: 1756676 | BK48: 1756676 | BL48: 1756676 | BM48: 1756676 | BN48: 1756676 | BO48: 1713916 | BP48: 1390836 | BQ48: 1390836 | BR48: 1390836 | BS48: 1145486 | BT48: 1123688 | BU48: 1123688 | BV48: =SUM(AB48:BU48) -> 2.6423872e+08 | CA48: =+H48+AB48+AC48+AD48+AE48+AF48+AG48 -> 1.7541933e+08
B49: └ 2-2-1 Comisiones por Venta | D49: =SUM(J49:AB49) -> 86405575 | G49: 4011222.4 | H49: 79374170 | I49: =IF(H$68=0,0,H49/H$68) -> 0.44087636 | Q49: 6290641.7 | R49: 14391880 | S49: 9799035.5 | T49: 10674167 | U49: 12853060 | V49: 3427746.4 | W49: 3349220.4 | X49: 1786576.2 | Y49: 7825189.7 | Z49: 3904479.1 | AA49: 5072174.2 | AB49: 7031404.5 | BV49: =SUM(AB49:BU49) -> 7031404.5 | CA49: =+H49+AB49+AC49+AD49+AE49+AF49+AG49 -> 86405575
B50: └ 2-2-2 Administración de la Venta | D50: =SUM(J50:AB50) -> 11539314 | H50: 10782128 | I50: =IF(H$68=0,0,H50/H$68) -> 0.059888317 | N50: 767000 | O50: 767000 | P50: 767000 | Q50: 767000 | R50: 767000 | S50: 767000 | T50: 767000 | U50: 767000 | V50: 767000 | W50: 767000 | X50: 767000 | Y50: 783295.8 | Z50: 770819.66 | AA50: 791013 | AB50: 757185.94 | BV50: =SUM(AB50:BU50) -> 757185.94 | CA50: =+H50+AB50+AC50+AD50+AE50+AF50+AG50 -> 11539314
B51: └ 2-2-3 Equipo de Trabajo Oficina de Ventas | D51: =SUM(J51:AB51) -> 17858976 | H51: 16260807 | I51: =IF(H$68=0,0,H51/H$68) -> 0.090319121 | J51: 559355.54 | L51: 645765.21 | M51: 595001.35 | N51: 677173.63 | O51: 620535.91 | P51: 825710.8 | Q51: 832455.53 | R51: 941719.5 | S51: 1237302.5 | T51: 1132936.9 | U51: 1276808.7 | V51: 1311409.7 | W51: 1120340.3 | X51: 924788.11 | Y51: 905264.29 | Z51: 1047302.9 | AA51: 1606936 | AB51: 1598169.6 | BV51: =SUM(AB51:BU51) -> 1598169.6 | CA51: =+H51+AB51+AC51+AD51+AE51+AF51+AG51 -> 17858976
B52: └ 2-2-4 Gastos Operativos Oficina de Ventas | D52: =SUM(J52:AB52) -> 1444454.4 | G52: 202244.53 | H52: 1312443.5 | I52: =IF(H$68=0,0,H52/H$68) -> 0.0072898438 | N52: 105698.84 | O52: 35991.7 | P52: 141199.04 | R52: 66110.39 | S52: 83212.27 | T52: 85836.93 | U52: 307928.98 | V52: 108522.24 | W52: 99915.09 | X52: 78825.18 | Y52: 14895.35 | Z52: 85113.54 | AA52: 99193.94 | AB52: 132010.93 | BV52: =SUM(AB52:BU52) -> 132010.93 | CA52: =+H52+AB52+AC52+AD52+AE52+AF52+AG52 -> 1444454.4
B53: 2-3 Administración Fiduciaria | C53: 81458723 | D53: =SUM(J53:AB53) -> 6982961.1 | E53: =+C53-D53 -> 74475762 | G53: 293802.58 | H53: =+D53+F53-G53 -> 6689158.5 | I53: =IF(H$68=0,0,H53/H$68) -> 0.037154301 | J53: 373034.61 | K53: 43563.47 | L53: 36723.13 | M53: 37034.89 | N53: 51335.37 | O53: 125971.53 | P53: 205035.01 | Q53: 193826.15 | R53: 228402.98 | S53: 824240.62 | T53: 143558.05 | U53: 111569.53 | V53: 187644.31 | W53: 111272.46 | X53: 1296067.7 | Y53: 578468.84 | Z53: 596002.47 | AA53: 770633.69 | AB53: =SUM(AB54:AB55) -> 1068576.3 | AC53: 800000 | AD53: 800000 | AE53: 800000 | AF53: 800000 | AG53: 800000 | AH53: 1358750 | AJ53: 1358750 | AK53: 1358750 | AL53: 1358750 | AM53: 1358750 | AN53: 1358750 | AO53: 1358750 | AP53: 1358750 | AQ53: 1358750 | AR53: 1358750 | AS53: 1358750 | AT53: 1358750 | AU53: 1358750 | AV53: 1358750 | AW53: 1358750 | AX53: 1358750 | AY53: 1358750 | AZ53: 1358750 | BA53: 1358750 | BB53: 1358750 | BC53: 1358750 | BD53: 1358750 | BE53: 1358750 | BF53: 1358750 | BG53: 1358750 | BH53: 1358750 | BI53: 1358750 | BJ53: 1358750 | BK53: 1358750 | BL53: 1358750 | BM53: 1358750 | BN53: 1358750 | BO53: 1358750 | BP53: 1358750 | BQ53: 1358750 | BR53: 1358750 | BS53: 1358750 | BT53: 1358750 | BU53: 1358750 | BV53: =SUM(AB53:BU53) -> 58059826 | CA53: =+H53+AB53+AC53+AD53+AE53+AF53+AG53 -> 11757735
B54: └ 2-3-1 Adm. General de la Fiduciaria | D54: =SUM(J54:AB54) -> 5022538.1 | H54: 4247764.4 | I54: =IF(H$68=0,0,H54/H$68) -> 0.023593807 | J54: 344499.26 | K54: 36279.57 | L54: 36723.13 | M54: 37034.89 | N54: 37423.76 | O54: 34807.29 | P54: 35695 | Q54: 35546.73 | R54: 36234.2 | S54: 627694.69 | T54: 37152.89 | U54: 37296.32 | V54: 113391.16 | W54: 37257.67 | X54: 1216866.4 | Y54: 486278.51 | Z54: 498144.27 | AA54: 559438.58 | AB54: 774773.75 | BV54: =SUM(AB54:BU54) -> 774773.75 | CA54: =+H54+AB54+AC54+AD54+AE54+AF54+AG54 -> 5022538.1
B55: └ 2-3-2 Debida Diligencia / Fiduciaria | D55: =SUM(J55:AB55) -> 1960423 | G55: 293802.58 | H55: 1666620.4 | I55: =IF(H$68=0,0,H55/H$68) -> 0.0092570862 | J55: 28535.35 | K55: 7283.9 | N55: 13911.61 | O55: 91164.24 | P55: 169340.01 | Q55: 158279.42 | R55: 192168.78 | S55: 196545.93 | T55: 106405.16 | U55: 74273.21 | V55: 74253.15 | W55: 74014.79 | X55: 79201.23 | Y55: 92190.33 | Z55: 97858.2 | AA55: 211195.11 | AB55: 293802.58 | BV55: =SUM(AB55:BU55) -> 293802.58 | CA55: =+H55+AB55+AC55+AD55+AE55+AF55+AG55 -> 1960423
B56: 2-4 Promoción y Publicidad | C56: 69521911 | D56: =SUM(J56:AB56) -> 34333891 | E56: =+C56-D56 -> 35188020 | G56: 856426.95 | H56: =+D56+F56-G56 -> 33477464 | I56: =IF(H$68=0,0,H56/H$68) -> 0.18594742 | J56: 11066720 | K56: 915790.08 | L56: 1931201.9 | M56: 1103623.2 | N56: 807731.34 | O56: 740040.2 | P56: 1412884.7 | Q56: 3494146.4 | R56: 184710.13 | S56: 551935.68 | T56: 1245788.4 | U56: 949800.34 | V56: 984721.38 | W56: 938693.31 | X56: 882717.03 | Y56: 1443186.7 | Z56: 1372155.5 | AA56: 1943642.6 | AB56: =SUM(AB57:AB64) -> 2364401.5 | AC56: 1600000 | AD56: 1600000 | AE56: 1600000 | AF56: 1600000 | AG56: 1600000 | AH56: 1170905 | AJ56: 1170905 | AK56: 1170905 | AL56: 1170905 | AM56: 1170905 | AN56: 1170905 | AO56: 1170905 | AP56: 1170905 | AQ56: 1170905 | AR56: 1170905 | AS56: 1170905 | AT56: 1170905 | AU56: 1170905 | AV56: 1170905 | AW56: 1170905 | AX56: 1170905 | AY56: 490452 | BV56: =SUM(AB56:BU56) -> 29589334 | CA56: =+H56+AB56+AC56+AD56+AE56+AF56+AG56 -> 43841865
B57: └ 2-4-1 Apartamento Modelo / Show Room | D57: =SUM(J57:AB57) -> 5143605.2 | H57: 5143605.2 | I57: =IF(H$68=0,0,H57/H$68) -> 0.028569671 | J57: 5993469.7 | K57: 292040.78 | M57: 149662.62 | N57: 167745.43 | P57: 258175.66 | R57: -1537035 | U57: -180453.94 | BV57: =SUM(AB57:BU57) -> 0 | CA57: =+H57+AB57+AC57+AD57+AE57+AF57+AG57 -> 5143605.2
B58: └ 2-4-2 Inversión Inicial Promoción y Mercadeo | D58: =SUM(J58:AB58) -> 11245197 | G58: -14760.54 | H58: 11245197 | I58: =IF(H$68=0,0,H58/H$68) -> 0.062460389 | J58: 4481135.7 | K58: 57400.51 | L58: 1795826.4 | M58: 187959.76 | N58: 188099.53 | O58: 192037.45 | P58: 179220.89 | Q58: 2902845.2 | R58: 1207725.2 | S58: 52946.6 | BV58: =SUM(AB58:BU58) -> 0 | CA58: =+H58+AB58+AC58+AD58+AE58+AF58+AG58 -> 11245197
B59: └ 2-4-3 Medios Digitales (Campaña y Redes) | D59: =SUM(J59:AB59) -> 4000132.3 | G59: 99358.92 | H59: 3632136.3 | I59: =IF(H$68=0,0,H59/H$68) -> 0.020174359 | M59: 74992.79 | N59: 52091.04 | O59: 129162.79 | P59: 186272.04 | Q59: 234473.14 | R59: 259817.28 | S59: 122677.4 | T59: 196734.06 | U59: 257568.44 | V59: 176353.58 | W59: 337884.2 | X59: 114023.92 | Y59: 472859.2 | Z59: 366567.64 | AA59: 650658.78 | AB59: 367996.01 | BV59: =SUM(AB59:BU59) -> 367996.01 | CA59: =+H59+AB59+AC59+AD59+AE59+AF59+AG59 -> 4000132.3
B60: └ 2-4-4 Community Management | D60: =SUM(J60:AB60) -> 4772335.5 | G60: 299997 | H60: 4194472.1 | I60: =IF(H$68=0,0,H60/H$68) -> 0.0232978 | K60: 435604.79 | M60: 147972 | N60: 149742 | O60: 142190 | P60: 142190 | Q60: 144432 | R60: 144698.68 | S60: 245567.68 | T60: 316570.4 | U60: 325416.5 | V60: 319751.11 | W60: 318842.61 | X60: 245440 | Y60: 384208 | Z60: 328204.02 | AA60: 403642.3 | AB60: 577863.4 | BV60: =SUM(AB60:BU60) -> 577863.4 | CA60: =+H60+AB60+AC60+AD60+AE60+AF60+AG60 -> 4772335.5
B61: └ 2-4-5 Vallas Publicitarias | D61: =SUM(J61:AB61) -> 3275050.5 | G61: 232709.5 | H61: 3042341 | I61: =IF(H$68=0,0,H61/H$68) -> 0.016898397 | J61: 559615 | K61: 130744 | L61: 130744 | M61: 130744 | N61: 130744 | O61: 109504 | P61: 109504 | Q61: 88264 | R61: 109504 | S61: 130744 | T61: 70800 | U61: 21240 | V61: 278729.5 | W61: 281966.5 | X61: 146325.5 | Y61: 190229.5 | Z61: 232709.5 | AA61: 190229.5 | AB61: 232709.5 | BV61: =SUM(AB61:BU61) -> 232709.5 | CA61: =+H61+AB61+AC61+AD61+AE61+AF61+AG61 -> 3275050.5
B62: └ 2-4-6 Materiales POP | D62: =SUM(J62:AB62) -> 1777671.1 | H62: 1777671.1 | I62: =IF(H$68=0,0,H62/H$68) -> 0.0098739068 | J62: 32500 | L62: 4631.5 | M62: 826 | N62: 138130.34 | O62: 167145.96 | P62: 537522.12 | Q62: 124132 | T62: 216162.42 | U62: 12555.41 | V62: 208600 | Z62: 335465.36 | BV62: =SUM(AB62:BU62) -> 0 | CA62: =+H62+AB62+AC62+AD62+AE62+AF62+AG62 -> 1777671.1
B63: └ 2-4-7 Feria y Eventos Publicitarios | D63: =SUM(J63:AB63) -> 3633762.2 | G63: 239122.07 | H63: 2447929.6 | I63: =IF(H$68=0,0,H63/H$68) -> 0.013596794 | M63: 411466 | N63: -18821 | T63: 445521.5 | U63: 513473.93 | V63: 1287.19 | Y63: 395890 | AA63: 699111.98 | AB63: 1185832.6 | BV63: =SUM(AB63:BU63) -> 1185832.6 | CA63: =+H63+AB63+AC63+AD63+AE63+AF63+AG63 -> 3633762.2
B64: └ 2-4-8 Programa de Referidos | D64: =SUM(J64:AB64) -> 486136.61 | H64: 486136.61 | I64: =IF(H$68=0,0,H64/H$68) -> 0.0027002 | X64: 376927.61 | Z64: 109209 | BV64: =SUM(AB64:BU64) -> 0 | CA64: =+H64+AB64+AC64+AD64+AE64+AF64+AG64 -> 486136.61
B65: 2-5 Post Ventas | C65: 19863403 | D65: =SUM(J65:AB65) -> 0 | E65: =+C65-D65 -> 19863403 | H65: =+D65+F65-G65 -> 0 | I65: =IF(H$68=0,0,H65/H$68) -> 0 | AP65: 541413 | AQ65: 541413 | AR65: 541413 | AS65: 541413 | AT65: 541413 | AU65: 541413 | AV65: 541413 | AW65: 541413 | AX65: 541413 | AY65: 541413 | AZ65: 541413 | BA65: 541413 | BB65: 541413 | BC65: 541413 | BD65: 541413 | BE65: 541413 | BF65: 541413 | BG65: 541413 | BH65: 541413 | BI65: 541413 | BJ65: 541413 | BK65: 541413 | BL65: 541413 | BM65: 541413 | BN65: 541413 | BO65: 541413 | BP65: 541413 | BQ65: 541413 | BR65: 541413 | BS65: 541413 | BT65: 541413 | BU65: 541413 | BV65: =SUM(AB65:BU65) -> 17325216 | CA65: =+H65+AB65+AC65+AD65+AE65+AF65+AG65 -> 0
B66: └ 2-5-1 Administración Condominio | D66: =SUM(J66:AB66) -> 0 | I66: =IF(C66=0,0,D66/C66) -> 0 | CA66: =+H66+AB66+AC66+AD66+AE66+AF66+AG66 -> 0
B67: └ 2-5-2 Gastos Operativos Post-Venta | D67: =SUM(J67:AB67) -> 0 | I67: =IF(C67=0,0,D67/C67) -> 0 | CA67: =+H67+AB67+AC67+AD67+AE67+AF67+AG67 -> 0
B68: GASTOS OPERATIVOS | C68: =+C47+C48+C53+C56+C65 -> 6.8610072e+08 | D68: =+D47+D48+D53+D56+D65 -> 1.8540095e+08 | E68: =+E47+E48+E53+E56+E65 -> 5.0069976e+08 | G68: 5363696.4 | H68: =+H47+H48+H53+H56+H65 -> 1.8003726e+08 | I68: =IF(H$75=0,0,H68/H$75) -> 0.25610994 | J68: =+J47+J48+J53+J56+J65 -> 12160286 | K68: =+K47+K48+K53+K56+K65 -> 959353.55 | L68: =+L47+L48+L53+L56+L65 -> 2613690.2 | M68: =+M47+M48+M53+M56+M65 -> 1735659.4 | N68: =+N47+N48+N53+N56+N65 -> 4178939.2 | O68: =+O47+O48+O53+O56+O65 -> 4059539.3 | P68: =+P47+P48+P53+P56+P65 -> 5121829.6 | Q68: =+Q47+Q48+Q53+Q56+Q65 -> 13348070 | ... AH68: =+AH47+AH48+AH53+AH56+AH65 -> 17839283 | AI68: =SUM(AB68:AH68)+H68 -> 2.9159383e+08 | AJ68: =+AJ47+AJ48+AJ53+AJ56+AJ65 -> 19408805 | AK68: =+AK47+AK48+AK53+AK56+AK65 -> 22654045 | AL68: =+AL47+AL48+AL53+AL56+AL65 -> 18691286 | AM68: =+AM47+AM48+AM53+AM56+AM65 -> 18063501 | AN68: =+AN47+AN48+AN53+AN56+AN65 -> 19176898 | AO68: =+AO47+AO48+AO53+AO56+AO65 -> 18092221 | AP68: =+AP47+AP48+AP53+AP56+AP65 -> 16555509 | AQ68: =+AQ47+AQ48+AQ53+AQ56+AQ65 -> 19476361 | ... CA68: =+CA47+CA48+CA53+CA56+CA65 -> 2.7375455e+08
B69: ◆ OTROS GASTOS
B70: 3-1 Permisos y Preliminares | C70: 30500000 | D70: =SUM(J70:AB70) -> 23156922 | E70: =+C70-D70 -> 7343078.1 | F70: 1691904.6 | G70: 311364.64 | H70: =+D70+F70-G70 -> 24537462 | I70: =IF(H$73=0,0,H70/H$73) -> 0.58466385 | J70: 12715384 | M70: 128745.38 | N70: 552632.58 | O70: 120006 | P70: 535636 | Q70: 3007800 | R70: 223322.53 | S70: -405849.76 | T70: 842419.7 | U70: 339222.22 | V70: 2552697.4 | W70: 517341.31 | Y70: 347884.07 | Z70: 1360886.6 | AA70: 190305.57 | AB70: =118333.33+10154.66 -> 128487.99 | AC70: 800000 | AE70: 400000 | BV70: =SUM(AB70:BU70) -> 1328488 | CA70: =+H70+AB70+AC70+AD70+AE70+AF70+AG70 -> 25865950
B71: 3-2 Imprevistos | C71: 19863403 | D71: =SUM(J71:AB71) -> 0 | E71: =+C71-D71 -> 19863403 | H71: =+D71+F71-G71 -> 0 | I71: =IF(H$73=0,0,H71/H$73) -> 0 | AP71: 541413 | AQ71: 541413 | AR71: 541413 | AS71: 541413 | AT71: 541413 | AU71: 541413 | AV71: 541413 | AW71: 541413 | AX71: 541413 | AY71: 541413 | AZ71: 541413 | BA71: 541413 | BB71: 541413 | BC71: 541413 | BD71: 541413 | BE71: 541413 | BF71: 541413 | BG71: 541413 | BH71: 541413 | BI71: 541413 | BJ71: 541413 | BK71: 541413 | BL71: 541413 | BM71: 541413 | BN71: 541413 | BO71: 541413 | BP71: 541413 | BQ71: 541413 | BR71: 541413 | BS71: 541413 | BT71: 541413 | BU71: 541413 | BV71: =SUM(AB71:BU71) -> 17325216 | CA71: =+H71+AB71+AC71+AD71+AE71+AF71+AG71 -> 0
B72: 3-3 Gastos Financieros | C72: 2.3273921e+08 | D72: =SUM(J72:AB72) -> 17431033 | E72: =+C72-D72 -> 2.1530818e+08 | H72: =+D72+F72-G72 -> 17431033 | I72: =IF(H$73=0,0,H72/H$73) -> 0.41533615 | Q72: 1169797.6 | R72: -1169797.6 | U72: 5900 | V72: 4408448 | Y72: 8473629.7 | Z72: -9722.22 | AA72: 2750000 | AB72: 1802777.8 | AC72: =+'Intereses 06-26'!Z39 -> 2447916.7 | AD72: =+'Intereses 06-26'!AA39 -> 4937500 | AE72: =+'Intereses 06-26'!AB39 -> 6937500 | AF72: =+'Intereses 06-26'!AC39 -> 3718750 | AG72: =+'Intereses 06-26'!AD39 -> 4989583.3 | AH72: 4403333.3 | AJ72: 5623333.3 | AK72: 5623333.3 | AL72: 6843333.3 | AM72: 7093333.3 | AN72: 8313333.3 | AO72: 7946925.2 | AP72: 7810515.6 | AQ72: 7567852 | AR72: 7093109.6 | AS72: 6537145.7 | AT72: 6661326.5 | AU72: 5761400.1 | AV72: 5179332.1 | AW72: 3849727.2 | AX72: 3531419.4 | AY72: 3531419.4 | AZ72: 3449257.7 | BA72: 2947499.6 | BB72: 2527292.5 | BC72: 2159596.3 | BD72: 1799282.9 | BE72: 1555421.2 | BV72: =SUM(AB72:BU72) -> 1.4264255e+08 | CA72: =+H72+AB72+AC72+AD72+AE72+AF72+AG72 -> 42265061
B73: OTROS GASTOS | C73: =+C70+C71+C72 -> 2.8310261e+08 | D73: =+D70+D71+D72 -> 40587955 | E73: =+E70+E71+E72 -> 2.4251466e+08 | F73: 1691904.6 | G73: 311364.64 | H73: =+H70+H71+H72 -> 41968495 | I73: =IF(H$75=0,0,H73/H$75) -> 0.059701803 | J73: =+J70+J71+J72 -> 12715384 | K73: =+K70+K71+K72 -> 0 | L73: =+L70+L71+L72 -> 0 | M73: =+M70+M71+M72 -> 128745.38 | N73: =+N70+N71+N72 -> 552632.58 | O73: =+O70+O71+O72 -> 120006 | P73: =+P70+P71+P72 -> 535636 | Q73: =+Q70+Q71+Q72 -> 4177597.5 | ... AA73: =+AA70+AA71+AA72 -> 2940305.6 | AB73: =SUM(AB70:AB72) -> 1931265.8 | AC73: =SUM(AC70:AC72) -> 3247916.7 | AD73: =SUM(AD70:AD72) -> 4937500 | AE73: =SUM(AE70:AE72) -> 7337500 | AF73: =SUM(AF70:AF72) -> 3718750 | AG73: =SUM(AG70:AG72) -> 4989583.3 | AH73: =SUM(AH70:AH72) -> 4403333.3 | AI73: =SUM(AB73:AH73)+H73 -> 72534344 | AJ73: =SUM(AJ70:AJ72) -> 5623333.3 | AK73: =SUM(AK70:AK72) -> 5623333.3 | AL73: =SUM(AL70:AL72) -> 6843333.3 | AM73: =SUM(AM70:AM72) -> 7093333.3 | AN73: =SUM(AN70:AN72) -> 8313333.3 | AO73: =SUM(AO70:AO72) -> 7946925.2 | AP73: =SUM(AP70:AP72) -> 8351928.6 | AQ73: =SUM(AQ70:AQ72) -> 8109265 | ... CA73: =SUM(CA70:CA72) -> 68131011
B75: TOTALES GENERALES RD$ | C75: =+C45+C68+C73 -> 3.4285284e+09 | D75: =+D45+D68+D73 -> 7.1232616e+08 | E75: =+E45+E68+E73 -> 2.7162023e+09 | F75: 9210448.9 | G75: 18627535 | H75: =+H45+H68+H73 -> 7.0296864e+08 | I75: =+I45+I68+I73 -> 1 | J75: =+J45+J68+J73 -> 1.5089127e+08 | K75: =+K45+K68+K73 -> 3157503.3 | L75: =+L45+L68+L73 -> 2613690.2 | M75: =+M45+M68+M73 -> 2895724.8 | N75: =+N45+N68+N73 -> 7649161.8 | O75: =+O45+O68+O73 -> 6705088.7 | ... AH75: =+AH45+AH68+AH73 -> 87994391 | AI75: =SUM(AB75:AH75)+H75 -> 1.3843639e+09 | AJ75: =+AJ45+AJ68+AJ73 -> 1.1300181e+08 | AK75: =+AK45+AK68+AK73 -> 1.608691e+08 | AL75: =+AL45+AL68+AL73 -> 1.036384e+08 | AM75: =+AM45+AM68+AM73 -> 94628572 | AN75: =+AN45+AN68+AN73 -> 1.1227118e+08 | AO75: =+AO45+AO68+AO73 -> 95905791 | AP75: =+AP45+AP68+AP73 -> 66199859 | AQ75: =+AQ45+AQ68+AQ73 -> 1.0903976e+08 | ... CA75: =+CA45+CA68+CA73 -> 1.2963695e+09
B76: TOTALES GENERALES ACUMULADOS RD$ | C76: =+C46+C69+C74 -> 0 | D76: =+D46+D69+D74 -> 0 | E76: =+E46+E69+E74 -> 0 | F76: =+F46+F69+F74 -> 0 | G76: =+G46+G69+G74 -> 0 | H76: =+H46+H69+H74 -> 0 | I76: =IF(C76=0,0,D76/C76) -> 0 | J76: =+J75 -> 1.5089127e+08 | K76: =+J76+K75 -> 1.5404878e+08 | L76: =+K76+L75 -> 1.5666247e+08 | M76: =+L76+M75 -> 1.5955819e+08 | N76: =+M76+N75 -> 1.6720735e+08 | O76: =+N76+O75 -> 1.7391244e+08 | P76: =+O76+P75 -> 1.8253669e+08 | Q76: =+P76+Q75 -> 2.2086389e+08 | R76: =+Q76+R75 -> 4.1783302e+08 | ... Z76: =+Y76+Z75 -> 6.1396087e+08 | AA76: =+Z76+AA75-G75+F75 -> 6.5391017e+08 | AB76: =+AA76+AB75 -> 7.0290908e+08 | AC76: =+AB76+AC75 -> 8.4660971e+08 | AD76: =+AC76+AD75 -> 9.4853625e+08 | AE76: =+AD76+AE75 -> 1.054591e+09 | AF76: =+AE76+AF75 -> 1.1512932e+09 | AG76: =+AF76+AG75 -> 1.247311e+09 | AH76: =+AG76+AH75 -> 1.3353054e+09 | AJ76: =+AH76+AJ75 -> 1.4483072e+09 | AK76: =+AJ76+AK75 -> 1.6091763e+09 | AL76: =+AK76+AL75 -> 1.7128147e+09 | AM76: =+AL76+AM75 -> 1.8074433e+09 | AN76: =+AM76+AN75 -> 1.9197145e+09 | AO76: =+AN76+AO75 -> 2.0156203e+09 | AP76: =+AO76+AP75 -> 2.0818201e+09 | AQ76: =+AP76+AQ75 -> 2.1908599e+09 | AR76: =+AQ76+AR75 -> 2.2874929e+09 | ... BZ76: =+BY76+BZ75 -> 6.1887167e+09 | CA76: =+CA75 -> 1.2963695e+09
B77: Gastos Bancarios | H77: =-273569.56-484512.22-2128.68 -> -760210.46
B78: Retenciones Varias | H78: =3942456+431409+56826 -> 4430691
B79: Fondo Rotatorio | H79: 2021249.3
B80: Desistimientos por pagar | H80: 59566.36
B81: Otras cuentas por pagar | H81: =SUM(H77:H80) -> 5751296.2
B82: NETO (Ingresos − Costos) RD$ | H82: =+AB83 -> 49199807 | AB82: =+AB24-AB75 -> 9327295 | AC82: =+AC24-AC75 -> -25700628 | AD82: =+AD24-AD75 -> 16073455 | AE82: =+AE24-AE75 -> -98054700 | AF82: =+AF24-AF75 -> -78702273 | AG82: =+AG24-AG75 -> 81982219 | AH82: =+AH24-AH75 -> -69994391 | AJ82: =+AJ24-AJ75 -> -1.1300181e+08 | AK82: =+AK24-AK75 -> -1.608691e+08 | AL82: =+AL24-AL75 -> -1.036384e+08 | AM82: =+AM24-AM75 -> -94628572 | AN82: =+AN24-AN75 -> -1.1227118e+08 | AO82: =+AO24-AO75 -> -95905791 | AP82: =+AP24-AP75 -> -66199859 | AQ82: =+AQ24-AQ75 -> -1.0903976e+08 | ... BU82: =+BU24-BU75 -> -3565264 | BV82: =+BV25-BV76 -> -4.9843591e+09 | BW82: =+BW25-BW76 -> -6.1887167e+09 | BX82: =+BX25-BX76 -> -6.1887167e+09 | BY82: =+BY25-BY76 -> -6.1887167e+09 | BZ82: =+BZ25-BZ76 -> -6.1887167e+09 | CA82: =+CA25-CA76 -> -51685688
B83: NETO (Ingresos − Costos) RD$ Acumulados | H83: =+H82 -> 49199807 | AB83: =+AB25-AB76+H81 -> 49199807 | AC83: =+AB83+AC82 -> 23499178 | AD83: =+AC83+AD82 -> 39572633 | AE83: =+AD83+AE82 -> -58482067 | AF83: =+AE83+AF82 -> -1.3718434e+08 | AG83: =+AF83+AG82 -> -55202121 | AH83: =+AG83+AH82 -> -1.2519651e+08 | AI83: =+AH83 -> -1.2519651e+08 | AJ83: =+AH83+AJ82 -> -2.3819832e+08 | AK83: =+AJ83+AK82 -> -3.9906743e+08 | AL83: =+AK83+AL82 -> -5.0270583e+08 | AM83: =+AL83+AM82 -> -5.973344e+08 | AN83: =+AM83+AN82 -> -7.0960558e+08 | AO83: =+AN83+AO82 -> -8.0551137e+08 | AP83: =+AO83+AP82 -> -8.7171123e+08 | AQ83: =+AP83+AQ82 -> -9.8075099e+08 | AR83: =+AQ83+AR82 -> -1.077384e+09 | ... BU83: =+BT83+BU82 -> -2.2112045e+09
