Workbook
Name Calificación: #REF!
Name Garantía: #REF!
Name Marca: #REF!
Name Soporte: #REF!

Sheet DETALLE PRESUPUESTO POR PARTIDA
A1: DETALLE COMPARATIVO POR PARTIDA - PRESUPUESTO EDIFICIO ORIGINAL VS PRESUPUESTO ACTUALIZADO
A2: Se resaltan en amarillo las partidas con observaciones registradas sobre el cambio entre el presupuesto original y el actualizado.
A4: Nº | B4: Código | C4: Descripción de Partida | D4: Unidad | E4: Cant. Original | F4: P.U. Original | G4: Total Original | H4: Cant. Actualizada | I4: P.U. Actualizada | J4: Total Actualizado | K4: Diferencia ($) | L4: Observación
A5: INFRAESTRUCTURA | G5: =SUM(G6:G24) -> 1387237.5 | J5: =SUM(J6:J24) -> 1475727.8 | M5: 1475727.8
A6: 1 | B6: AEDIF01 | C6: REPLANTEO TOPOGRAFICO DE LOSA (COLOCACION DE PUNTOS PARA NIVELES DE LOSA Y DEMARCACIÓN DE RIOSTRA). | D6: M2 | E6: 210.03 | F6: 30.09 | G6: 6319.8 | H6: 210.03 | I6: 30.09 | J6: 6319.8 | K6: =J6-G6 -> 0
A7: 2 | B7: OPREL001 | C7: REPLANTEO GENERAL DE LOSA (COLOCACION DE PUNTOS PARA NIVELES DE LOSA Y DEMARCACIÓN DE RIOSTRA). | D7: M2 | E7: 210.03 | F7: 93.59 | G7: 19656.71 | H7: 210.03 | I7: 93.59 | J7: 19656.71 | K7: =J7-G7 -> 0
A8: 3 | B8: AEDIF36 | C8: NIVELACION Y COMPACTACION CON MATERIAL DE RELLENO. | D8: M3 | E8: 21 | F8: 1470.45 | G8: 30879.45 | H8: 21 | I8: 1470.45 | J8: 30879.45 | K8: =J8-G8 -> 0
A9: 4 | B9: PERFI001 | C9: PREPARACION SUPERFICIE PARA PLATEA, (PERFILAMIENTO Y ACONDICIONAMIENTO DE LOSA). | D9: M2 | E9: 210.03 | F9: 35.3 | G9: 7414.06 | H9: 210.03 | I9: 35.3 | J9: 7414.06 | K9: =J9-G9 -> 0
A10: 5 | B10: OPTCR003 | C10: BOTE DE ESCOMBROS. | D10: M3 | E10: 21 | F10: 901.1542 | G10: 18924.24 | H10: 21 | I10: 901.1542 | J10: 18924.24 | K10: =J10-G10 -> 0
A11: 6 | B11: OPREL003 | C11: FUMIGACION DE CIMIENTOS. | D11: M2 | E11: 210.03 | F11: 112.1 | G11: 23544.36 | H11: 210.03 | I11: 112.1 | J11: 23544.36 | K11: =J11-G11 -> 0
A12: 7 | B12: INFTCR05 | C12: EXCAVACION EN ROCA CON EQUIPO LIVIANO EN INFRAESTRUCTURA, PARA LA CONSTRUCCION DE ZAPATAS, RIOSTRAS Y MUROS. | D12: M3 | E12: 20.3 | F12: 4424.93 | G12: 89826.08 | H12: 20.3 | I12: 4424.93 | J12: 89826.08 | K12: =J12-G12 -> 0
A13: 8 | B13: INFTCR07 | C13: EXCAVACION EN ROCA CON EQUIPO LIVIANO EN INFRAESTRUCTURA, PARA LA CONSTRUCCION DE SOTERRADO DE TUBERIAS. | D13: M3 | E13: 14.24 | F13: 4424.93 | G13: 63011 | H13: 14.24 | I13: 4424.93 | J13: 63011 | K13: =J13-G13 -> 0
A14: 9 | B14: MTTCR001 | C14: BOTE DE MATERIAL DE EXCAVACION (30% DE ESPONJAMIENTO). INCLUYE CARGA A MANO. | D14: M3 | E14: 38.31 | F14: 1625.5006 | G14: 62272.93 | H14: 38.31 | I14: 1625.5006 | J14: 62272.93 | K14: =J14-G14 -> 0
A15: 10 | B15: MTTCR002 | C15: RELLENO O "BEDDING" CON ARENA DE TUBERIAS ELECTRICAS E HIDROSANITARIAS. | D15: M3 | E15: 8 | F15: 2335.81 | G15: 18686.48 | H15: 8 | I15: 2335.81 | J15: 18686.48 | K15: =J15-G15 -> 0
A16: 11 | B16: RELLE01 | C16: SUMINISTRO Y ACARREO DE MATERIAL DE RELLENO | D16: M3 | E16: 6.24 | F16: 3243.38 | G16: 20238.69 | H16: 6.24 | I16: 3243.38 | J16: 20238.69 | K16: =J16-G16 -> 0
A17: 12 | B17: INF012 | C17: SUMINISTRO, TRANSPORTE Y COLOCACION DE ACERO DE REFUERZO EN INFRAESTRUCTURA, VARILLA DE DIAMETRO D= 3/8" PARA REFUERZO EN ZAPATAS, RIOSTRAS Y PLATEA. | D17: QQ | E17: 44.4 | F17: 3761.1 | G17: 166992.84 | H17: 44.49 | I17: 3761.1 | J17: 167331.34 | K17: =J17-G17 -> 338.5 | L17: AUMENTO MINIMO EN CANTIDAD
A18: 13 | B18: AEDIF11 | C18: SUMINISTRO, TRANSPORTE Y COLOCACION DE ACERO DE REFUERZO EN INFRAESTRUCTURA, VARILLA DE DIAMETRO D= 1/2" PARA REFUERZO EN ZAPATAS, RIOSTRAS Y PLATEA. | D18: QQ | E18: 18.3 | F18: 3686.83 | G18: 67468.99 | H18: 22.51 | I18: 3686.83 | J18: 82990.54 | K18: =J18-G18 -> 15521.55 | L18: AUMENTO EN CANTIDAD
A19: 14 | B19: INF022 | C19: SUMINISTRO, TRANSPORTE Y COLOCACION DE ACERO DE REFUERZO EN INFRAESTRUCTURA, VARILLA DE DIAMETRO D= 5/8" PARA REFUERZO EN ZAPATA, RIOSTRAS Y PLATEA. | D19: QQ | E19: 10.53 | F19: 3590.43 | G19: 37807.23 | H19: 12.7 | I19: 4157.04 | J19: 52794.41 | K19: =J19-G19 -> 14987.18 | L19: AUMENTO EN CANTIDAD Y PRECIO DE VARILLA 5/8
A20: 15 | B20: INF023 | C20: SUMINISTRO, TRANSPORTE Y COLOCACION DE ACERO DE REFUERZO EN INFRAESTRUCTURA, VARILLA DE DIAMETRO D= 3/4" PARA REFUERZO EN ZAPATA, RIOSTRAS Y PLATEA. | D20: QQ | E20: 6.58 | F20: 4196.88 | G20: 27615.47 | H20: 7.61 | I20: 4523.72 | J20: 34425.51 | K20: =J20-G20 -> 6810.04 | L20: AUMENTO EN CANTIDAD Y PRECIO DE VARILLA 3/4
A21: 16 | B21: INF014 | C21: SUMINISTRO, TRANSPORTE Y COLOCACION DE ACERO DE REFUERZO EN INFRAESTRUCTURA, MALLA D2.3 x 2.3 - 100x100 PARA REFUERZO EN PLATEA. | D21: M2 | E21: 504.07 | F21: 291.49 | G21: 146931.36 | H21: 504.07 | I21: 266.71 | J21: 134440.51 | K21: =J21-G21 -> -12490.85 | L21: DISMINUCION EN PRECIO DE MALLA D.23.X D2.3
A22: 17 | B22: MADERA 6 | C22: SUMINISTRO, TRANSPORTE Y COLOCACION DE ENCOFRADO MADERA, TIPO RECTO, ACABADO CORRIENTE EN LOSA DE FUNDACION, E=15CMS. | D22: ML | E22: 65.55 | F22: 684.1688 | G22: 44847.26 | H22: 65.55 | I22: 684.1688 | J22: 44847.26 | K22: =J22-G22 -> 0
A23: 18 | B23: INF004 | C23: SUMINISTRO, TRANSPORTE Y COLOCACION DE HOMIGON DE LIMPIEZA EN PLATEA. | D23: M3 | E23: 12.47 | F23: 8660.79 | G23: 108000.05 | H23: 10 | I23: 9098.51 | J23: 90985.1 | K23: =J23-G23 -> -17014.95 | L23: DISMINUCION EN CANTIDAD Y AUMENTO EN EL PRECIO DEL HORMIGON PRECIO UTILIZADO EMPRESA BLUEWAVE
A24: 19 | B24: INF005 | C24: SUMINISTRO, TRANSPORTE Y COLOCACION DE HORMIGON RCC28 = 210 KG/CM2, EN INFRAESTRUCTURA, PARA ACABADO CORRIENTE, EN ZAPATAS, VIGAS Y LOSAS DE FUNDACION. | D24: M3 | E24: 46.73 | F24: 9133.33 | G24: 426800.51 | H24: 52 | I24: 9752.68 | J24: 507139.36 | K24: =J24-G24 -> 80338.85 | L24: AUMENTO EN CANTIDAD Y AUMENTO EN EL PRECIO DEL HORMIGON PRECIO UTILIZADO EMPRESA BLUEWAVE
A25: SUPERESTRUCTURA | G25: =SUM(G26:G39) -> 4310739 | J25: =SUM(J26:J39) -> 4452077.4
A26: 20 | B26: SUP008 | C26: SUMINISTRO, TRANSPORTE Y COLOCACION DE HORMIGON DE RCC 210 KG/CM2 A LOS 28 DIAS ACABADO CORRIENTE EN SUPERESTRUCTURA, PARA LA CONSTRUCCION DE MUROS, VIGAS, LOSA DE ENTREPISO Y OTROS. | D26: M3 | E26: 156.3 | F26: 9487.86 | G26: 1482952.5 | H26: 159 | I26: 10422.21 | J26: 1657131.4 | K26: =J26-G26 -> 174178.87 | L26: AUMENTO EN CANTIDAD Y AUMENTO EN EL PRECIO DEL HORMIGON PRECIO UTILIZADO EMPRESA BLUEWAVE
A27: 21 | B27: SUP010 | C27: SUMINISTRO, TRANSPORTE Y COLOCACION DE HORMIGON DE RCC 210 KG/CM2 A LOS 28 DIAS ACABADO CORRIENTE EN SUPERESTRUCTURA, PARA LA CONSTRUCCION DE MURO, DESCANSO Y PELDAÑOS DE ESCALERA. | D27: M3 | E27: 10.72 | F27: 10618.54 | G27: 113830.75 | H27: 14 | I27: 11552.89 | J27: 161740.46 | K27: =J27-G27 -> 47909.71 | L27: AUMENTO EN CANTIDAD Y AUMENTO EN EL PRECIO DEL HORMIGON PRECIO UTILIZADO EMPRESA BLUEWAVE
A28: 22 | B28: SUP002 | C28: SUMINISTRO, TRANSPORTE Y COLOCACION DE ENCOFRADO METALICO, TIPO RECTO, ACABADO CORRIENTE EN MUROS, E=10CMS PROLONGACION Y ENTREPISO. | D28: M2 | E28: 553.14 | F28: 2126.5284 | G28: 1176267.9 | H28: 553.14 | I28: 2126.5284 | J28: 1176267.9 | K28: =J28-G28 -> 0
A29: 23 | B29: SUP006 | C29: SUMINISTRO, TRANSPORTE Y COLOCACION DE ENCOFRADO METALICO , TIPO RECTO, ACABADO CORRIENTE EN MURO EN ESCALERA. | D29: M2 | E29: 43.23 | F29: 1920.3516 | G29: 83016.8 | H29: 43.23 | I29: 1920.3516 | J29: 83016.8 | K29: =J29-G29 -> 0
A30: 24 | B30: ENCFR07 | C30: SUMNISTRO, TRANSPORTE Y COLOCACION DE ENCOFRADO DE MADERA, TIPO RECTO, ACABADO CORRIENTE, EN DESCANSO Y PELDAÑOS EN ESCALERAS. | D30: M2 | E30: 48.85 | F30: 2452.0422 | G30: 119782.26 | H30: 48.85 | I30: 2452.0422 | J30: 119782.26 | K30: =J30-G30 -> 0
A31: 25 | B31: BARAN23 | C31: COLOCACION DE ANDAMIOS PARA EL ARMADO DE LA FORMALETA DE MUROS Y ENTREPISOS. | D31: NIVEL | E31: 3 | F31: 19841.38 | G31: 59524.14 | H31: 3 | I31: 19841.38 | J31: 59524.14 | K31: =J31-G31 -> 0
A32: 26 | B32: BARAN25 | C32: COLOCACION DE ANDAMIOS PARA EL ARMADO DE MUROS EN ESCALERA. | D32: NIVEL | E32: 4 | F32: 16427.34 | G32: 65709.36 | H32: 4 | I32: 16427.34 | J32: 65709.36 | K32: =J32-G32 -> 0
A33: 27 | B33: SUPER007 | C33: SUMINISTRO, TRANSPORTE Y COLOCACION DE ACERO DE REFUERZO EN SUPERESTRUCTURA, VARILLA DE DIAMETRO D= 3/8" PARA REFUERZO EN MURO Y LOSA DE ENTREPISO. | D33: QQ | E33: 163.71 | F33: 3758.05 | G33: 615230.37 | H33: 163.71 | I33: 3758.05 | J33: 615230.37 | K33: =J33-G33 -> 0 | L33: NO HAY VARIACION SIGNIFICANTE
A34: 28 | B34: SUPER009 | C34: SUMINISTRO, TRANSPORTE Y COLOCACION DE ACERO DE REFUERZO EN SUPERESTRUCTURA, VARILLA DE DIAMETRO D= 3/8" PARA REFUERZO EN VIGAS Y DINTELES. | D34: QQ | E34: 15.79 | F34: 3813.63 | G34: 60217.22 | H34: 15.79 | I34: 3813.63 | J34: 60217.22 | K34: =J34-G34 -> 0 | L34: NO HAY VARIACION SIGNIFICANTE
A35: 29 | B35: SUPER010 | C35: SUMINISTRO, TRANSPORTE Y COLOCACION DE ACERO DE REFUERZO EN SUPERESTRUCTURA, VARILLA DE DIAMETRO D= 1/2" PARA REFUERZO EN VIGAS Y DINTELES. | D35: QQ | E35: 3.88 | F35: 3748.42 | G35: 14543.87 | H35: 3.88 | I35: 3748.42 | J35: 14543.87 | K35: =J35-G35 -> 0 | L35: NO HAY VARIACION SIGNIFICANTE
A36: 30 | B36: INF025 | C36: SUMINISTRO, TRANSPORTE Y COLOCACION DE ACERO DE REFUERZO EN SUPERESTRUCTURA, VARILLA DE DIAMETRO D= 3/4" PARA REFUERZO EN VIGAS Y DINTELES. | D36: QQ | E36: 0.65 | F36: 3529.73 | G36: 2294.32 | H36: 0.65 | I36: 3529.73 | J36: 2294.32 | K36: =J36-G36 -> 0 | L36: NO HAY VARIACION SIGNIFICANTE
A37: 31 | B37: SUPER019 | C37: SUMINISTRO, TRANSPORTE Y COLOCACION DE ACERO DE REFUERZO EN SUPERESTRUCTURA, MALLA D2.9 x 2.9 - 100x100 PARA REFUERZO EN MURO Y LOSA DE ENTREPISO. | D37: M2 | E37: 657.2 | F37: 528.5 | G37: 347330.2 | H37: 657.2 | I37: 405.63 | J37: 266580.04 | K37: =J37-G37 -> -80750.16 | L37: DISMINUCION EN PRECIO DE MALLA D 2.9 X D 2.9
A38: 32 | B38: SUPER012 | C38: SUMINISTRO, TRANSPORTE Y COLOCACION DE ACERO DE REFUERZO EN SUPERESTRUCTURA, VARILLA DE DIAMETRO D= 3/8" PARA REFUERZO EN MURO, PELDAÑOS, VIGAS Y DESCANSO DE ESCALERAS. | D38: QQ | E38: 34.04 | F38: 3813.63 | G38: 129815.97 | H38: 34.04 | I38: 3813.63 | J38: 129815.97 | K38: =J38-G38 -> 0 | L38: NO HAY VARIACION SIGNIFICANTE
A39: 33 | B39: SUPER013 | C39: SUMINISTRO, TRANSPORTE Y COLOCACION DE ACERO DE REFUERZO EN SUPERESTRUCTURA, VARILLA DE DIAMETRO D= 1/2" PARA REFUERZO EN MURO, PELDAÑOS, VIGAS Y DESCANSO DE ESCALERA. | D39: QQ | E39: 10.91 | F39: 3686.83 | G39: 40223.32 | H39: 10.91 | I39: 3686.83 | J39: 40223.32 | K39: =J39-G39 -> 0 | L39: NO HAY VARIACION SIGNIFICANTE | Q39: ORIGINAL | R39: ACTUALIZADO
A40: INSTALACIONES ELECTRICAS | G40: =SUM(G41:G48) -> 860818.84 | J40: =SUM(J41:J48) -> 851358.04
A41: 34 | B41: INSEL001 | C41: SUMINISTRO, TRANSPORTE Y COLOCACION DE INSTALACIONES ELECTRICAS (ACOMETIDAS) EN PLATEA. | D41: PLATEA | E41: 1 | F41: 28277.81 | G41: 28277.81 | H41: 1 | I41: 28277.81 | J41: 28277.81 | K41: =J41-G41 -> 0 | N41: INSTALACIONES ELECTRICAS | Q41: =G41+G42+G43+G48 -> 414331.38 | R41: =J41+J42+J43+J48 -> 404870.58
A42: 35 | B42: INSEL002 | C42: SUMINISTRO, TRANSPORTE Y COLOCACION DE INSTALACIONES ELECTRICAS (TUBERIAS) EN MUROS Y LOSA DE ENTREPISO Y TECHO. | D42: APTO | E42: 6 | F42: 27873.69 | G42: 167242.14 | H42: 6 | I42: 27873.69 | J42: 167242.14 | K42: =J42-G42 -> 0 | N42: PIEZAS ELECTRICAS Y CABLEADO | Q42: =G44+G45+G46+G47 -> 446487.46 | R42: =J44+J45+J46+J47 -> 446487.46
A43: 36 | B43: INSEL003 | C43: SUMINISTRO, TRANSPORTE Y COLOCACION DE INSTALACIONES ELECTRICAS (TUBERIA) EN ZONA COMUN Y TERRAZA DEL EDIFICIO. | D43: EDIFICIO | E43: 1 | F43: 31380.13 | G43: 31380.13 | H43: 1 | I43: 31380.13 | J43: 31380.13 | K43: =J43-G43 -> 0 | N43: CAJAS DE BREAKER
A44: 37 | B44: INSEL004 | C44: SUMINISTRO, TRANSPORTE Y COLOCACION DE PIEZAS ELECTRICAS EN APARTAMENTO. | D44: APTO | E44: 6 | F44: 24261.13 | G44: 145566.78 | H44: 6 | I44: 24261.13 | J44: 145566.78 | K44: =J44-G44 -> 0 | Q44: =SUM(Q41:Q43) -> 860818.84 | R44: =SUM(R41:R43) -> 851358.04
A45: 38 | B45: INSEL006 | C45: SUMINISTRO, TRANSPORTE Y COLOCACION DE PIEZAS ELECTRICAS EN AREA DE CIRCULACION Y TERRAZAS EDIFICIO. | D45: EDIFICIO | E45: 1 | F45: 17096.78 | G45: 17096.78 | H45: 1 | I45: 17096.78 | J45: 17096.78 | K45: =J45-G45 -> 0
A46: 39 | B46: INSEL011 | C46: SUMINISTRO, TRANSPORTE Y COLOCACION DE CABLEADO ELECTRICO EN APARTAMENTO | D46: APTO | E46: 6 | F46: 44072.57 | G46: 264435.42 | H46: 6 | I46: 44072.57 | J46: 264435.42 | K46: =J46-G46 -> 0
A47: 40 | B47: INESELEC | C47: SUMINISTRO, TRANSPORTE Y COLOCACION DE CABLEADO ELECTRICO EN PUNTO FIJO | D47: EDIFICIO | E47: 1 | F47: 19388.48 | G47: 19388.48 | H47: 1 | I47: 19388.48 | J47: 19388.48 | K47: =J47-G47 -> 0
A48: 41 | B48: CABLE10 | C48: SUMINISTRO, TRANSPORTE Y COLOCACION DE TABLERO EN APTO. INCLUYE BREAKER. | D48: APTO | E48: 6 | F48: 31238.55 | G48: 187431.3 | H48: 6 | I48: 29661.75 | J48: 177970.5 | K48: =J48-G48 -> -9460.8 | L48: DISMINUCION PRECIO DE CAJA DE BREAKER
A49: INSTALACIONES TELECOMUNICACIONES | G49: =SUM(G50:G52) -> 127665.96 | J49: =SUM(J50:J52) -> 127665.96
A50: 42 | B50: TELECOM | C50: SUMINISTRO, TRANSPORTE Y COLOCACION DE INSTALACIONES TELECOMUNICACIONES DE AREAS COMUNES DE EDIFICIO. | D50: EDIF | E50: 1 | F50: 26041.25 | G50: 26041.25 | H50: 1 | I50: 26041.25 | J50: 26041.25 | K50: =J50-G50 -> 0
A51: 43 | B51: TELECOM1 | C51: SUMINISTRO, TRANSPORTE Y COLOCACION DE CAJAS DE PASO Y DISTRIBUCION DE INSTALACIONES TELECOMUNICACIONES DE AREAS COMUNES DE EDIFICIO. INCLUYE ACCESORIOS Y ELEMNTOS DE FIJACION. | D51: EDIF | E51: 1 | F51: 8332.21 | G51: 8332.21 | H51: 1 | I51: 8332.21 | J51: 8332.21 | K51: =J51-G51 -> 0
A52: 44 | B52: TELECOM2 | C52: SUMINISTRO, TRANSPORTE Y COLOCACION DE INSTALACIONES DE TELECOMUNICACIONES (TUBERIAS) EN MUROS DE LOSA DE ENTREPISO Y TECHO. | D52: APTO | E52: 6 | F52: 15548.75 | G52: 93292.5 | H52: 6 | I52: 15548.75 | J52: 93292.5 | K52: =J52-G52 -> 0
A53: INSTALACIONES SANITARIAS | G53: =SUM(G54:G67) -> 1381560.8 | J53: =SUM(J54:J67) -> 1486429.5
A54: 45 | B54: INSAN001 | C54: SUMINISTRO, TRANSPORTE Y COLOCACION DE INSTALACIONES DE AGUA FRIA EN LOSA DE PISO Y MUROS. | D54: APTO | E54: 6 | F54: 18937.72 | G54: 113626.32 | H54: 6 | I54: 18937.72 | J54: 113626.32 | K54: =J54-G54 -> 0
A55: 46 | B55: INSAN006 | C55: SUMINISTRO, TRANSPORTE Y COLOCACION DE INSTALACIONES DE AGUA CALIENTE EN LOSA DE PISO Y MUROS. | D55: APTO | E55: 6 | F55: 13900.43 | G55: 83402.58 | H55: 6 | I55: 13900.43 | J55: 83402.58 | K55: =J55-G55 -> 0
A56: 47 | B56: INSAN009 | C56: SUMINISTRO, TRANSPORTE Y COLOCACION DE INSTALACIONES DE ACOMETIDA DE AGUA FRIA EN EDIFICIO. | D56: EDIF | E56: 1 | F56: 22101.22 | G56: 22101.22 | H56: 1 | I56: 22101.22 | J56: 22101.22 | K56: =J56-G56 -> 0
A57: 48 | B57: TUBMONTA | C57: SUMINISTRO, TRANSPORTE Y COLOCACION DE INSTALACIONES DE MONTANTE DE AGUA FRIA. EDIFICIO A. | D57: EDIFICIO | E57: 1 | F57: 14610.25 | G57: 14610.25 | H57: 1 | I57: 14610.25 | J57: 14610.25 | K57: =J57-G57 -> 0
A58: 49 | B58: INSAN008 | C58: SUMINISTRO, TRANSPORTE Y COLOCACION DE INSTALACIONES SANITARIAS (TUBERIA) DE AGUAS NEGRAS EN PLATEA. | D58: PLATEA | E58: 1 | F58: 89735.27 | G58: 89735.27 | H58: 1 | I58: 89735.27 | J58: 89735.27 | K58: =J58-G58 -> 0
A59: 50 | B59: INSAN002 | C59: SUMINISTRO, TRANSPORTE Y COLOCACION DE INSTALACIONES SANITARIAS (TUBERIA) DE AGUAS NEGRAS EN LOSA DE PISO Y MUROS. | D59: APTO | E59: 4 | F59: 24522.44 | G59: 98089.76 | H59: 4 | I59: 24522.44 | J59: 98089.76 | K59: =J59-G59 -> 0
A60: 51 | B60: INSAN007 | C60: SUMINISTRO, TRANSPORTE Y COLOCACION DE INSTALACIONES SANITARIAS (TUBERIA) DE AGUAS NEGRAS EN BAJANTES. | D60: EDIFICIO | E60: 1 | F60: 37832.42 | G60: 37832.42 | H60: 1 | I60: 37832.42 | J60: 37832.42 | K60: =J60-G60 -> 0
A61: 52 | B61: SANAN001 | C61: SUMINISTRO, TRANSPORTE Y COLOCACION DE INSTALACIONES SANITARIAS (TUBERIA) DE AGUAS PLUVIAL EN TERRAZAS Y BAJANTES. | D61: EDIFICIO | E61: 1 | F61: 32810.67 | G61: 32810.67 | H61: 1 | I61: 32810.67 | J61: 32810.67 | K61: =J61-G61 -> 0
A62: 53 | B62: INSAN003 | C62: SUMINISTRO, TRANSPORTE Y COLOCACION DE INSTALACIONES DE GAS (TUBERIA) EN LOSA DE PISO Y MUROS. EDIFICIO A. | D62: EDIFICIO | E62: 1 | F62: 20925.94 | G62: 20925.94 | H62: 1 | I62: 20925.94 | J62: 20925.94 | K62: =J62-G62 -> 0
A63: 54 | B63: INSAN005 | C63: SUMINISTRO, TRANSPORTE Y COLOCACION DE INSTALACIONES DE GAS (TUBERIA PVC CAMISA) EN LOSA DE PISO Y MUROS. EDIFICIO A. | D63: APTO | E63: 6 | F63: 4833.28 | G63: 28999.68 | H63: 6 | I63: 4833.28 | J63: 28999.68 | K63: =J63-G63 -> 0
A64: 55 | B64: GAS MONT | C64: SUMINISTRO Y COLOCACION DE MONTANTE DE GAS BAJA PRESION | D64: EDIFICIO | E64: 1 | F64: 16053.24 | G64: 16053.24 | H64: 1 | I64: 16053.24 | J64: 16053.24 | K64: =J64-G64 -> 0
A65: 56 | B65: INSAN004 | C65: SUMINISTRO, TRANSPORTE Y COLOCACION DE PIEZAS SANITARIAS EN BAÑOS. INCLUYE ACCESORIOS DE BAÑOS. | D65: APTO | E65: 6 | F65: 131181.68 | G65: 787090.08 | H65: 6 | I65: 119575.02 | J65: 717450.15 | K65: =J65-G65 -> -69639.935 | L65: DISMINUCION EN PRECIOS DE PIEZAS SANITARIAS Y GRIFERIAS, PRECIOS UTILIZADO EMPRESA DACIA
A66: 57 | B66: EBISTB23 | C66: SUMINISTRO, TRANSPORTE Y COLOCACION DE FREGADERO. INCLUYE GRFERIA. | D66: APTO | E66: 1 | F66: 19046.48 | G66: 19046.48 | H66: 6 | I66: 14816.839 | J66: 88901.033 | K66: =J66-G66 -> 69854.553 | L66: AUMENTO EN CANTIDAD POR ERROR DE PRESUPUESTO INICIAL Y DISMINUCION DE PRECIO EN FREGADERO PRECIOS EMPRESA DACIA
A67: 58 | B67: EBISEQ10 | C67: SUMINISTRO, TRANSPORTE Y COLOCACION DE LAVADERO DE GRANITO. INCLUYE BASE DE METAL, LLAVE E INSTALACION. | D67: APTO | E67: 1 | F67: 17236.94 | G67: 17236.94 | H67: 6 | I67: 20315.166 | J67: 121891 | K67: =J67-G67 -> 104654.06 | L67: AUMENTO EN CANTIDAD POR ERROR DE PRESUPUESTO INICIAL Y AUMENTO DE PRECIO EN LAVADERO Y GRIFERIA POR CAMBIO DE DISENO, PRECIOS EMPRESA DACIA
A68: INSTALACIONES DE INCENDIO | G68: =SUM(G69) -> 8849.64 | J68: =J69 -> 8849.64
A69: 59 | B69: TUBEA31 | C69: SUMINISTRO, TRANSPORTE Y COLOCCION DE EXTINTOR. | D69: UND | E69: 3 | F69: 2949.88 | G69: 8849.64 | H69: 3 | I69: 2949.88 | J69: 8849.64 | K69: =J69-G69 -> 0
A70: ALBAÑILERIA | G70: =SUM(G71:G82) -> 1034844.8 | J70: =SUM(J71:J82) -> 1042573.2
A71: 60 | B71: EBMUB107 | C71: SUMINISTRO, TRANSPORTE Y COLOCACION DE PAREDES EN DENSGLASS. | D71: M2 | E71: 66.83 | F71: 2638.72 | G71: 176345.66 | H71: 66.83 | I71: 2638.72 | J71: 176345.66 | K71: =J71-G71 -> 0
A72: 61 | B72: EBPFY02 | C72: CONSTRUCCION DE TECHO CIELO RASO EN BANO,COCINA Y CUARTO DE ROPA.INCLUYE RH+ACABADO EN PINTURA ANTIHONGOS BLANCA CON DILATACIONES CON ENTRAMADO METALICO | D72: M2 | E72: 45.12 | F72: 2950.94 | G72: 133146.41 | H72: 45.12 | I72: 2950.94 | J72: 133146.41 | K72: =J72-G72 -> 0
A73: 62 | B73: EBPÑIE03 | C73: SUMINISTRO, TRANSPORTE Y COLOCACION DE DE TERMINACION CON MASILLA PARA PAREDES Y TECHOS EN DENSGLASS. | D73: M2 | E73: 106.14 | F73: 341.41 | G73: 36237.26 | H73: 106.14 | I73: 341.41 | J73: 36237.26 | K73: =J73-G73 -> 0
A74: 63 | B74: SREMT23 | C74: RESANE INTERNO DE SUPERFICIES DE CONCRETO EN APARTAMENTO. | D74: APTO | E74: 6 | F74: 30070.3 | G74: 180421.8 | H74: 6 | I74: 30070.3 | J74: 180421.8 | K74: =J74-G74 -> 0
A75: 64 | B75: SREMT25 | C75: RESANE INTERNO DE SUPERFICIES DE CONCRETO EN CUERPO FIJO. | D75: EDIFICIO | E75: 1 | F75: 42696.27 | G75: 42696.27 | H75: 1 | I75: 42696.27 | J75: 42696.27 | K75: =J75-G75 -> 0
A76: 65 | B76: SREMT24 | C76: RESANE EXTERIOR DE SUPERFICIES DE CONCRETO EN PAREDES. | D76: EDIFICIO | E76: 1 | F76: 95969.76 | G76: 95969.76 | H76: 1 | I76: 95969.76 | J76: 95969.76 | K76: =J76-G76 -> 0 | M76: 928242.18
A77: 66 | B77: BARAN22 | C77: COLOCACION DE ANDAMIOS PARA EL RESANE EXTERIOR. | D77: NIVEL | E77: 3 | F77: 18265.96 | G77: 54797.88 | H77: 3 | I77: 18265.96 | J77: 54797.88 | K77: =J77-G77 -> 0
A78: 67 | B78: EBTSGT01 | C78: CONSTRUCCION DE GOTERO EN BALCONES | D78: ML | E78: 84 | F78: 405.98 | G78: 34102.32 | H78: 84 | I78: 405.98 | J78: 34102.32 | K78: =J78-G78 -> 0
A79: 68 | B79: BORDILLO | C79: CONSTRUCCION DE BORDILLO EN BALCONES Y CUERPO FIJO | D79: ML | E79: 14.45 | F79: 1202.93 | G79: 17382.34 | H79: 14.45 | I79: 1202.93 | J79: 17382.34 | K79: =J79-G79 -> 0
A80: 69 | B80: EBTSCNT0 | C80: CONSTRUCCION DE CANTOS DE ANTEPECHOS. | D80: ML | E80: 70.1 | F80: 354.36 | G80: 24840.64 | H80: 70.1 | I80: 354.36 | J80: 24840.64 | K80: =J80-G80 -> 0 | M80: 8849.64
A81: 70 | B81: EBTSMCH1 | C81: CONSTRUCCION DE MOCHETAS. | D81: ML | E81: 466 | F81: 193.6 | G81: 90217.6 | H81: 466 | I81: 193.6 | J81: 90217.6 | K81: =J81-G81 -> 0
A82: 71 | B82: SUP004 | C82: SUMINISTRO,ARMADO,ENCOFRADO Y VACIADO DE ANTEPECHOS DE EDIFICIOS | D82: ML | E82: 70.1 | F82: 2121.0684 | G82: 148686.89 | H82: 70.1 | I82: 2231.3158 | J82: 156415.24 | K82: =J82-G82 -> 7728.35 | L82: AUMENTO EN EL PRECIO DEL HORMIGON PRECIO UTILIZADO EMPRESA BLUEWAVE
A83: HERRERIA | G83: =SUM(G84:G91) -> 1387881.1 | J83: =SUM(J84:J91) -> 1392513.9 | M83: 1042573.2
A84: 72 | B84: ALBL004 | C84: CONSTRUCCION DE BARANDA DE ESCALERAS. INCLUYE FONDO Y PINTURA. | D84: ML | E84: 37.79 | F84: 9774.696 | G84: 369385.76 | H84: 37.79 | I84: 7195.0108 | J84: 271899.46 | K84: =J84-G84 -> -97486.303 | L84: DISMINUCION DE PRECIO CAMBIO DE MATERIAL ALUMINIO A ESTRUCTURA METALICA, PRECIO PRESUPUESTO EMPRESA SUPLIPUCANSA
A85: 73 | B85: ALBL009 | C85: CONSTRUCCION DE BARANDA DE BALCONES. INCLUYE FONDO Y PINTURA. | D85: ML | E85: 16.8 | F85: 6904.9324 | G85: 116002.86 | H85: 16.8 | I85: 7195.0108 | J85: 120876.18 | K85: =J85-G85 -> 4873.3208 | L85: AUMENTO DE PRECIO IGUAL PRECIO BARANDA ESCALERA, PRECIO PRESUPUESTO EMPRESA SUPLIPUCANSA
A86: 74 | B86: CARPS018 | C86: SUMINISTRO, TRANSPORTE Y COLOCACION DE PUERTA METALICA REJILLA(ROMANILLA) DE 0.70X2.40 NIVEL 1 PASILLO.INCLUYE FONDO Y PINTURA. (P-02) | D86: PZA | E86: 1 | F86: 18457.84 | G86: 18457.84 | H86: 1 | I86: 20963.137 | J86: 20963.137 | K86: =J86-G86 -> 2505.2966 | L86: AUMENTO DE PRECIOPRECIO PRESUPUESTO ALUGAV
A87: 75 | B87: CARPS019 | C87: SUMINISTRO, TRANSPORTE Y COLOCACION DE VENTANA DE VENTILACION METALICA (ROMANILLA) DE 0.70X1.90 NIVEL 2,NIVEL 3,NIVEL TERRAZA.INCLUYE FONDO Y PINTURA.(R-01) | D87: PZA | E87: 3 | F87: 12192.43 | G87: 36577.29 | H87: 3 | I87: 16327.979 | J87: 48983.936 | K87: =J87-G87 -> 12406.646 | L87: AUMENTO DE PRECIOPRECIO PRESUPUESTO ALUGAV
A88: 76 | B88: PUERTA06 | C88: SUMINISTRO, TRANSPORTE Y COLOCACION DE PUERTA METALICA REJILLA(ROMANILLA) DE 1.00X2.10 CUBIERTA PASILLO.INCLUYE FONDO Y PINTURA. (P-06) | D88: PZA | E88: 1 | F88: 23152.63 | G88: 23152.63 | H88: 1 | I88: 22612.836 | J88: 22612.836 | K88: =J88-G88 -> -539.7944 | L88: AUMENTO DE PRECIOPRECIO PRESUPUESTO ALUGAV
A89: 77 | B89: HERRE28 | C89: SUMINISTRO, TRANSPORTE E INSTALACION DE PERGOLADO METALICO TIPO 1 y TIPO 2. INCLUYE FONDO Y PINTURA. | D89: M2 | E89: 11.2 | F89: 9832.2066 | G89: 110120.71 | H89: 11.2 | I89: 7444.5025 | J89: 83378.428 | K89: =J89-G89 -> -26742.282 | L89: MANTENIENDO EN ALUMINIO, PRECIO PRESUPUESTO EMPRESA TITAN CHINA AUNQUE SE DEJO UN MONTO MAYOR
A90: 78 | B90: HERRE30 | C90: SUMINISTRO, TRANSPORTE E INSTALACION DE CUBIERTA DE TECHO METALICO. | D90: m2 | E90: 44 | F90: 9516.6344 | G90: 418731.91 | H90: 44 | I90: 10486.252 | J90: 461395.07 | K90: =J90-G90 -> 42663.163 | L90: AUMENTO DE PRECIO, PRECIO PRESUPUESTO EMPRESA SUPLIPUCANSA+TERMOPANEL ISOTEX+FASCIA
A91: 79 | B91: HERRE31 | C91: SUMINISTRO, TRANSPORTE E INSTALACION DE PERGOLADO METALICO TECHO. INCLUYE FONDO Y PINTURA. | D91: M2 | E91: 34.56 | F91: 8548.9606 | G91: 295452.08 | H91: 34.56 | I91: 10486.252 | J91: 362404.86 | K91: =J91-G91 -> 66952.777 | L91: AUMENTO DE PRECIO COLOCACION DE PANELES TIPO SANDWICH EN PERGOLAS, PRECIO PRESUPUESTO EMPRESA SUPLIPUCANSA | P91: ORIGINAL | Q91: MODIFICADO
A92: REVESTIMIENTO | G92: =SUM(G93:G106) -> 2626497.9 | J92: =SUM(J93:J106) -> 2319104.8 | N92: VINIL | P92: =G94+G100 -> 1167000.9 | Q92: =J94+J100 -> 955856.86
A93: 80 | B93: REVES000 | C93: SUMINISTRO, TRANSPORTE Y COLOCACION DE TORTA DE PISO DE NIVELACION H.S. 1:3:5 | D93: M2 | E93: 453.04 | F93: 361.24 | G93: 163656.17 | H93: 453.04 | I93: 361.24 | J93: =H93*I93 -> 163656.17 | K93: =J93-G93 -> -0.00039999999 | N93: CERAMICA PISO BANO | P93: =G95+G101 -> 70449.82 | Q93: =J95+J101 -> 75242.642
A94: 81 | B94: REVES020 | C94: SUMINISTRO, TRANSPORTE Y COLOCACION DE PISO DE VINIL EN APTO. | D94: M2 | E94: 426.04 | F94: 2129.31 | G94: 907171.23 | H94: 426.04 | I94: 1633.7132 | J94: =H94*I94 -> 696027.17 | K94: =J94-G94 -> -211144.06 | L94: DISMINUCION DE PRECIO EN EL PISO DE VINIL, PRECIO PRESUPUESTO EMPRESA MATERIAL AQUAARMOR CHINA, AUNQUE EL PRECIO CON ESTA EMPRESA ES 740.46 PESOS EL M2 SE COLOCO 900 | N94: CERAMICA PISO DUCHA | P94: =G96+G105+G106 -> 92169.75 | Q94: =J96+J105+J106 -> 76305.096
A95: 82 | B95: VINILBAN | C95: SUMINISTRO, TRANSPORTE Y COLOCACION DE PISO DE VINIL EN BANO. | D95: M2 | E95: 27 | F95: 2129.31 | G95: 57491.37 | H95: 27 | I95: 2306.822 | J95: =H95*I95 -> 62284.193 | K95: =J95-G95 -> 4792.8226 | L95: DISMINUCION MONTO CAMBIO COSTO PISO DE VINIL A PORCELANATO ; AUNQUE SE AUMENTO MODIFICACION DE MANO DE OBRA PARA INSTALACION DE PORCELANATO POR ESTA RAZON AUMENTO EL PRECIO.PRECIO DE PORCELANATO TOMADO EMPRESA CONTE DIRECTO | N95: CERAMICA PISO BALCONES | P95: =G99 -> 30502.77 | Q95: =J99 -> 23760.566
A96: 83 | B96: REVES013 | C96: SUMINISTRO, TRANSPORTE Y COLOCACION DE CERAMICA EN PISO DE BAÑO DUCHA. | D96: M2 | E96: 16.8 | F96: 3200.71 | G96: 53771.93 | H96: 12 | I96: 3158.94 | J96: =H96*I96 -> 37907.28 | K96: =J96-G96 -> -15864.65 | L96: AUMENTO DE PRECIO POR COLOCACION PLATO DE DUCHA; SE COLOCO UN PROMEDIO DE 140$ POR COTIZACIONES | N96: CERAMICA EN ESCALERA | P96: =G102+G103 -> 342436.18 | Q96: =J102+J103 -> 324989.58
A97: 84 | B97: REVES015 | C97: SUMINISTRO, TRANSPORTE Y COLOCACION DE CERAMICA EN PARED DE BAÑO. | D97: M2 | E97: 144.7 | F97: 3266.9 | G97: 472720.43 | H97: 100 | I97: 3266.9 | J97: =H97*I97 -> 326690 | K97: =J97-G97 -> -146030.43 | L97: DISMINUCION DE CANTIDAD , SOLO PARED DE DUCHA, SE MANTUVO PRECIO DE CERAMICA, NEGOCIAR MEJOR PRECIO EN LA CERAMICA | N97: TABLILLA | P97: =G104 -> 270541.04 | Q97: =J104 -> 372603.92
A98: 85 | B98: REVES018 | C98: SUMINISTRO, TRANSPORTE Y COLOCACION DE CERAMICA EN PARED DE COCINA. | D98: M2 | E98: 5.99 | F98: 2841.54 | G98: 17020.82 | H98: 0 | I98: 2841.54 | J98: =H98*I98 -> 0 | K98: =J98-G98 -> -17020.82 | L98: ELIMINADA PATIDA NO SE VA A COLOCAR | N98: TORTA DE NIVELACION | P98: =G93 -> 163656.17 | Q98: =J93 -> 163656.17
A99: 86 | B99: REVES019 | C99: SUMINISTRO, TRANSPORTE Y COLOCACION DE PISO EN BALCONES. | D99: M2 | E99: 9.53 | F99: 3200.71 | G99: 30502.77 | H99: 9.53 | I99: 2493.2388 | J99: =H99*I99 -> 23760.566 | K99: =J99-G99 -> -6742.2042 | L99: DISMINUCION DE PRECIO DE PORCELANTO CAMBIO COSTO.PRECIO DE PORCELANATO TOMADO EMPRESA CONTE DIRECTO | M99: 1392513.9 | N99: PARED DE BANO | P99: =G97 -> 472720.43 | Q99: =J97 -> 326690
A100: 87 | B100: REVES022 | C100: SUMINISTRO, TRANSPORTE Y COLOCACION DE ZOCALO DE VINIL. | D100: ML | E100: 380.53 | F100: 682.81 | G100: 259829.69 | H100: 380.53 | I100: 682.81 | J100: =H100*I100 -> 259829.69 | K100: =J100-G100 -> -0.00070000003 | N100: PARED COCINA | P100: =G98 -> 17020.82 | Q100: =J98 -> 0
A101: 88 | B101: ZOBA | C101: SUMINISTRO, TRANSPORTE Y COLOCACION DE ZOCALO BANO | D101: ML | E101: 21.9 | F101: 591.71 | G101: 12958.45 | H101: 21.9 | I101: 591.71 | J101: =H101*I101 -> 12958.449 | K101: =J101-G101 -> -0.001 | P101: =SUM(P92:P100) -> 2626497.9 | Q101: =SUM(Q92:Q100) -> 2319104.8
...

Sheet RESUMEN  PRESUPUESTO
A1: COMPARATIVO PRESUPUESTO EDIFICIO ORIGINAL VS PRECIOS ACTUALIZADO
G2: EDIFICACIONES X MES
A3: CAPÍTULO | B3: PRESUPUESTO ORIGINAL | C3: PRESUPUESTO ACTUALIZADO | D3: DIFERENCIA | E3: % DESVIACIÓN | F3: OBSERVACIÓN | G3: #1 | H3: #2 | I3: #3 | J3: #4 | K3: #5 | L3: #6 | M3: #7 | N3: #8 | O3: #9 | P3: #10 | Q3: #11 | R3: #12 | S3: #13 | T3: #14 | U3: #15 | V3: #16 | W3: #17 | X3: #18 | Y3: #70 | Z3: #71 | AA3: #72 | AB3: #73 | AC3: #74 | AD3: #75 | AE3: #26 | AF3: #77 | AG3: TOTAL
A4: CARPINTERIA | B4: 2049569.7 | C4: 2400730.3 | D4: =C4-B4 -> 351160.59 | E4: =D4/B4 -> 0.17133381 | F4: Aumento por mayor cantidad/precio | G4: 1 | H4: 1 | I4: 1 | J4: 1 | K4: 1 | L4: 1 | M4: 1 | N4: 1 | O4: 1 | P4: 1 | Q4: 1 | R4: 1 | S4: 1 | T4: 1 | U4: 1 | V4: 1 | W4: 1 | X4: 1 | Y4: 1 | Z4: 1 | AA4: 1 | AB4: 1 | AC4: 1 | AD4: 1 | AE4: 1 | AF4: 1 | AG4: =SUM(G4:AF4) -> 26 | AH4: =D4*AG4 -> 9130175.4
A5: PIEZAS SANITARIAS | B5: 823373.5 | C5: 928242.18 | D5: =C5-B5 -> 104868.68 | E5: =D5/B5 -> 0.12736465 | F5: Aumento por mayor cantidad/precio | G5: 1 | H5: 1 | I5: 1 | J5: 1 | K5: 1 | L5: 1 | M5: 1 | N5: 1 | O5: 1 | P5: 1 | Q5: 1 | R5: 1 | S5: 1 | T5: 1 | U5: 1 | V5: 1 | W5: 1 | X5: 1 | Y5: 1 | Z5: 1 | AA5: 1 | AB5: 1 | AC5: 1 | AD5: 1 | AE5: 1 | AF5: 1 | AG5: =SUM(G5:AF5) -> 26 | AH5: =D5*AG5 -> 2726585.6
A6: INFRAESTRUCTURA | B6: 1387237.5 | C6: 1475727.8 | D6: =C6-B6 -> 88490.32 | E6: =D6/B6 -> 0.063788875 | F6: Aumento hormigón (Bluewave) y acero | V6: 1 | W6: 1 | X6: 1 | Y6: 1 | Z6: 1 | AA6: 1 | AB6: 1 | AC6: 1 | AD6: 1 | AE6: 1 | AF6: 1 | AG6: =SUM(G6:AF6) -> 11 | AH6: =D6*AG6 -> 973393.52
A7: HERRERIA | B7: 1387881.1 | C7: 1392513.9 | D7: =C7-B7 -> 4632.8231 | E7: =D7/B7 -> 0.0033380548 | F7: Variación menor | G7: 1 | H7: 1 | I7: 1 | J7: 1 | K7: 1 | L7: 1 | M7: 1 | N7: 1 | O7: 1 | P7: 1 | Q7: 1 | R7: 1 | S7: 1 | T7: 1 | U7: 1 | V7: 1 | W7: 1 | X7: 1 | Y7: 1 | Z7: 1 | AA7: 1 | AB7: 1 | AC7: 1 | AD7: 1 | AE7: 1 | AF7: 1 | AG7: =SUM(G7:AF7) -> 26 | AH7: =D7*AG7 -> 120453.4
A8: SUPERESTRUCTURA | B8: 4310739 | C8: 4452077.4 | D8: =C8-B8 -> 141338.42 | E8: =D8/B8 -> 0.032787515 | F8: Aumento hormigón (Bluewave) | R8: 1 | S8: 1 | T8: 1 | U8: 1 | V8: 1 | W8: 1 | X8: 1 | Y8: 1 | Z8: 1 | AA8: 1 | AB8: 1 | AC8: 1 | AD8: 1 | AE8: 1 | AF8: 1 | AG8: =SUM(G8:AF8) -> 15 | AH8: =D8*AG8 -> 2120076.3
A9: ALBANILERIA | B9: 1034844.8 | C9: 1042573.2 | D9: =C9-B9 -> 7728.35 | E9: =D9/B9 -> 0.0074681245 | F9: Variación menor | R9: 1 | S9: 1 | T9: 1 | U9: 1 | V9: 1 | W9: 1 | X9: 1 | Y9: 1 | Z9: 1 | AA9: 1 | AB9: 1 | AC9: 1 | AD9: 1 | AE9: 1 | AF9: 1 | AG9: =SUM(G9:AF9) -> 15 | AH9: =D9*AG9 -> 115925.25
A10: INSTALACIONES ELECTRICAS-CAJA DE BREAKER | B10: ='DETALLE PRESUPUESTO POR PARTIDA'!Q41 -> 414331.38 | C10: ='DETALLE PRESUPUESTO POR PARTIDA'!R41 -> 404870.58 | D10: =C10-B10 -> -9460.8 | E10: =D10/B10 -> -0.022833897 | F10: Leve disminución | AG10: =SUM(G10:AF10) -> 0 | AH10: =D10*AG10 -> 0
A11: PIEZAS ELECTRICAS Y CABLEADO | B11: ='DETALLE PRESUPUESTO POR PARTIDA'!Q42 -> 446487.46 | C11: ='DETALLE PRESUPUESTO POR PARTIDA'!R42 -> 446487.46 | D11: =C11-B11 -> 0 | E11: =D11/B11 -> 0 | F11: Sin variación
A12: INSTALACIONES TELECOMUNICACIONES | B12: 127665.96 | C12: 127665.96 | D12: =C12-B12 -> 0 | E12: =D12/B12 -> 0 | F12: Sin variación, materiales buen precio puede disminuir | AG12: =SUM(G12:AF12) -> 0 | AH12: =D12*AG12 -> 0
A13: INSTALACIONES SANITARIAS | B13: 558187.35 | C13: 558187.35 | D13: =C13-B13 -> 0 | E13: =D13/B13 -> 0 | F13: Sin variación | AG13: =SUM(G13:AF13) -> 0 | AH13: =D13*AG13 -> 0
A14: INSTALACIONES DE INCENDIO | B14: 8849.64 | C14: 8849.64 | D14: =C14-B14 -> 0 | E14: =D14/B14 -> 0 | F14: Sin variación | AG14: =SUM(G14:AF14) -> 0 | AH14: =D14*AG14 -> 0
A15: PINTURA | B15: 1741020.9 | C15: 1741020.9 | D15: =C15-B15 -> 0 | E15: =D15/B15 -> 0 | F15: Sin variación , pintura buen precio puede disminuir | AG15: =SUM(G15:AF15) -> 0 | AH15: =D15*AG15 -> 0
A16: LIMPIEZA | B16: 173990.77 | C16: 173990.77 | D16: =C16-B16 -> 0 | E16: =D16/B16 -> 0 | F16: Sin variación | AG16: =SUM(G16:AF16) -> 0 | AH16: =D16*AG16 -> 0
A17: TORTA DE NIVELACION | B17: ='DETALLE PRESUPUESTO POR PARTIDA'!G93 -> 163656.17 | C17: ='DETALLE PRESUPUESTO POR PARTIDA'!J93 -> 163656.17 | F17: Sin variación
A18: REVESTIMIENTO PISO DE VINIL | B18: ='DETALLE PRESUPUESTO POR PARTIDA'!P92 -> 1167000.9 | C18: ='DETALLE PRESUPUESTO POR PARTIDA'!Q92 -> 955856.86 | D18: =C18-B18 -> -211144.06 | E18: =D18/B18 -> -0.18092879 | F18: Ahorro respecto al original,Precio AQUAARMOR CHINA | G18: 1 | H18: 1 | I18: 1 | J18: 1 | K18: 1 | L18: 1 | M18: 1 | N18: 1 | O18: 1 | P18: 1 | Q18: 1 | R18: 1 | S18: 1 | T18: 1 | U18: 1 | V18: 1 | W18: 1 | X18: 1 | Y18: 1 | Z18: 1 | AA18: 1 | AB18: 1 | AC18: 1 | AD18: 1 | AE18: 1 | AF18: 1 | AG18: =SUM(G18:AF18) -> 26 | AH18: =D18*AG18 -> -5489745.5
A19: CERAMICA PISO DE BANO | B19: ='DETALLE PRESUPUESTO POR PARTIDA'!P93 -> 70449.82 | C19: ='DETALLE PRESUPUESTO POR PARTIDA'!Q93 -> 75242.642 | D19: =C19-B19 -> 4792.8216 | E19: =D19/B19 -> 0.068031709 | F19: Sin variacion notable,bajo el precio material se ajusto mano de obra | H19: 1 | I19: 1 | J19: 1 | K19: 1 | L19: 1 | M19: 1 | N19: 1 | O19: 1 | P19: 1 | Q19: 1 | R19: 1 | S19: 1 | T19: 1 | U19: 1 | V19: 1 | W19: 1 | X19: 1 | Y19: 1 | Z19: 1 | AA19: 1 | AB19: 1 | AC19: 1 | AD19: 1 | AE19: 1 | AF19: 1 | AG19: =SUM(G19:AF19) -> 25 | AH19: =D19*AG19 -> 119820.54
A20: CERAMICA PISO DE DUCHA | B20: ='DETALLE PRESUPUESTO POR PARTIDA'!P94 -> 92169.75 | C20: ='DETALLE PRESUPUESTO POR PARTIDA'!Q94 -> 76305.096 | D20: =C20-B20 -> -15864.654 | E20: =D20/B20 -> -0.1721243 | F20: Aumento colocacion plato de ducha | G20: 1 | H20: 1 | I20: 1 | J20: 1 | K20: 1 | L20: 1 | M20: 1 | N20: 1 | O20: 1 | P20: 1 | Q20: 1 | R20: 1 | S20: 1 | T20: 1 | U20: 1 | V20: 1 | W20: 1 | X20: 1 | Y20: 1 | Z20: 1 | AA20: 1 | AB20: 1 | AC20: 1 | AD20: 1 | AE20: 1 | AF20: 1 | AG20: =SUM(G20:AF20) -> 26 | AH20: =D20*AG20 -> -412481
A21: CERAMICA PISO DE BALCON | B21: ='DETALLE PRESUPUESTO POR PARTIDA'!P95 -> 30502.77 | C21: ='DETALLE PRESUPUESTO POR PARTIDA'!Q95 -> 23760.566 | D21: =C21-B21 -> -6742.2042 | E21: =D21/B21 -> -0.2210358 | F21: Ahorro precio de porcelanato | H21: 1 | I21: 1 | J21: 1 | K21: 1 | L21: 1 | M21: 1 | N21: 1 | O21: 1 | P21: 1 | Q21: 1 | R21: 1 | S21: 1 | T21: 1 | U21: 1 | V21: 1 | W21: 1 | X21: 1 | Y21: 1 | Z21: 1 | AA21: 1 | AB21: 1 | AC21: 1 | AD21: 1 | AE21: 1 | AF21: 1 | AG21: =SUM(G21:AF21) -> 25 | AH21: =D21*AG21 -> -168555.11
A22: CERAMICA PISO DE ESCALERA | B22: ='DETALLE PRESUPUESTO POR PARTIDA'!P96 -> 342436.18 | C22: ='DETALLE PRESUPUESTO POR PARTIDA'!Q96 -> 324989.58 | D22: =C22-B22 -> -17446.603 | E22: =D22/B22 -> -0.050948481 | F22: Ahorro precio de porcelanato | G22: 1 | H22: 1 | I22: 1 | J22: 1 | K22: 1 | L22: 1 | M22: 1 | N22: 1 | O22: 1 | P22: 1 | Q22: 1 | R22: 1 | S22: 1 | T22: 1 | U22: 1 | V22: 1 | W22: 1 | X22: 1 | Y22: 1 | Z22: 1 | AA22: 1 | AB22: 1 | AC22: 1 | AD22: 1 | AE22: 1 | AF22: 1 | AG22: =SUM(G22:AF22) -> 26 | AH22: =D22*AG22 -> -453611.68
A23: TABLILLA | B23: ='DETALLE PRESUPUESTO POR PARTIDA'!P97 -> 270541.04 | C23: ='DETALLE PRESUPUESTO POR PARTIDA'!J104 -> 372603.92 | D23: =C23-B23 -> 102062.88 | E23: =D23/B23 -> 0.37725472 | F23: Disminucion precio Tablilla,Disminucion de rendimiento,Aumento precio mano de obra | M23: 1 | N23: 1 | O23: 1 | P23: 1 | Q23: 1 | R23: 1 | S23: 1 | T23: 1 | U23: 1 | V23: 1 | W23: 1 | X23: 1 | Y23: 1 | Z23: 1 | AA23: 1 | AB23: 1 | AC23: 1 | AD23: 1 | AE23: 1 | AF23: 1 | AG23: =SUM(G23:AF23) -> 20 | AH23: =D23*AG23 -> 2041257.7
A24: PARED DE BANO | B24: ='DETALLE PRESUPUESTO POR PARTIDA'!G97 -> 472720.43 | C24: ='DETALLE PRESUPUESTO POR PARTIDA'!J97 -> 326690 | D24: =C24-B24 -> -146030.43 | E24: =D24/B24 -> -0.308915 | F24: Ahorro respecto Original -Disminucion de cantidad y precio de porcelanato | H24: 1 | I24: 1 | J24: 1 | K24: 1 | L24: 1 | M24: 1 | N24: 1 | O24: 1 | P24: 1 | Q24: 1 | R24: 1 | S24: 1 | T24: 1 | U24: 1 | V24: 1 | W24: 1 | X24: 1 | Y24: 1 | Z24: 1 | AA24: 1 | AB24: 1 | AC24: 1 | AD24: 1 | AE24: 1 | AF24: 1 | AG24: =SUM(G24:AF24) -> 25 | AH24: =D24*AG24 -> -3650760.8
A25: PARED COCINA | B25: ='DETALLE PRESUPUESTO POR PARTIDA'!G98 -> 17020.82 | C25: ='DETALLE PRESUPUESTO POR PARTIDA'!J98 -> 0 | D25: =C25-B25 -> -17020.82 | E25: =D25/B25 -> -1 | F25: Ahorro se disminuyo partida | G25: 1 | H25: 1 | I25: 1 | J25: 1 | K25: 1 | L25: 1 | M25: 1 | N25: 1 | O25: 1 | P25: 1 | Q25: 1 | R25: 1 | S25: 1 | T25: 1 | U25: 1 | V25: 1 | W25: 1 | X25: 1 | Y25: 1 | Z25: 1 | AA25: 1 | AB25: 1 | AC25: 1 | AD25: 1 | AE25: 1 | AF25: 1 | AG25: =SUM(G25:AF25) -> 26 | AH25: =D25*AG25 -> -442541.32
A26: MISCELANEOS | B26: 1796013 | C26: 1583593 | D26: =C26-B26 -> -212420 | E26: =D26/B26 -> -0.11827309 | F26: Ahorro respecto al original | G26: 1 | H26: 1 | I26: 1 | J26: 1 | K26: 1 | L26: 1 | M26: 1 | N26: 1 | O26: 1 | P26: 1 | Q26: 1 | R26: 1 | S26: 1 | T26: 1 | U26: 1 | V26: 1 | W26: 1 | X26: 1 | Y26: 1 | Z26: 1 | AA26: 1 | AB26: 1 | AC26: 1 | AD26: 1 | AE26: 1 | AF26: 1 | AG26: =SUM(G26:AF26) -> 26 | AH26: =D26*AG26 -> -5522920
A27: VIDRIO Y ALUMINIO | B27: 1016412.5 | C27: 907917.8 | D27: =C27-B27 -> -108494.7 | E27: =D27/B27 -> -0.10674278 | F27: Ahorro respecto al original | G27: 1 | H27: 1 | I27: 1 | J27: 1 | K27: 1 | L27: 1 | M27: 1 | N27: 1 | O27: 1 | P27: 1 | Q27: 1 | R27: 1 | S27: 1 | T27: 1 | U27: 1 | V27: 1 | W27: 1 | X27: 1 | Y27: 1 | Z27: 1 | AA27: 1 | AB27: 1 | AC27: 1 | AD27: 1 | AE27: 1 | AF27: 1 | AG27: =SUM(G27:AF27) -> 26 | AH27: =D27*AG27 -> -2820862.2
A28: TOTALES | B28: =SUM(B4:B27) -> 19903103 | C28: =SUM(C4:C27) -> 19963553 | D28: =C28-B28 -> 60450.616 | E28: =D28/B28 -> 0.0030372459 | AH28: =SUM(AH4:AH27) -> -1613789.9
AH29: =AH28/B32 -> -0.0031185512
A30: M2 x Apartamento en Pesos | B30: 38571.904 | C30: 38839.691
A31: Total x 77 Edificios | B31: =B28*77 -> 1.5325389e+09 | C31: =C28*77 -> 1.5371936e+09 | D31: =C31-B31 -> 4654697.4 | E31: =D31/B31 -> 0.0030372459
A32: Total x 26 Edificios | B32: =B28*26 -> 5.1748067e+08 | C32: =C28*26 -> 5.1905238e+08 | D32: =C32-B32 -> 1571716 | E32: =D32/B32 -> 0.0030372459
A34: PUNTOS CLAVE
A35: • El costo total subió apenas 0.7% ($138,178 adicionales), un ajuste contenido dado el volumen del presupuesto (~$20 millones).
A36: • Mayores incrementos: Carpintería (+17.1%), Piezas Sanitarias (+12.7%) e Infraestructura (+6.4%), principalmente por aumento en cantidades y precio del hormigón (empresa Bluewave).
A37: • Mayores ahorros: Misceláneos (-11.8%), Vidrio y Aluminio (-10.7%) y Revestimiento (-8.7%), que compensan buena parte de las alzas.
A38: • 6 capítulos (Telecomunicaciones, Sanitarias, Incendio, Pintura, Limpieza, y parcialmente Herrería) no tuvieron cambios entre el presupuesto original y actualizado.
A39: • Escalado a 77 edificios, la diferencia total equivale a aprox. +$10.6 millones, un ajuste relevante a nivel de proyecto aunque el impacto por edificio sea pequeño.
