Workbook

Sheet Flujo Completo Reprogramado
A1: Flujo Completo Mensual — Real + Reprogramado (Dic-2025 a Jul-2027)
A2: Bloque 1: presupuesto original (referencia, fuente Flujo_Araya_fase_I). Bloque 2: real ejecutado (Dic-25 a Jul-26) y proyección (Ago-26 a Jul-27, con la variación acumulada de Dic-25 a Jul-26 redistribuida solo en Ago-26 y Sep-26) — cierra en el total de RD$751,309,285.
A4: BLOQUE 1 — PRESUPUESTO ORIGINAL (referencia)
A5: Categoría | B5: Acum. Anterior | C5: Dic-25 | D5: Ene-26 | E5: Feb-26 | F5: Mar-26 | G5: Abr-26 | H5: May-26 | I5: Jun-26 | J5: Jul-26 | K5: Ago-26 | L5: Sep-26 | M5: Oct-26 | N5: Nov-26 | O5: Dic-26 | P5: Ene-27 | Q5: Feb-27 | R5: Mar-27 | S5: Abr-27 | T5: May-27 | U5: Jun-27 | V5: Jul-27 | W5: Ago-27 | X5: Sep-27 | Y5: Oct-27 | Z5: Nov-27 | AA5: Dic-27 | AB5: Ene-28 | AC5: Feb-28 | AD5: Mar-28 | AE5: Abr-28 | AF5: Total
A6: Instalaciones Preliminares | B6: 0 | C6: 330400 | D6: 128384 | E6: 1533833.6 | F6: 0 | G6: 0 | H6: 0 | I6: 0 | J6: 0 | K6: 0 | L6: 0 | M6: 0 | N6: 0 | O6: 0 | P6: 0 | Q6: 0 | R6: 0 | S6: 0 | T6: 0 | U6: 0 | V6: 0 | W6: 0 | X6: 0 | Y6: 0 | Z6: 0 | AA6: 0 | AB6: 0 | AC6: 0 | AD6: 0 | AE6: 0 | AF6: =SUM(B6,C6:AE6) -> 1992617.6
A7: Movimiento de Tierra | B7: 0 | C7: 0 | D7: 0 | E7: 0 | F7: 0 | G7: 1895547.6 | H7: 4597021 | I7: 4597021 | J7: 0 | K7: 0 | L7: 0 | M7: 0 | N7: 0 | O7: 0 | P7: 0 | Q7: 0 | R7: 0 | S7: 0 | T7: 0 | U7: 0 | V7: 0 | W7: 0 | X7: 0 | Y7: 0 | Z7: 0 | AA7: 0 | AB7: 0 | AC7: 0 | AD7: 0 | AE7: 0 | AF7: =SUM(B7,C7:AE7) -> 11089590
A8: Instalaciones Residual | B8: 0 | C8: 0 | D8: 0 | E8: 0 | F8: 0 | G8: 0 | H8: 0 | I8: 2456464.8 | J8: 1228232.4 | K8: 2456464.8 | L8: 3684697.2 | M8: 2456464.8 | N8: 0 | O8: 0 | P8: 0 | Q8: 0 | R8: 0 | S8: 0 | T8: 0 | U8: 0 | V8: 0 | W8: 0 | X8: 0 | Y8: 0 | Z8: 0 | AA8: 0 | AB8: 0 | AC8: 0 | AD8: 0 | AE8: 0 | AF8: =SUM(B8,C8:AE8) -> 12282324
A9: Instalaciones Pluvial | B9: 0 | C9: 0 | D9: 0 | E9: 0 | F9: 0 | G9: 0 | H9: 0 | I9: 0 | J9: 0 | K9: 1298558.4 | L9: 1298558.4 | M9: 2597116.8 | N9: 1298558.4 | O9: 0 | P9: 0 | Q9: 0 | R9: 0 | S9: 0 | T9: 0 | U9: 0 | V9: 0 | W9: 0 | X9: 0 | Y9: 0 | Z9: 0 | AA9: 0 | AB9: 0 | AC9: 0 | AD9: 0 | AE9: 0 | AF9: =SUM(B9,C9:AE9) -> 6492792
A10: Instalaciones Agua Potable | B10: 0 | C10: 0 | D10: 0 | E10: 0 | F10: 0 | G10: 0 | H10: 0 | I10: 0 | J10: 1005131.4 | K10: 1005131.4 | L10: 1507697.1 | M10: 1005131.4 | N10: 502565.69 | O10: 0 | P10: 0 | Q10: 0 | R10: 0 | S10: 0 | T10: 0 | U10: 0 | V10: 0 | W10: 0 | X10: 0 | Y10: 0 | Z10: 0 | AA10: 0 | AB10: 0 | AC10: 0 | AD10: 0 | AE10: 0 | AF10: =SUM(B10,C10:AE10) -> 5025656.9
A11: Pozo y Tanques | B11: 0 | C11: 0 | D11: 0 | E11: 0 | F11: 0 | G11: 0 | H11: 0 | I11: 0 | J11: 0 | K11: 3108517.7 | L11: 3108517.7 | M11: 6217035.4 | N11: 6217035.4 | O11: 6217035.4 | P11: 6183196.6 | Q11: 0 | R11: 0 | S11: 0 | T11: 0 | U11: 0 | V11: 0 | W11: 0 | X11: 0 | Y11: 0 | Z11: 0 | AA11: 0 | AB11: 0 | AC11: 0 | AD11: 0 | AE11: 0 | AF11: =SUM(B11,C11:AE11) -> 31051338
A12: Escalera | B12: 0 | C12: 0 | D12: 0 | E12: 0 | F12: 0 | G12: 0 | H12: 0 | I12: 0 | J12: 0 | K12: 0 | L12: 0 | M12: 0 | N12: 0 | O12: 0 | P12: 0 | Q12: 0 | R12: 0 | S12: 0 | T12: 0 | U12: 0 | V12: 0 | W12: 0 | X12: 0 | Y12: 0 | Z12: 0 | AA12: 0 | AB12: 0 | AC12: 0 | AD12: 0 | AE12: 0 | AF12: =SUM(B12,C12:AE12) -> 0
A13: Planta de Tratamiento | B13: 0 | C13: 0 | D13: 0 | E13: 0 | F13: 0 | G13: 0 | H13: 0 | I13: 4159815.1 | J13: 0 | K13: 1386605 | L13: 2773210 | M13: 2773210 | N13: 1386605 | O13: 1386605 | P13: 0 | Q13: 0 | R13: 0 | S13: 0 | T13: 0 | U13: 0 | V13: 0 | W13: 0 | X13: 0 | Y13: 0 | Z13: 0 | AA13: 0 | AB13: 0 | AC13: 0 | AD13: 0 | AE13: 0 | AF13: =SUM(B13,C13:AE13) -> 13866050
A14: Electrificacion y Telecom | B14: 0 | C14: 0 | D14: 0 | E14: 0 | F14: 0 | G14: 0 | H14: 0 | I14: 0 | J14: 0 | K14: 16627956 | L14: 6651182.3 | M14: 6651182.3 | N14: 6651182.3 | O14: 6651182.3 | P14: 6651182.3 | Q14: 6651182.3 | R14: 10242177 | S14: 0 | T14: 0 | U14: 0 | V14: 0 | W14: 0 | X14: 0 | Y14: 0 | Z14: 0 | AA14: 0 | AB14: 0 | AC14: 0 | AD14: 0 | AE14: 0 | AF14: =SUM(B14,C14:AE14) -> 66777227
A15: Vialidad y Gas | B15: 0 | C15: 0 | D15: 0 | E15: 0 | F15: 0 | G15: 0 | H15: 0 | I15: 0 | J15: 0 | K15: 0 | L15: 0 | M15: 3306411.3 | N15: 826602.81 | O15: 2479808.4 | P15: 826602.81 | Q15: 3306411.3 | R15: 1653205.6 | S15: 2479808.4 | T15: 2831079.6 | U15: 0 | V15: 0 | W15: 0 | X15: 0 | Y15: 0 | Z15: 0 | AA15: 0 | AB15: 0 | AC15: 0 | AD15: 0 | AE15: 0 | AF15: =SUM(B15,C15:AE15) -> 17709930
A16: Cocina | B16: 0 | C16: 0 | D16: 0 | E16: 0 | F16: 0 | G16: 0 | H16: 0 | I16: 0 | J16: 0 | K16: 0 | L16: 0 | M16: 0 | N16: 0 | O16: 0 | P16: 0 | Q16: 0 | R16: 0 | S16: 0 | T16: 0 | U16: 0 | V16: 0 | W16: 0 | X16: 0 | Y16: 0 | Z16: 0 | AA16: 0 | AB16: 0 | AC16: 0 | AD16: 0 | AE16: 0 | AF16: =SUM(B16,C16:AE16) -> 0
A17: Paisajismo | B17: 0 | C17: 0 | D17: 0 | E17: 0 | F17: 0 | G17: 0 | H17: 0 | I17: 0 | J17: 0 | K17: 0 | L17: 0 | M17: 0 | N17: 1796347.4 | O17: 718538.96 | P17: 1437077.9 | Q17: 1437077.9 | R17: 1437077.9 | S17: 359269.48 | T17: 1718806.8 | U17: 0 | V17: 0 | W17: 0 | X17: 0 | Y17: 0 | Z17: 0 | AA17: 0 | AB17: 0 | AC17: 0 | AD17: 0 | AE17: 0 | AF17: =SUM(B17,C17:AE17) -> 8904196.4
A18: Elementos Urbanos y Obras Ext. | B18: 0 | C18: 791187.8 | D18: 301404.37 | E18: 4265784.7 | F18: 688406.98 | G18: 0 | H18: 0 | I18: 0 | J18: 0 | K18: 0 | L18: 0 | M18: 5178434.3 | N18: 3452289.5 | O18: 5178434.3 | P18: 3452289.5 | Q18: 3452289.5 | R18: 6639957.6 | S18: 1122416.6 | T18: 4012087.9 | U18: 0 | V18: 0 | W18: 0 | X18: 0 | Y18: 0 | Z18: 0 | AA18: 0 | AB18: 0 | AC18: 0 | AD18: 0 | AE18: 0 | AF18: =SUM(B18,C18:AE18) -> 38534983
A19: TOTAL URBANISMO | B19: 22125480 | C19: =SUM(C6:C18) -> 1121587.8 | D19: =SUM(D6:D18) -> 429788.37 | E19: =SUM(E6:E18) -> 5799618.3 | F19: =SUM(F6:F18) -> 688406.98 | G19: =SUM(G6:G18) -> 1895547.6 | H19: =SUM(H6:H18) -> 4597021 | I19: =SUM(I6:I18) -> 11213301 | J19: =SUM(J6:J18) -> 2233363.8 | ... AE19: =SUM(AE6:AE18) -> 0 | AF19: =SUM(B19:AE19) -> 2.3585219e+08
A21: Excavaciones y Compactacion | B21: 0 | C21: 360773.79 | D21: 360773.79 | E21: 721547.59 | F21: 1443095.2 | G21: 1443095.2 | H21: 1443095.2 | I21: 1443095.2 | J21: 1443095.2 | K21: 721547.59 | L21: 0 | M21: 0 | N21: 0 | O21: 0 | P21: 0 | Q21: 0 | R21: 0 | S21: 0 | T21: 0 | U21: 0 | V21: 0 | W21: 0 | X21: 0 | Y21: 0 | Z21: 0 | AA21: 0 | AB21: 0 | AC21: 0 | AD21: 0 | AE21: 0 | AF21: =SUM(B21,C21:AE21) -> 9380118.6
A22: Acero en Platea | B22: 0 | C22: 446815.89 | D22: 446815.89 | E22: 893631.78 | F22: 1787263.6 | G22: 1787263.6 | H22: 1787263.6 | I22: 1787263.6 | J22: 1787263.6 | K22: 893631.78 | L22: 0 | M22: 0 | N22: 0 | O22: 0 | P22: 0 | Q22: 0 | R22: 0 | S22: 0 | T22: 0 | U22: 0 | V22: 0 | W22: 0 | X22: 0 | Y22: 0 | Z22: 0 | AA22: 0 | AB22: 0 | AC22: 0 | AD22: 0 | AE22: 0 | AF22: =SUM(B22,C22:AE22) -> 11617213
A23: Encofrado en Platea | B23: 0 | C23: 44847.285 | D23: 44847.285 | E23: 89694.569 | F23: 179389.14 | G23: 179389.14 | H23: 179389.14 | I23: 179389.14 | J23: 179389.14 | K23: 89694.569 | L23: 0 | M23: 0 | N23: 0 | O23: 0 | P23: 0 | Q23: 0 | R23: 0 | S23: 0 | T23: 0 | U23: 0 | V23: 0 | W23: 0 | X23: 0 | Y23: 0 | Z23: 0 | AA23: 0 | AB23: 0 | AC23: 0 | AD23: 0 | AE23: 0 | AF23: =SUM(B23,C23:AE23) -> 1166029.4
A24: Concreto en Platea | B24: 0 | C24: 534800.56 | D24: 534800.56 | E24: 1069601.1 | F24: 2139202.2 | G24: 2139202.2 | H24: 2139202.2 | I24: 2139202.2 | J24: 2139202.2 | K24: 1069601.1 | L24: 0 | M24: 0 | N24: 0 | O24: 0 | P24: 0 | Q24: 0 | R24: 0 | S24: 0 | T24: 0 | U24: 0 | V24: 0 | W24: 0 | X24: 0 | Y24: 0 | Z24: 0 | AA24: 0 | AB24: 0 | AC24: 0 | AD24: 0 | AE24: 0 | AF24: =SUM(B24,C24:AE24) -> 13904815
A25: Concreto en Molde | B25: 0 | C25: 0 | D25: 0 | E25: 79839.163 | F25: 958069.96 | G25: 2475014.1 | H25: 3353244.9 | I25: 4790349.8 | J25: 4950028.1 | K25: 6227454.8 | L25: 4790349.8 | M25: 4790349.8 | N25: 4790349.8 | O25: 4311314.8 | P25: 0 | Q25: 0 | R25: 0 | S25: 0 | T25: 0 | U25: 0 | V25: 0 | W25: 0 | X25: 0 | Y25: 0 | Z25: 0 | AA25: 0 | AB25: 0 | AC25: 0 | AD25: 0 | AE25: 0 | AF25: =SUM(B25,C25:AE25) -> 41516365
A26: Encofrado en Molde | B26: 0 | C26: 0 | D26: 0 | E26: 344766.8 | F26: 1379067.2 | G26: 2413367.6 | H26: 3447668 | I26: 4137201.6 | J26: 4826735.2 | K26: 4826735.2 | L26: 4137201.6 | M26: 4137201.6 | N26: 4137201.6 | O26: 2068600.8 | P26: 0 | Q26: 0 | R26: 0 | S26: 0 | T26: 0 | U26: 0 | V26: 0 | W26: 0 | X26: 0 | Y26: 0 | Z26: 0 | AA26: 0 | AB26: 0 | AC26: 0 | AD26: 0 | AE26: 0 | AF26: =SUM(B26,C26:AE26) -> 35855747
A27: Acero en Superestructura | B27: 0 | C27: 0 | D27: 0 | E27: 333722.19 | F27: 1668611 | G27: 2669777.5 | H27: 3670944.1 | I27: 4004666.3 | J27: 4672110.7 | K27: 4672110.7 | L27: 4004666.3 | M27: 4004666.3 | N27: 4004666.3 | O27: 1001166.6 | P27: 0 | Q27: 0 | R27: 0 | S27: 0 | T27: 0 | U27: 0 | V27: 0 | W27: 0 | X27: 0 | Y27: 0 | Z27: 0 | AA27: 0 | AB27: 0 | AC27: 0 | AD27: 0 | AE27: 0 | AF27: =SUM(B27,C27:AE27) -> 34707108
A28: Instalaciones Electricas | B28: 0 | C28: 0 | D28: 0 | E28: 88641.51 | F28: 354566.04 | G28: 620490.57 | H28: 886415.1 | I28: 1063698.1 | J28: 1240981.1 | K28: 1240981.1 | L28: 1063698.1 | M28: 1063698.1 | N28: 1063698.1 | O28: 531849.06 | P28: 0 | Q28: 0 | R28: 0 | S28: 0 | T28: 0 | U28: 0 | V28: 0 | W28: 0 | X28: 0 | Y28: 0 | Z28: 0 | AA28: 0 | AB28: 0 | AC28: 0 | AD28: 0 | AE28: 0 | AF28: =SUM(B28,C28:AE28) -> 9218717
A29: Aguas Blancas | B29: 0 | C29: 0 | D29: 0 | E29: 58435.092 | F29: 233740.37 | G29: 409045.65 | H29: 584350.93 | I29: 701221.11 | J29: 818091.3 | K29: 818091.3 | L29: 701221.11 | M29: 701221.11 | N29: 701221.11 | O29: 350610.55 | P29: 0 | Q29: 0 | R29: 0 | S29: 0 | T29: 0 | U29: 0 | V29: 0 | W29: 0 | X29: 0 | Y29: 0 | Z29: 0 | AA29: 0 | AB29: 0 | AC29: 0 | AD29: 0 | AE29: 0 | AF29: =SUM(B29,C29:AE29) -> 6077249.6
A30: Aguas Residuales | B30: 0 | C30: 0 | D30: 0 | E30: 64617.03 | F30: 258468.12 | G30: 452319.21 | H30: 646170.3 | I30: 775404.36 | J30: 904638.42 | K30: 904638.42 | L30: 775404.36 | M30: 775404.36 | N30: 775404.36 | O30: 387702.18 | P30: 0 | Q30: 0 | R30: 0 | S30: 0 | T30: 0 | U30: 0 | V30: 0 | W30: 0 | X30: 0 | Y30: 0 | Z30: 0 | AA30: 0 | AB30: 0 | AC30: 0 | AD30: 0 | AE30: 0 | AF30: =SUM(B30,C30:AE30) -> 6720171.1
A31: Gas | B31: 0 | C31: 0 | D31: 0 | E31: 16494.715 | F31: 65978.86 | G31: 115463.01 | H31: 164947.15 | I31: 197936.58 | J31: 230926.01 | K31: 230926.01 | L31: 197936.58 | M31: 197936.58 | N31: 197936.58 | O31: 98968.29 | P31: 0 | Q31: 0 | R31: 0 | S31: 0 | T31: 0 | U31: 0 | V31: 0 | W31: 0 | X31: 0 | Y31: 0 | Z31: 0 | AA31: 0 | AB31: 0 | AC31: 0 | AD31: 0 | AE31: 0 | AF31: =SUM(B31,C31:AE31) -> 1715450.4
A32: Albañileria | B32: 0 | C32: 0 | D32: 0 | E32: 0 | F32: 0 | G32: 2658473.8 | H32: 2658473.8 | I32: 2658473.8 | J32: 2658473.8 | K32: 2658473.8 | L32: 2658473.8 | M32: 2658473.8 | N32: 2658473.8 | O32: 1772315.9 | P32: 0 | Q32: 0 | R32: 0 | S32: 0 | T32: 0 | U32: 0 | V32: 0 | W32: 0 | X32: 0 | Y32: 0 | Z32: 0 | AA32: 0 | AB32: 0 | AC32: 0 | AD32: 0 | AE32: 0 | AF32: =SUM(B32,C32:AE32) -> 23040106
... A44: Remates y Limpieza | B44: 0 | C44: 0 | D44: 0 | E44: 0 | F44: 0 | G44: 0 | H44: 0 | I44: 0 | J44: 0 | K44: 0 | L44: 347981.54 | M44: 521972.31 | N44: 521972.31 | O44: 521972.31 | P44: 521972.31 | Q44: 521972.31 | R44: 521972.31 | S44: 521972.31 | T44: 260986.15 | U44: 260986.15 | V44: 0 | W44: 0 | X44: 0 | Y44: 0 | Z44: 0 | AA44: 0 | AB44: 0 | AC44: 0 | AD44: 0 | AE44: 0 | AF44: =SUM(B44,C44:AE44) -> 4523760
A45: TOTAL EDIFICIOS | B45: 0 | C45: =SUM(C21:C44) -> 1387237.5 | D45: =SUM(D21:D44) -> 1387237.5 | E45: =SUM(E21:E44) -> 3798163.3 | F45: =SUM(F21:F44) -> 11925251 | G45: =SUM(G21:G44) -> 29783110 | H45: =SUM(H21:H44) -> 38576638 | I45: =SUM(I21:I44) -> 68677665 | J45: =SUM(J21:J44) -> 42068379 | ... AE45: =SUM(AE21:AE44) -> 0 | AF45: =SUM(B45:AE45) -> 5.154571e+08
A47: TOTAL GENERAL | B47: =B19+B45 -> 22125480 | C47: =C19+C45 -> 2508825.3 | D47: =D19+D45 -> 1817025.9 | E47: =E19+E45 -> 9597781.6 | F47: =F19+F45 -> 12613658 | G47: =G19+G45 -> 31678657 | H47: =H19+H45 -> 43173659 | I47: =I19+I45 -> 79890966 | ... AF47: =AF19+AF45 -> 7.5130928e+08
A49: BLOQUE 2 — REAL EJECUTADO (Dic-25 a Jul-26) + REPROGRAMADO (Ago-26 a Jul-27)
A50: Categoría | B50: Acum. Anterior | C50: Dic-25 | D50: Ene-26 | E50: Feb-26 | F50: Mar-26 | G50: Abr-26 | H50: May-26 | I50: Jun-26 | J50: Jul-26 | K50: Ago-26 | L50: Sep-26 | M50: Oct-26 | N50: Nov-26 | O50: Dic-26 | P50: Ene-27 | Q50: Feb-27 | R50: Mar-27 | S50: Abr-27 | T50: May-27 | U50: Jun-27 | V50: Jul-27 | W50: Ago-27 | X50: Sep-27 | Y50: Oct-27 | Z50: Nov-27 | AA50: Dic-27 | AB50: Ene-28 | AC50: Feb-28 | AD50: Mar-28 | AE50: Abr-28 | AF50: Total
A51: Instalaciones Preliminares | B51: 0 | C51: =IFERROR(C6*'Comparación Mensual'!C5/C19,0) -> 4538721 | D51: =IFERROR(D6*'Comparación Mensual'!C6/D19,0) -> 66566.996 | E51: =IFERROR(E6*'Comparación Mensual'!C7/E19,0) -> 647841.35 | F51: =IFERROR(F6*'Comparación Mensual'!C8/F19,0) -> 0 | G51: =IFERROR(G6*'Comparación Mensual'!C9/G19,0) -> 0 | H51: =IFERROR(H6*'Comparación Mensual'!C10/H19,0) -> 0 | I51: =IFERROR(I6*'Comparación Mensual'!C11/I19,0) -> 0 | J51: =IFERROR(J6*'Comparación Mensual'!C12/J19,0) -> 0 | K51: =K6*Reprogramación!$C$14/Reprogramación!$B$14 -> 0 | L51: =L6*Reprogramación!$C$15/Reprogramación!$B$15 -> 0 | M51: =M6 -> 0 | N51: =N6 -> 0 | O51: =O6 -> 0 | P51: =P6 -> 0 | Q51: =Q6 -> 0 | R51: =R6 -> 0 | S51: =S6 -> 0 | T51: =T6 -> 0 | ... V51: =V6 -> 0 | W51: 0 | X51: 0 | Y51: 0 | Z51: 0 | AA51: 0 | AB51: 0 | AC51: 0 | AD51: 0 | AE51: 0 | AF51: =SUM(B51,C51:AE51) -> 5253129.3
A52: Movimiento de Tierra | B52: 0 | C52: =IFERROR(C7*'Comparación Mensual'!C5/C19,0) -> 0 | D52: =IFERROR(D7*'Comparación Mensual'!C6/D19,0) -> 0 | E52: =IFERROR(E7*'Comparación Mensual'!C7/E19,0) -> 0 | F52: =IFERROR(F7*'Comparación Mensual'!C8/F19,0) -> 0 | G52: =IFERROR(G7*'Comparación Mensual'!C9/G19,0) -> 2442502.3 | H52: =IFERROR(H7*'Comparación Mensual'!C10/H19,0) -> 4340947.8 | I52: =IFERROR(I7*'Comparación Mensual'!C11/I19,0) -> 2244901.6 | J52: =IFERROR(J7*'Comparación Mensual'!C12/J19,0) -> 0 | K52: =K7*Reprogramación!$C$14/Reprogramación!$B$14 -> 0 | L52: =L7*Reprogramación!$C$15/Reprogramación!$B$15 -> 0 | M52: =M7 -> 0 | N52: =N7 -> 0 | O52: =O7 -> 0 | P52: =P7 -> 0 | Q52: =Q7 -> 0 | R52: =R7 -> 0 | S52: =S7 -> 0 | T52: =T7 -> 0 | ... V52: =V7 -> 0 | W52: 0 | X52: 0 | Y52: 0 | Z52: 0 | AA52: 0 | AB52: 0 | AC52: 0 | AD52: 0 | AE52: 0 | AF52: =SUM(B52,C52:AE52) -> 9028351.8
A53: Instalaciones Residual | B53: 0 | C53: =IFERROR(C8*'Comparación Mensual'!C5/C19,0) -> 0 | D53: =IFERROR(D8*'Comparación Mensual'!C6/D19,0) -> 0 | E53: =IFERROR(E8*'Comparación Mensual'!C7/E19,0) -> 0 | F53: =IFERROR(F8*'Comparación Mensual'!C8/F19,0) -> 0 | G53: =IFERROR(G8*'Comparación Mensual'!C9/G19,0) -> 0 | H53: =IFERROR(H8*'Comparación Mensual'!C10/H19,0) -> 0 | I53: =IFERROR(I8*'Comparación Mensual'!C11/I19,0) -> 1199586 | J53: =IFERROR(J8*'Comparación Mensual'!C12/J19,0) -> 4468464.1 | K53: =K8*Reprogramación!$C$14/Reprogramación!$B$14 -> 1871864.9 | L53: =L8*Reprogramación!$C$15/Reprogramación!$B$15 -> 2491616.5 | M53: =M8 -> 2456464.8 | N53: =N8 -> 0 | O53: =O8 -> 0 | P53: =P8 -> 0 | Q53: =Q8 -> 0 | R53: =R8 -> 0 | S53: =S8 -> 0 | T53: =T8 -> 0 | ... V53: =V8 -> 0 | W53: 0 | X53: 0 | Y53: 0 | Z53: 0 | AA53: 0 | AB53: 0 | AC53: 0 | AD53: 0 | AE53: 0 | AF53: =SUM(B53,C53:AE53) -> 12487996
A54: Instalaciones Pluvial | B54: 0 | C54: =IFERROR(C9*'Comparación Mensual'!C5/C19,0) -> 0 | D54: =IFERROR(D9*'Comparación Mensual'!C6/D19,0) -> 0 | E54: =IFERROR(E9*'Comparación Mensual'!C7/E19,0) -> 0 | F54: =IFERROR(F9*'Comparación Mensual'!C8/F19,0) -> 0 | G54: =IFERROR(G9*'Comparación Mensual'!C9/G19,0) -> 0 | H54: =IFERROR(H9*'Comparación Mensual'!C10/H19,0) -> 0 | I54: =IFERROR(I9*'Comparación Mensual'!C11/I19,0) -> 0 | J54: =IFERROR(J9*'Comparación Mensual'!C12/J19,0) -> 0 | K54: =K9*Reprogramación!$C$14/Reprogramación!$B$14 -> 989521.96 | L54: =L9*Reprogramación!$C$15/Reprogramación!$B$15 -> 878093.73 | M54: =M9 -> 2597116.8 | N54: =N9 -> 1298558.4 | O54: =O9 -> 0 | P54: =P9 -> 0 | Q54: =Q9 -> 0 | R54: =R9 -> 0 | S54: =S9 -> 0 | T54: =T9 -> 0 | ... V54: =V9 -> 0 | W54: 0 | X54: 0 | Y54: 0 | Z54: 0 | AA54: 0 | AB54: 0 | AC54: 0 | AD54: 0 | AE54: 0 | AF54: =SUM(B54,C54:AE54) -> 5763290.9
A55: Instalaciones Agua Potable | B55: 0 | C55: =IFERROR(C10*'Comparación Mensual'!C5/C19,0) -> 0 | D55: =IFERROR(D10*'Comparación Mensual'!C6/D19,0) -> 0 | E55: =IFERROR(E10*'Comparación Mensual'!C7/E19,0) -> 0 | F55: =IFERROR(F10*'Comparación Mensual'!C8/F19,0) -> 0 | G55: =IFERROR(G10*'Comparación Mensual'!C9/G19,0) -> 0 | H55: =IFERROR(H10*'Comparación Mensual'!C10/H19,0) -> 0 | I55: =IFERROR(I10*'Comparación Mensual'!C11/I19,0) -> 0 | J55: =IFERROR(J10*'Comparación Mensual'!C12/J19,0) -> 3656794.5 | K55: =K10*Reprogramación!$C$14/Reprogramación!$B$14 -> 765925.95 | L55: =L10*Reprogramación!$C$15/Reprogramación!$B$15 -> 1019514.7 | M55: =M10 -> 1005131.4 | N55: =N10 -> 502565.69 | O55: =O10 -> 0 | P55: =P10 -> 0 | Q55: =Q10 -> 0 | R55: =R10 -> 0 | S55: =S10 -> 0 | T55: =T10 -> 0 | ... V55: =V10 -> 0 | W55: 0 | X55: 0 | Y55: 0 | Z55: 0 | AA55: 0 | AB55: 0 | AC55: 0 | AD55: 0 | AE55: 0 | AF55: =SUM(B55,C55:AE55) -> 6949932.1
A56: Pozo y Tanques | B56: 0 | C56: =IFERROR(C11*'Comparación Mensual'!C5/C19,0) -> 0 | D56: =IFERROR(D11*'Comparación Mensual'!C6/D19,0) -> 0 | E56: =IFERROR(E11*'Comparación Mensual'!C7/E19,0) -> 0 | F56: =IFERROR(F11*'Comparación Mensual'!C8/F19,0) -> 0 | G56: =IFERROR(G11*'Comparación Mensual'!C9/G19,0) -> 0 | H56: =IFERROR(H11*'Comparación Mensual'!C10/H19,0) -> 0 | I56: =IFERROR(I11*'Comparación Mensual'!C11/I19,0) -> 0 | J56: =IFERROR(J11*'Comparación Mensual'!C12/J19,0) -> 0 | K56: =K11*Reprogramación!$C$14/Reprogramación!$B$14 -> 2368739.5 | L56: =L11*Reprogramación!$C$15/Reprogramación!$B$15 -> 2102000.1 | M56: =M11 -> 6217035.4 | N56: =N11 -> 6217035.4 | O56: =O11 -> 6217035.4 | P56: =P11 -> 6183196.6 | Q56: =Q11 -> 0 | R56: =R11 -> 0 | S56: =S11 -> 0 | T56: =T11 -> 0 | ... V56: =V11 -> 0 | W56: 0 | X56: 0 | Y56: 0 | Z56: 0 | AA56: 0 | AB56: 0 | AC56: 0 | AD56: 0 | AE56: 0 | AF56: =SUM(B56,C56:AE56) -> 29305042
A57: Escalera | B57: 0 | C57: =IFERROR(C12*'Comparación Mensual'!C5/C19,0) -> 0 | D57: =IFERROR(D12*'Comparación Mensual'!C6/D19,0) -> 0 | E57: =IFERROR(E12*'Comparación Mensual'!C7/E19,0) -> 0 | F57: =IFERROR(F12*'Comparación Mensual'!C8/F19,0) -> 0 | G57: =IFERROR(G12*'Comparación Mensual'!C9/G19,0) -> 0 | H57: =IFERROR(H12*'Comparación Mensual'!C10/H19,0) -> 0 | I57: =IFERROR(I12*'Comparación Mensual'!C11/I19,0) -> 0 | J57: =IFERROR(J12*'Comparación Mensual'!C12/J19,0) -> 0 | K57: =K12*Reprogramación!$C$14/Reprogramación!$B$14 -> 0 | L57: =L12*Reprogramación!$C$15/Reprogramación!$B$15 -> 0 | M57: =M12 -> 0 | N57: =N12 -> 0 | O57: =O12 -> 0 | P57: =P12 -> 0 | Q57: =Q12 -> 0 | R57: =R12 -> 0 | S57: =S12 -> 0 | T57: =T12 -> 0 | ... V57: =V12 -> 0 | W57: 0 | X57: 0 | Y57: 0 | Z57: 0 | AA57: 0 | AB57: 0 | AC57: 0 | AD57: 0 | AE57: 0 | AF57: =SUM(B57,C57:AE57) -> 0
A58: Planta de Tratamiento | B58: 0 | C58: =IFERROR(C13*'Comparación Mensual'!C5/C19,0) -> 0 | D58: =IFERROR(D13*'Comparación Mensual'!C6/D19,0) -> 0 | E58: =IFERROR(E13*'Comparación Mensual'!C7/E19,0) -> 0 | F58: =IFERROR(F13*'Comparación Mensual'!C8/F19,0) -> 0 | G58: =IFERROR(G13*'Comparación Mensual'!C9/G19,0) -> 0 | H58: =IFERROR(H13*'Comparación Mensual'!C10/H19,0) -> 0 | I58: =IFERROR(I13*'Comparación Mensual'!C11/I19,0) -> 2031397.2 | J58: =IFERROR(J13*'Comparación Mensual'!C12/J19,0) -> 0 | K58: =K13*Reprogramación!$C$14/Reprogramación!$B$14 -> 1056614.9 | L58: =L13*Reprogramación!$C$15/Reprogramación!$B$15 -> 1875262.9 | M58: =M13 -> 2773210 | N58: =N13 -> 1386605 | O58: =O13 -> 1386605 | P58: =P13 -> 0 | Q58: =Q13 -> 0 | R58: =R13 -> 0 | S58: =S13 -> 0 | T58: =T13 -> 0 | ... V58: =V13 -> 0 | W58: 0 | X58: 0 | Y58: 0 | Z58: 0 | AA58: 0 | AB58: 0 | AC58: 0 | AD58: 0 | AE58: 0 | AF58: =SUM(B58,C58:AE58) -> 10509695
A59: Electrificacion y Telecom | B59: 0 | C59: =IFERROR(C14*'Comparación Mensual'!C5/C19,0) -> 0 | D59: =IFERROR(D14*'Comparación Mensual'!C6/D19,0) -> 0 | E59: =IFERROR(E14*'Comparación Mensual'!C7/E19,0) -> 0 | F59: =IFERROR(F14*'Comparación Mensual'!C8/F19,0) -> 0 | G59: =IFERROR(G14*'Comparación Mensual'!C9/G19,0) -> 0 | H59: =IFERROR(H14*'Comparación Mensual'!C10/H19,0) -> 0 | I59: =IFERROR(I14*'Comparación Mensual'!C11/I19,0) -> 0 | J59: =IFERROR(J14*'Comparación Mensual'!C12/J19,0) -> 0 | K59: =K14*Reprogramación!$C$14/Reprogramación!$B$14 -> 12670764 | L59: =L14*Reprogramación!$C$15/Reprogramación!$B$15 -> 4497573.2 | M59: =M14 -> 6651182.3 | N59: =N14 -> 6651182.3 | O59: =O14 -> 6651182.3 | P59: =P14 -> 6651182.3 | Q59: =Q14 -> 6651182.3 | R59: =R14 -> 10242177 | S59: =S14 -> 0 | T59: =T14 -> 0 | ... V59: =V14 -> 0 | W59: 0 | X59: 0 | Y59: 0 | Z59: 0 | AA59: 0 | AB59: 0 | AC59: 0 | AD59: 0 | AE59: 0 | AF59: =SUM(B59,C59:AE59) -> 60666426
A60: Vialidad y Gas | B60: 0 | C60: =IFERROR(C15*'Comparación Mensual'!C5/C19,0) -> 0 | D60: =IFERROR(D15*'Comparación Mensual'!C6/D19,0) -> 0 | E60: =IFERROR(E15*'Comparación Mensual'!C7/E19,0) -> 0 | F60: =IFERROR(F15*'Comparación Mensual'!C8/F19,0) -> 0 | G60: =IFERROR(G15*'Comparación Mensual'!C9/G19,0) -> 0 | H60: =IFERROR(H15*'Comparación Mensual'!C10/H19,0) -> 0 | I60: =IFERROR(I15*'Comparación Mensual'!C11/I19,0) -> 0 | J60: =IFERROR(J15*'Comparación Mensual'!C12/J19,0) -> 0 | K60: =K15*Reprogramación!$C$14/Reprogramación!$B$14 -> 0 | L60: =L15*Reprogramación!$C$15/Reprogramación!$B$15 -> 0 | M60: =M15 -> 3306411.3 | N60: =N15 -> 826602.81 | O60: =O15 -> 2479808.4 | P60: =P15 -> 826602.81 | Q60: =Q15 -> 3306411.3 | R60: =R15 -> 1653205.6 | S60: =S15 -> 2479808.4 | T60: =T15 -> 2831079.6 | ... V60: =V15 -> 0 | W60: 0 | X60: 0 | Y60: 0 | Z60: 0 | AA60: 0 | AB60: 0 | AC60: 0 | AD60: 0 | AE60: 0 | AF60: =SUM(B60,C60:AE60) -> 17709930
A61: Cocina | B61: 0 | C61: =IFERROR(C16*'Comparación Mensual'!C5/C19,0) -> 0 | D61: =IFERROR(D16*'Comparación Mensual'!C6/D19,0) -> 0 | E61: =IFERROR(E16*'Comparación Mensual'!C7/E19,0) -> 0 | F61: =IFERROR(F16*'Comparación Mensual'!C8/F19,0) -> 0 | G61: =IFERROR(G16*'Comparación Mensual'!C9/G19,0) -> 0 | H61: =IFERROR(H16*'Comparación Mensual'!C10/H19,0) -> 0 | I61: =IFERROR(I16*'Comparación Mensual'!C11/I19,0) -> 0 | J61: =IFERROR(J16*'Comparación Mensual'!C12/J19,0) -> 0 | K61: =K16*Reprogramación!$C$14/Reprogramación!$B$14 -> 0 | L61: =L16*Reprogramación!$C$15/Reprogramación!$B$15 -> 0 | M61: =M16 -> 0 | N61: =N16 -> 0 | O61: =O16 -> 0 | P61: =P16 -> 0 | Q61: =Q16 -> 0 | R61: =R16 -> 0 | S61: =S16 -> 0 | T61: =T16 -> 0 | ... V61: =V16 -> 0 | W61: 0 | X61: 0 | Y61: 0 | Z61: 0 | AA61: 0 | AB61: 0 | AC61: 0 | AD61: 0 | AE61: 0 | AF61: =SUM(B61,C61:AE61) -> 0
A62: Paisajismo | B62: 0 | C62: =IFERROR(C17*'Comparación Mensual'!C5/C19,0) -> 0 | D62: =IFERROR(D17*'Comparación Mensual'!C6/D19,0) -> 0 | E62: =IFERROR(E17*'Comparación Mensual'!C7/E19,0) -> 0 | F62: =IFERROR(F17*'Comparación Mensual'!C8/F19,0) -> 0 | G62: =IFERROR(G17*'Comparación Mensual'!C9/G19,0) -> 0 | H62: =IFERROR(H17*'Comparación Mensual'!C10/H19,0) -> 0 | I62: =IFERROR(I17*'Comparación Mensual'!C11/I19,0) -> 0 | J62: =IFERROR(J17*'Comparación Mensual'!C12/J19,0) -> 0 | K62: =K17*Reprogramación!$C$14/Reprogramación!$B$14 -> 0 | L62: =L17*Reprogramación!$C$15/Reprogramación!$B$15 -> 0 | M62: =M17 -> 0 | N62: =N17 -> 1796347.4 | O62: =O17 -> 718538.96 | P62: =P17 -> 1437077.9 | Q62: =Q17 -> 1437077.9 | R62: =R17 -> 1437077.9 | S62: =S17 -> 359269.48 | T62: =T17 -> 1718806.8 | ... V62: =V17 -> 0 | W62: 0 | X62: 0 | Y62: 0 | Z62: 0 | AA62: 0 | AB62: 0 | AC62: 0 | AD62: 0 | AE62: 0 | AF62: =SUM(B62,C62:AE62) -> 8904196.4
A63: Elementos Urbanos y Obras Ext. | B63: 0 | C63: =IFERROR(C18*'Comparación Mensual'!C5/C19,0) -> 10868586 | D63: =IFERROR(D18*'Comparación Mensual'!C6/D19,0) -> 156277.91 | E63: =IFERROR(E18*'Comparación Mensual'!C7/E19,0) -> 1801728.5 | F63: =IFERROR(F18*'Comparación Mensual'!C8/F19,0) -> 1833923.4 | G63: =IFERROR(G18*'Comparación Mensual'!C9/G19,0) -> 0 | H63: =IFERROR(H18*'Comparación Mensual'!C10/H19,0) -> 0 | I63: =IFERROR(I18*'Comparación Mensual'!C11/I19,0) -> 0 | J63: =IFERROR(J18*'Comparación Mensual'!C12/J19,0) -> 0 | K63: =K18*Reprogramación!$C$14/Reprogramación!$B$14 -> 0 | L63: =L18*Reprogramación!$C$15/Reprogramación!$B$15 -> 0 | M63: =M18 -> 5178434.3 | N63: =N18 -> 3452289.5 | O63: =O18 -> 5178434.3 | P63: =P18 -> 3452289.5 | Q63: =Q18 -> 3452289.5 | R63: =R18 -> 6639957.6 | S63: =S18 -> 1122416.6 | T63: =T18 -> 4012087.9 | ... V63: =V18 -> 0 | W63: 0 | X63: 0 | Y63: 0 | Z63: 0 | AA63: 0 | AB63: 0 | AC63: 0 | AD63: 0 | AE63: 0 | AF63: =SUM(B63,C63:AE63) -> 47148715
A64: TOTAL URBANISMO | B64: =Reprogramación!$B$6 -> 22125480 | C64: =SUM(C51:C63) -> 15407306 | D64: =SUM(D51:D63) -> 222844.91 | E64: =SUM(E51:E63) -> 2449569.8 | F64: =SUM(F51:F63) -> 1833923.4 | G64: =SUM(G51:G63) -> 2442502.3 | H64: =SUM(H51:H63) -> 4340947.8 | I64: =SUM(I51:I63) -> 5475884.7 | J64: =SUM(J51:J63) -> 8125258.5 | ... AE64: =SUM(AE51:AE63) -> 0 | AF64: =SUM(B64:AE64) -> 2.3585219e+08
A66: Excavaciones y Compactacion | B66: 0 | C66: =IFERROR(C21*'Comparación Mensual'!G5/C45,0) -> 257787.43 | D66: =IFERROR(D21*'Comparación Mensual'!G6/D45,0) -> 554632.17 | E66: =IFERROR(E21*'Comparación Mensual'!G7/E45,0) -> 1219985.6 | F66: =IFERROR(F21*'Comparación Mensual'!G8/F45,0) -> 2858735.4 | G66: =IFERROR(G21*'Comparación Mensual'!G9/G45,0) -> 845636.3 | H66: =IFERROR(H21*'Comparación Mensual'!G10/H45,0) -> 637576.43 | I66: =IFERROR(I21*'Comparación Mensual'!G11/I45,0) -> 490300.83 | J66: =IFERROR(J21*'Comparación Mensual'!G12/J45,0) -> 809908.37 | K66: =K21*Reprogramación!$C$40/Reprogramación!$B$40 -> 1308233.1 | L66: =L21*Reprogramación!$C$41/Reprogramación!$B$41 -> 0 | M66: =M21 -> 0 | N66: =N21 -> 0 | O66: =O21 -> 0 | P66: =P21 -> 0 | Q66: =Q21 -> 0 | R66: =R21 -> 0 | S66: =S21 -> 0 | T66: =T21 -> 0 | ... V66: =V21 -> 0 | W66: 0 | X66: 0 | Y66: 0 | Z66: 0 | AA66: 0 | AB66: 0 | AC66: 0 | AD66: 0 | AE66: 0 | AF66: =SUM(B66,C66:AE66) -> 8982795.6
A67: Acero en Platea | B67: 0 | C67: =IFERROR(C22*'Comparación Mensual'!G5/C45,0) -> 319267.98 | D67: =IFERROR(D22*'Comparación Mensual'!G6/D45,0) -> 686908.17 | E67: =IFERROR(E22*'Comparación Mensual'!G7/E45,0) -> 1510943.9 | F67: =IFERROR(F22*'Comparación Mensual'!G8/F45,0) -> 3540524.3 | G67: =IFERROR(G22*'Comparación Mensual'!G9/G45,0) -> 1047314.8 | H67: =IFERROR(H22*'Comparación Mensual'!G10/H45,0) -> 789634.07 | I67: =IFERROR(I22*'Comparación Mensual'!G11/I45,0) -> 607234.24 | J67: =IFERROR(J22*'Comparación Mensual'!G12/J45,0) -> 1003066 | K67: =K22*Reprogramación!$C$40/Reprogramación!$B$40 -> 1620237.8 | L67: =L22*Reprogramación!$C$41/Reprogramación!$B$41 -> 0 | M67: =M22 -> 0 | N67: =N22 -> 0 | O67: =O22 -> 0 | P67: =P22 -> 0 | Q67: =Q22 -> 0 | R67: =R22 -> 0 | S67: =S22 -> 0 | T67: =T22 -> 0 | ... V67: =V22 -> 0 | W67: 0 | X67: 0 | Y67: 0 | Z67: 0 | AA67: 0 | AB67: 0 | AC67: 0 | AD67: 0 | AE67: 0 | AF67: =SUM(B67,C67:AE67) -> 11125131
A68: Encofrado en Platea | B68: 0 | C68: =IFERROR(C23*'Comparación Mensual'!G5/C45,0) -> 32045.194 | D68: =IFERROR(D23*'Comparación Mensual'!G6/D45,0) -> 68945.547 | E68: =IFERROR(E23*'Comparación Mensual'!G7/E45,0) -> 151654.7 | F68: =IFERROR(F23*'Comparación Mensual'!G8/F45,0) -> 355365.39 | G68: =IFERROR(G23*'Comparación Mensual'!G9/G45,0) -> 105119.86 | H68: =IFERROR(H23*'Comparación Mensual'!G10/H45,0) -> 79256.232 | I68: =IFERROR(I23*'Comparación Mensual'!G11/I45,0) -> 60948.609 | J68: =IFERROR(J23*'Comparación Mensual'!G12/J45,0) -> 100678.57 | K68: =K23*Reprogramación!$C$40/Reprogramación!$B$40 -> 162624.62 | L68: =L23*Reprogramación!$C$41/Reprogramación!$B$41 -> 0 | M68: =M23 -> 0 | N68: =N23 -> 0 | O68: =O23 -> 0 | P68: =P23 -> 0 | Q68: =Q23 -> 0 | R68: =R23 -> 0 | S68: =S23 -> 0 | T68: =T23 -> 0 | ... V68: =V23 -> 0 | W68: 0 | X68: 0 | Y68: 0 | Z68: 0 | AA68: 0 | AB68: 0 | AC68: 0 | AD68: 0 | AE68: 0 | AF68: =SUM(B68,C68:AE68) -> 1116638.7
A69: Concreto en Platea | B69: 0 | C69: =IFERROR(C24*'Comparación Mensual'!G5/C45,0) -> 382136.58 | D69: =IFERROR(D24*'Comparación Mensual'!G6/D45,0) -> 822170.57 | E69: =IFERROR(E24*'Comparación Mensual'!G7/E45,0) -> 1808471.1 | F69: =IFERROR(F24*'Comparación Mensual'!G8/F45,0) -> 4237706 | G69: =IFERROR(G24*'Comparación Mensual'!G9/G45,0) -> 1253546.6 | H69: =IFERROR(H24*'Comparación Mensual'!G10/H45,0) -> 945124.72 | I69: =IFERROR(I24*'Comparación Mensual'!G11/I45,0) -> 726807.66 | J69: =IFERROR(J24*'Comparación Mensual'!G12/J45,0) -> 1200584.6 | K69: =K24*Reprogramación!$C$40/Reprogramación!$B$40 -> 1939286.6 | L69: =L24*Reprogramación!$C$41/Reprogramación!$B$41 -> 0 | M69: =M24 -> 0 | N69: =N24 -> 0 | O69: =O24 -> 0 | P69: =P24 -> 0 | Q69: =Q24 -> 0 | R69: =R24 -> 0 | S69: =S24 -> 0 | T69: =T24 -> 0 | ... V69: =V24 -> 0 | W69: 0 | X69: 0 | Y69: 0 | Z69: 0 | AA69: 0 | AB69: 0 | AC69: 0 | AD69: 0 | AE69: 0 | AF69: =SUM(B69,C69:AE69) -> 13315835
A70: Concreto en Molde | B70: 0 | C70: =IFERROR(C25*'Comparación Mensual'!G5/C45,0) -> 0 | D70: =IFERROR(D25*'Comparación Mensual'!G6/D45,0) -> 0 | E70: =IFERROR(E25*'Comparación Mensual'!G7/E45,0) -> 134991.28 | F70: =IFERROR(F25*'Comparación Mensual'!G8/F45,0) -> 1897912.6 | G70: =IFERROR(G25*'Comparación Mensual'!G9/G45,0) -> 1450328.3 | H70: =IFERROR(H25*'Comparación Mensual'!G10/H45,0) -> 1481503 | I70: =IFERROR(I25*'Comparación Mensual'!G11/I45,0) -> 1627552 | J70: =IFERROR(J25*'Comparación Mensual'!G12/J45,0) -> 2778104.5 | K70: =K25*Reprogramación!$C$40/Reprogramación!$B$40 -> 11290957 | L70: =L25*Reprogramación!$C$41/Reprogramación!$B$41 -> 8145433.3 | M70: =M25 -> 4790349.8 | N70: =N25 -> 4790349.8 | O70: =O25 -> 4311314.8 | P70: =P25 -> 0 | Q70: =Q25 -> 0 | R70: =R25 -> 0 | S70: =S25 -> 0 | T70: =T25 -> 0 | ... V70: =V25 -> 0 | W70: 0 | X70: 0 | Y70: 0 | Z70: 0 | AA70: 0 | AB70: 0 | AC70: 0 | AD70: 0 | AE70: 0 | AF70: =SUM(B70,C70:AE70) -> 42698796
A71: Encofrado en Molde | B71: 0 | C71: =IFERROR(C26*'Comparación Mensual'!G5/C45,0) -> 0 | D71: =IFERROR(D26*'Comparación Mensual'!G6/D45,0) -> 0 | E71: =IFERROR(E26*'Comparación Mensual'!G7/E45,0) -> 582928.34 | F71: =IFERROR(F26*'Comparación Mensual'!G8/F45,0) -> 2731897.5 | G71: =IFERROR(G26*'Comparación Mensual'!G9/G45,0) -> 1414204.2 | H71: =IFERROR(H26*'Comparación Mensual'!G10/H45,0) -> 1523220.3 | I71: =IFERROR(I26*'Comparación Mensual'!G11/I45,0) -> 1405640.7 | J71: =IFERROR(J26*'Comparación Mensual'!G12/J45,0) -> 2708908.8 | K71: =K26*Reprogramación!$C$40/Reprogramación!$B$40 -> 8751321.3 | L71: =L26*Reprogramación!$C$41/Reprogramación!$B$41 -> 7034830.6 | M71: =M26 -> 4137201.6 | N71: =N26 -> 4137201.6 | O71: =O26 -> 2068600.8 | P71: =P26 -> 0 | Q71: =Q26 -> 0 | R71: =R26 -> 0 | S71: =S26 -> 0 | T71: =T26 -> 0 | ... V71: =V26 -> 0 | W71: 0 | X71: 0 | Y71: 0 | Z71: 0 | AA71: 0 | AB71: 0 | AC71: 0 | AD71: 0 | AE71: 0 | AF71: =SUM(B71,C71:AE71) -> 36495956
A72: Acero en Superestructura | B72: 0 | C72: =IFERROR(C27*'Comparación Mensual'!G5/C45,0) -> 0 | D72: =IFERROR(D27*'Comparación Mensual'!G6/D45,0) -> 0 | E72: =IFERROR(E27*'Comparación Mensual'!G7/E45,0) -> 564254.23 | F72: =IFERROR(F27*'Comparación Mensual'!G8/F45,0) -> 3305476.5 | G72: =IFERROR(G27*'Comparación Mensual'!G9/G45,0) -> 1564457.3 | H72: =IFERROR(H27*'Comparación Mensual'!G10/H45,0) -> 1621866.3 | I72: =IFERROR(I27*'Comparación Mensual'!G11/I45,0) -> 1360611 | J72: =IFERROR(J27*'Comparación Mensual'!G12/J45,0) -> 2622128.9 | K72: =K27*Reprogramación!$C$40/Reprogramación!$B$40 -> 8470972.7 | L72: =L27*Reprogramación!$C$41/Reprogramación!$B$41 -> 6809469.8 | M72: =M27 -> 4004666.3 | N72: =N27 -> 4004666.3 | O72: =O27 -> 1001166.6 | P72: =P27 -> 0 | Q72: =Q27 -> 0 | R72: =R27 -> 0 | S72: =S27 -> 0 | T72: =T27 -> 0 | ... V72: =V27 -> 0 | W72: 0 | X72: 0 | Y72: 0 | Z72: 0 | AA72: 0 | AB72: 0 | AC72: 0 | AD72: 0 | AE72: 0 | AF72: =SUM(B72,C72:AE72) -> 35329736
A73: Instalaciones Electricas | B73: 0 | C73: =IFERROR(C28*'Comparación Mensual'!G5/C45,0) -> 0 | D73: =IFERROR(D28*'Comparación Mensual'!G6/D45,0) -> 0 | E73: =IFERROR(E28*'Comparación Mensual'!G7/E45,0) -> 149874.2 | F73: =IFERROR(F28*'Comparación Mensual'!G8/F45,0) -> 702386.44 | G73: =IFERROR(G28*'Comparación Mensual'!G9/G45,0) -> 363599.96 | H73: =IFERROR(H28*'Comparación Mensual'!G10/H45,0) -> 391628.62 | I73: =IFERROR(I28*'Comparación Mensual'!G11/I45,0) -> 361398.25 | J73: =IFERROR(J28*'Comparación Mensual'!G12/J45,0) -> 696475.9 | K73: =K28*Reprogramación!$C$40/Reprogramación!$B$40 -> 2250014.6 | L73: =L28*Reprogramación!$C$41/Reprogramación!$B$41 -> 1808695.1 | M73: =M28 -> 1063698.1 | N73: =N28 -> 1063698.1 | O73: =O28 -> 531849.06 | P73: =P28 -> 0 | Q73: =Q28 -> 0 | R73: =R28 -> 0 | S73: =S28 -> 0 | T73: =T28 -> 0 | ... V73: =V28 -> 0 | W73: 0 | X73: 0 | Y73: 0 | Z73: 0 | AA73: 0 | AB73: 0 | AC73: 0 | AD73: 0 | AE73: 0 | AF73: =SUM(B73,C73:AE73) -> 9383318.3
A74: Aguas Blancas | B74: 0 | C74: =IFERROR(C29*'Comparación Mensual'!G5/C45,0) -> 0 | D74: =IFERROR(D29*'Comparación Mensual'!G6/D45,0) -> 0 | E74: =IFERROR(E29*'Comparación Mensual'!G7/E45,0) -> 98801.484 | F74: =IFERROR(F29*'Comparación Mensual'!G8/F45,0) -> 463033.81 | G74: =IFERROR(G29*'Comparación Mensual'!G9/G45,0) -> 239695.8 | H74: =IFERROR(H29*'Comparación Mensual'!G10/H45,0) -> 258173.11 | I74: =IFERROR(I29*'Comparación Mensual'!G11/I45,0) -> 238244.36 | J74: =IFERROR(J29*'Comparación Mensual'!G12/J45,0) -> 459137.41 | K74: =K29*Reprogramación!$C$40/Reprogramación!$B$40 -> 1483275.9 | L74: =L29*Reprogramación!$C$41/Reprogramación!$B$41 -> 1192345 | M74: =M29 -> 701221.11 | N74: =N29 -> 701221.11 | O74: =O29 -> 350610.55 | P74: =P29 -> 0 | Q74: =Q29 -> 0 | R74: =R29 -> 0 | S74: =S29 -> 0 | T74: =T29 -> 0 | ... V74: =V29 -> 0 | W74: 0 | X74: 0 | Y74: 0 | Z74: 0 | AA74: 0 | AB74: 0 | AC74: 0 | AD74: 0 | AE74: 0 | AF74: =SUM(B74,C74:AE74) -> 6185759.6
A75: Aguas Residuales | B75: 0 | C75: =IFERROR(C30*'Comparación Mensual'!G5/C45,0) -> 0 | D75: =IFERROR(D30*'Comparación Mensual'!G6/D45,0) -> 0 | E75: =IFERROR(E30*'Comparación Mensual'!G7/E45,0) -> 109253.84 | F75: =IFERROR(F30*'Comparación Mensual'!G8/F45,0) -> 512018.87 | G75: =IFERROR(G30*'Comparación Mensual'!G9/G45,0) -> 265053.58 | H75: =IFERROR(H30*'Comparación Mensual'!G10/H45,0) -> 285485.64 | I75: =IFERROR(I30*'Comparación Mensual'!G11/I45,0) -> 263448.6 | J75: =IFERROR(J30*'Comparación Mensual'!G12/J45,0) -> 507710.26 | K75: =K30*Reprogramación!$C$40/Reprogramación!$B$40 -> 1640193.9 | L75: =L30*Reprogramación!$C$41/Reprogramación!$B$41 -> 1318485 | M75: =M30 -> 775404.36 | N75: =N30 -> 775404.36 | O75: =O30 -> 387702.18 | P75: =P30 -> 0 | Q75: =Q30 -> 0 | R75: =R30 -> 0 | S75: =S30 -> 0 | T75: =T30 -> 0 | ... V75: =V30 -> 0 | W75: 0 | X75: 0 | Y75: 0 | Z75: 0 | AA75: 0 | AB75: 0 | AC75: 0 | AD75: 0 | AE75: 0 | AF75: =SUM(B75,C75:AE75) -> 6840160.6
A76: Gas | B76: 0 | C76: =IFERROR(C31*'Comparación Mensual'!G5/C45,0) -> 0 | D76: =IFERROR(D31*'Comparación Mensual'!G6/D45,0) -> 0 | E76: =IFERROR(E31*'Comparación Mensual'!G7/E45,0) -> 27889.103 | F76: =IFERROR(F31*'Comparación Mensual'!G8/F45,0) -> 130702.47 | G76: =IFERROR(G31*'Comparación Mensual'!G9/G45,0) -> 67659.923 | H76: =IFERROR(H31*'Comparación Mensual'!G10/H45,0) -> 72875.591 | I76: =IFERROR(I31*'Comparación Mensual'!G11/I45,0) -> 67250.221 | J76: =IFERROR(J31*'Comparación Mensual'!G12/J45,0) -> 129602.61 | K76: =K31*Reprogramación!$C$40/Reprogramación!$B$40 -> 418690.4 | L76: =L31*Reprogramación!$C$41/Reprogramación!$B$41 -> 336568.16 | M76: =M31 -> 197936.58 | N76: =N31 -> 197936.58 | O76: =O31 -> 98968.29 | P76: =P31 -> 0 | Q76: =Q31 -> 0 | R76: =R31 -> 0 | S76: =S31 -> 0 | T76: =T31 -> 0 | ... V76: =V31 -> 0 | W76: 0 | X76: 0 | Y76: 0 | Z76: 0 | AA76: 0 | AB76: 0 | AC76: 0 | AD76: 0 | AE76: 0 | AF76: =SUM(B76,C76:AE76) -> 1746079.9
A77: Albañileria | B77: 0 | C77: =IFERROR(C32*'Comparación Mensual'!G5/C45,0) -> 0 | D77: =IFERROR(D32*'Comparación Mensual'!G6/D45,0) -> 0 | E77: =IFERROR(E32*'Comparación Mensual'!G7/E45,0) -> 0 | F77: =IFERROR(F32*'Comparación Mensual'!G8/F45,0) -> 0 | G77: =IFERROR(G32*'Comparación Mensual'!G9/G45,0) -> 1557833.5 | H77: =IFERROR(H32*'Comparación Mensual'!G10/H45,0) -> 1174545 | I77: =IFERROR(I32*'Comparación Mensual'!G11/I45,0) -> 903233.51 | J77: =IFERROR(J32*'Comparación Mensual'!G12/J45,0) -> 1492015.4 | K77: =K32*Reprogramación!$C$40/Reprogramación!$B$40 -> 4820061.1 | L77: =L32*Reprogramación!$C$41/Reprogramación!$B$41 -> 4520425.9 | M77: =M32 -> 2658473.8 | N77: =N32 -> 2658473.8 | O77: =O32 -> 1772315.9 | P77: =P32 -> 0 | Q77: =Q32 -> 0 | R77: =R32 -> 0 | S77: =S32 -> 0 | T77: =T32 -> 0 | ... V77: =V32 -> 0 | W77: 0 | X77: 0 | Y77: 0 | Z77: 0 | AA77: 0 | AB77: 0 | AC77: 0 | AD77: 0 | AE77: 0 | AF77: =SUM(B77,C77:AE77) -> 21557378
A78: Antepecho | B78: 0 | C78: =IFERROR(C33*'Comparación Mensual'!G5/C45,0) -> 0 | D78: =IFERROR(D33*'Comparación Mensual'!G6/D45,0) -> 0 | E78: =IFERROR(E33*'Comparación Mensual'!G7/E45,0) -> 62849.601 | F78: =IFERROR(F33*'Comparación Mensual'!G8/F45,0) -> 294545.08 | G78: =IFERROR(G33*'Comparación Mensual'!G9/G45,0) -> 152475.29 | H78: =IFERROR(H33*'Comparación Mensual'!G10/H45,0) -> 164229.08 | I78: =IFERROR(I33*'Comparación Mensual'!G11/I45,0) -> 151552.01 | J78: =IFERROR(J33*'Comparación Mensual'!G12/J45,0) -> 292066.5 | K78: =K33*Reprogramación!$C$40/Reprogramación!$B$40 -> 943541.46 | L78: =L33*Reprogramación!$C$41/Reprogramación!$B$41 -> 758474.53 | M78: =M33 -> 446060.78 | N78: =N33 -> 446060.78 | O78: =O33 -> 223030.39 | P78: =P33 -> 0 | Q78: =Q33 -> 0 | R78: =R33 -> 0 | S78: =S33 -> 0 | T78: =T33 -> 0 | ... V78: =V33 -> 0 | W78: 0 | X78: 0 | Y78: 0 | Z78: 0 | AA78: 0 | AB78: 0 | AC78: 0 | AD78: 0 | AE78: 0 | AF78: =SUM(B78,C78:AE78) -> 3934885.5
A79: Herreria | B79: 0 | C79: =IFERROR(C34*'Comparación Mensual'!G5/C45,0) -> 0 | D79: =IFERROR(D34*'Comparación Mensual'!G6/D45,0) -> 0 | E79: =IFERROR(E34*'Comparación Mensual'!G7/E45,0) -> 0 | F79: =IFERROR(F34*'Comparación Mensual'!G8/F45,0) -> 0 | G79: =IFERROR(G34*'Comparación Mensual'!G9/G45,0) -> 2439844.5 | H79: =IFERROR(H34*'Comparación Mensual'!G10/H45,0) -> 1839546.6 | I79: =IFERROR(I34*'Comparación Mensual'!G11/I45,0) -> 1414624.5 | J79: =IFERROR(J34*'Comparación Mensual'!G12/J45,0) -> 2336761.7 | K79: =K34*Reprogramación!$C$40/Reprogramación!$B$40 -> 7549073.7 | L79: =L34*Reprogramación!$C$41/Reprogramación!$B$41 -> 7079791.6 | M79: =M34 -> 4163643.2 | N79: =N34 -> 4163643.2 | O79: =O34 -> 2775762.2 | P79: =P34 -> 0 | Q79: =Q34 -> 0 | R79: =R34 -> 0 | S79: =S34 -> 0 | T79: =T34 -> 0 | ... V79: =V34 -> 0 | W79: 0 | X79: 0 | Y79: 0 | Z79: 0 | AA79: 0 | AB79: 0 | AC79: 0 | AD79: 0 | AE79: 0 | AF79: =SUM(B79,C79:AE79) -> 33762691
A80: Revestimiento | B80: 0 | C80: =IFERROR(C35*'Comparación Mensual'!G5/C45,0) -> 0 | D80: =IFERROR(D35*'Comparación Mensual'!G6/D45,0) -> 0 | E80: =IFERROR(E35*'Comparación Mensual'!G7/E45,0) -> 0 | F80: =IFERROR(F35*'Comparación Mensual'!G8/F45,0) -> 2593319.3 | G80: =IFERROR(G35*'Comparación Mensual'!G9/G45,0) -> 2301372.5 | H80: =IFERROR(H35*'Comparación Mensual'!G10/H45,0) -> 1735144.1 | I80: =IFERROR(I35*'Comparación Mensual'!G11/I45,0) -> 4892573.5 | J80: =IFERROR(J35*'Comparación Mensual'!G12/J45,0) -> 2204140 | K80: =K35*Reprogramación!$C$40/Reprogramación!$B$40 -> 7120630.2 | L80: =L35*Reprogramación!$C$41/Reprogramación!$B$41 -> 17807952 | M80: =M35 -> 3927337.9 | N80: =N35 -> 3927337.9 | O80: =O35 -> 3927337.9 | P80: =P35 -> 2618225.3 | Q80: =Q35 -> 7200119.6 | R80: =R35 -> 4581894.3 | S80: =S35 -> 0 | T80: =T35 -> 0 | ... V80: =V35 -> 0 | W80: 0 | X80: 0 | Y80: 0 | Z80: 0 | AA80: 0 | AB80: 0 | AC80: 0 | AD80: 0 | AE80: 0 | AF80: =SUM(B80,C80:AE80) -> 64837384
A81: Carpinteria | B81: 0 | C81: =IFERROR(C36*'Comparación Mensual'!G5/C45,0) -> 0 | D81: =IFERROR(D36*'Comparación Mensual'!G6/D45,0) -> 0 | E81: =IFERROR(E36*'Comparación Mensual'!G7/E45,0) -> 0 | F81: =IFERROR(F36*'Comparación Mensual'!G8/F45,0) -> 0 | G81: =IFERROR(G36*'Comparación Mensual'!G9/G45,0) -> 0 | H81: =IFERROR(H36*'Comparación Mensual'!G10/H45,0) -> 0 | I81: =IFERROR(I36*'Comparación Mensual'!G11/I45,0) -> 4106053.6 | J81: =IFERROR(J36*'Comparación Mensual'!G12/J45,0) -> 0 | K81: =K36*Reprogramación!$C$40/Reprogramación!$B$40 -> 0 | L81: =L36*Reprogramación!$C$41/Reprogramación!$B$41 -> 20549626 | M81: =M36 -> 0 | N81: =N36 -> 0 | O81: =O36 -> 12085287 | P81: =P36 -> 0 | Q81: =Q36 -> 12085287 | R81: =R36 -> 0 | S81: =S36 -> 4028428.9 | T81: =T36 -> 0 | ... V81: =V36 -> 0 | W81: 0 | X81: 0 | Y81: 0 | Z81: 0 | AA81: 0 | AB81: 0 | AC81: 0 | AD81: 0 | AE81: 0 | AF81: =SUM(B81,C81:AE81) -> 52854682
A82: Ventaneria | B82: 0 | C82: =IFERROR(C37*'Comparación Mensual'!G5/C45,0) -> 0 | D82: =IFERROR(D37*'Comparación Mensual'!G6/D45,0) -> 0 | E82: =IFERROR(E37*'Comparación Mensual'!G7/E45,0) -> 0 | F82: =IFERROR(F37*'Comparación Mensual'!G8/F45,0) -> 0 | G82: =IFERROR(G37*'Comparación Mensual'!G9/G45,0) -> 0 | H82: =IFERROR(H37*'Comparación Mensual'!G10/H45,0) -> 1347189 | I82: =IFERROR(I37*'Comparación Mensual'!G11/I45,0) -> 2071995.9 | J82: =IFERROR(J37*'Comparación Mensual'!G12/J45,0) -> 0 | K82: =K37*Reprogramación!$C$40/Reprogramación!$B$40 -> 11057104 | L82: =L37*Reprogramación!$C$41/Reprogramación!$B$41 -> 0 | M82: =M37 -> 0 | N82: =N37 -> 6098475 | O82: =O37 -> 0 | P82: =P37 -> 3049237.5 | Q82: =Q37 -> 2032825 | R82: =R37 -> 0 | S82: =S37 -> 0 | T82: =T37 -> 0 | ... V82: =V37 -> 0 | W82: 0 | X82: 0 | Y82: 0 | Z82: 0 | AA82: 0 | AB82: 0 | AC82: 0 | AD82: 0 | AE82: 0 | AF82: =SUM(B82,C82:AE82) -> 25656827
A83: Cableado y Piezas Electricas | B83: 0 | C83: =IFERROR(C38*'Comparación Mensual'!G5/C45,0) -> 0 | D83: =IFERROR(D38*'Comparación Mensual'!G6/D45,0) -> 0 | E83: =IFERROR(E38*'Comparación Mensual'!G7/E45,0) -> 0 | F83: =IFERROR(F38*'Comparación Mensual'!G8/F45,0) -> 0 | G83: =IFERROR(G38*'Comparación Mensual'!G9/G45,0) -> 0 | H83: =IFERROR(H38*'Comparación Mensual'!G10/H45,0) -> 0 | I83: =IFERROR(I38*'Comparación Mensual'!G11/I45,0) -> 0 | J83: =IFERROR(J38*'Comparación Mensual'!G12/J45,0) -> 0 | K83: =K38*Reprogramación!$C$40/Reprogramación!$B$40 -> 2298707.7 | L83: =L38*Reprogramación!$C$41/Reprogramación!$B$41 -> 3233715.6 | M83: =M38 -> 1901756.3 | N83: =N38 -> 1901756.3 | O83: =O38 -> 1901756.3 | P83: =P38 -> 950878.14 | Q83: =Q38 -> 1901756.3 | R83: =R38 -> 1901756.3 | S83: =S38 -> 1901756.3 | T83: =T38 -> 950878.14 | ... V83: =V38 -> 0 | W83: 0 | X83: 0 | Y83: 0 | Z83: 0 | AA83: 0 | AB83: 0 | AC83: 0 | AD83: 0 | AE83: 0 | AF83: =SUM(B83,C83:AE83) -> 18844717
A84: Piezas Sanitarias | B84: 0 | C84: =IFERROR(C39*'Comparación Mensual'!G5/C45,0) -> 0 | D84: =IFERROR(D39*'Comparación Mensual'!G6/D45,0) -> 0 | E84: =IFERROR(E39*'Comparación Mensual'!G7/E45,0) -> 0 | F84: =IFERROR(F39*'Comparación Mensual'!G8/F45,0) -> 0 | G84: =IFERROR(G39*'Comparación Mensual'!G9/G45,0) -> 0 | H84: =IFERROR(H39*'Comparación Mensual'!G10/H45,0) -> 0 | I84: =IFERROR(I39*'Comparación Mensual'!G11/I45,0) -> 0 | J84: =IFERROR(J39*'Comparación Mensual'!G12/J45,0) -> 0 | K84: =K39*Reprogramación!$C$40/Reprogramación!$B$40 -> 2893774.1 | L84: =L39*Reprogramación!$C$41/Reprogramación!$B$41 -> 4070827.5 | M84: =M39 -> 2394063.9 | N84: =N39 -> 2394063.9 | O84: =O39 -> 2394063.9 | P84: =P39 -> 1197031.9 | Q84: =Q39 -> 2394063.9 | R84: =R39 -> 2394063.9 | S84: =S39 -> 2394063.9 | T84: =T39 -> 1197031.9 | ... V84: =V39 -> 0 | W84: 0 | X84: 0 | Y84: 0 | Z84: 0 | AA84: 0 | AB84: 0 | AC84: 0 | AD84: 0 | AE84: 0 | AF84: =SUM(B84,C84:AE84) -> 23723049
A85: Pintura Interior | B85: 0 | C85: =IFERROR(C40*'Comparación Mensual'!G5/C45,0) -> 0 | D85: =IFERROR(D40*'Comparación Mensual'!G6/D45,0) -> 0 | E85: =IFERROR(E40*'Comparación Mensual'!G7/E45,0) -> 0 | F85: =IFERROR(F40*'Comparación Mensual'!G8/F45,0) -> 0 | G85: =IFERROR(G40*'Comparación Mensual'!G9/G45,0) -> 0 | H85: =IFERROR(H40*'Comparación Mensual'!G10/H45,0) -> 0 | I85: =IFERROR(I40*'Comparación Mensual'!G11/I45,0) -> 340346.52 | J85: =IFERROR(J40*'Comparación Mensual'!G12/J45,0) -> 562204.84 | K85: =K40*Reprogramación!$C$40/Reprogramación!$B$40 -> 3632484.9 | L85: =L40*Reprogramación!$C$41/Reprogramación!$B$41 -> 3406674.4 | M85: =M40 -> 3005210.7 | N85: =N40 -> 3005210.7 | O85: =O40 -> 2003473.8 | P85: =P40 -> 2003473.8 | Q85: =Q40 -> 2003473.8 | R85: =R40 -> 3005210.7 | S85: =S40 -> 3005210.7 | T85: =T40 -> 2003473.8 | ... V85: =V40 -> 0 | W85: 0 | X85: 0 | Y85: 0 | Z85: 0 | AA85: 0 | AB85: 0 | AC85: 0 | AD85: 0 | AE85: 0 | AF85: =SUM(B85,C85:AE85) -> 27976448
A86: Pintura Exterior | B86: 0 | C86: =IFERROR(C41*'Comparación Mensual'!G5/C45,0) -> 0 | D86: =IFERROR(D41*'Comparación Mensual'!G6/D45,0) -> 0 | E86: =IFERROR(E41*'Comparación Mensual'!G7/E45,0) -> 0 | F86: =IFERROR(F41*'Comparación Mensual'!G8/F45,0) -> 0 | G86: =IFERROR(G41*'Comparación Mensual'!G9/G45,0) -> 0 | H86: =IFERROR(H41*'Comparación Mensual'!G10/H45,0) -> 0 | I86: =IFERROR(I41*'Comparación Mensual'!G11/I45,0) -> 170144.77 | J86: =IFERROR(J41*'Comparación Mensual'!G12/J45,0) -> 281055.36 | K86: =K41*Reprogramación!$C$40/Reprogramación!$B$40 -> 1815938.4 | L86: =L41*Reprogramación!$C$41/Reprogramación!$B$41 -> 1703052 | M86: =M41 -> 1502353.8 | N86: =N41 -> 1502353.8 | O86: =O41 -> 1001569.2 | P86: =P41 -> 1001569.2 | Q86: =Q41 -> 1001569.2 | R86: =R41 -> 1502353.8 | S86: =S41 -> 1502353.8 | T86: =T41 -> 1001569.2 | ... V86: =V41 -> 0 | W86: 0 | X86: 0 | Y86: 0 | Z86: 0 | AA86: 0 | AB86: 0 | AC86: 0 | AD86: 0 | AE86: 0 | AF86: =SUM(B86,C86:AE86) -> 13985882
A87: Pendientes de Techo e Imperm. | B87: 0 | C87: =IFERROR(C42*'Comparación Mensual'!G5/C45,0) -> 0 | D87: =IFERROR(D42*'Comparación Mensual'!G6/D45,0) -> 0 | E87: =IFERROR(E42*'Comparación Mensual'!G7/E45,0) -> 0 | F87: =IFERROR(F42*'Comparación Mensual'!G8/F45,0) -> 0 | G87: =IFERROR(G42*'Comparación Mensual'!G9/G45,0) -> 279515.55 | H87: =IFERROR(H42*'Comparación Mensual'!G10/H45,0) -> 316115.55 | I87: =IFERROR(I42*'Comparación Mensual'!G11/I45,0) -> 243095.12 | J87: =IFERROR(J42*'Comparación Mensual'!G12/J45,0) -> 401559.12 | K87: =K42*Reprogramación!$C$40/Reprogramación!$B$40 -> 1297265.1 | L87: =L42*Reprogramación!$C$41/Reprogramación!$B$41 -> 1216621.7 | M87: =M42 -> 715498.26 | N87: =N42 -> 715498.26 | O87: =O42 -> 715498.26 | P87: =P42 -> 0 | Q87: =Q42 -> 0 | R87: =R42 -> 0 | S87: =S42 -> 0 | T87: =T42 -> 0 | ... V87: =V42 -> 0 | W87: 0 | X87: 0 | Y87: 0 | Z87: 0 | AA87: 0 | AB87: 0 | AC87: 0 | AD87: 0 | AE87: 0 | AF87: =SUM(B87,C87:AE87) -> 5900666.9
A88: Miscelaneos | B88: 0 | C88: =IFERROR(C43*'Comparación Mensual'!G5/C45,0) -> 0 | D88: =IFERROR(D43*'Comparación Mensual'!G6/D45,0) -> 0 | E88: =IFERROR(E43*'Comparación Mensual'!G7/E45,0) -> 0 | F88: =IFERROR(F43*'Comparación Mensual'!G8/F45,0) -> 0 | G88: =IFERROR(G43*'Comparación Mensual'!G9/G45,0) -> 2104883.7 | H88: =IFERROR(H43*'Comparación Mensual'!G10/H45,0) -> 2380499 | I88: =IFERROR(I43*'Comparación Mensual'!G11/I45,0) -> 1830620.7 | J88: =IFERROR(J43*'Comparación Mensual'!G12/J45,0) -> 3023929.3 | K88: =K43*Reprogramación!$C$40/Reprogramación!$B$40 -> 9769017.4 | L88: =L43*Reprogramación!$C$41/Reprogramación!$B$41 -> 9161734.2 | M88: =M43 -> 5388038.9 | N88: =N43 -> 5388038.9 | O88: =O43 -> 1796013 | P88: =P43 -> 3592026 | Q88: =Q43 -> 0 | R88: =R43 -> 0 | S88: =S43 -> 0 | T88: =T43 -> 0 | ... V88: =V43 -> 0 | W88: 0 | X88: 0 | Y88: 0 | Z88: 0 | AA88: 0 | AB88: 0 | AC88: 0 | AD88: 0 | AE88: 0 | AF88: =SUM(B88,C88:AE88) -> 44434801
A89: Remates y Limpieza | B89: 0 | C89: =IFERROR(C44*'Comparación Mensual'!G5/C45,0) -> 0 | D89: =IFERROR(D44*'Comparación Mensual'!G6/D45,0) -> 0 | E89: =IFERROR(E44*'Comparación Mensual'!G7/E45,0) -> 0 | F89: =IFERROR(F44*'Comparación Mensual'!G8/F45,0) -> 0 | G89: =IFERROR(G44*'Comparación Mensual'!G9/G45,0) -> 0 | H89: =IFERROR(H44*'Comparación Mensual'!G10/H45,0) -> 0 | I89: =IFERROR(I44*'Comparación Mensual'!G11/I45,0) -> 0 | J89: =IFERROR(J44*'Comparación Mensual'!G12/J45,0) -> 0 | K89: =K44*Reprogramación!$C$40/Reprogramación!$B$40 -> 0 | L89: =L44*Reprogramación!$C$41/Reprogramación!$B$41 -> 591702.18 | M89: =M44 -> 521972.31 | N89: =N44 -> 521972.31 | O89: =O44 -> 521972.31 | P89: =P44 -> 521972.31 | Q89: =Q44 -> 521972.31 | R89: =R44 -> 521972.31 | S89: =S44 -> 521972.31 | T89: =T44 -> 260986.15 | ... V89: =V44 -> 0 | W89: 0 | X89: 0 | Y89: 0 | Z89: 0 | AA89: 0 | AB89: 0 | AC89: 0 | AD89: 0 | AE89: 0 | AF89: =SUM(B89,C89:AE89) -> 4767480.7
A90: TOTAL EDIFICIOS | B90: 0 | C90: =SUM(C66:C89) -> 991237.18 | D90: =SUM(D66:D89) -> 2132656.5 | E90: =SUM(E66:E89) -> 6421897.4 | F90: =SUM(F66:F89) -> 23623624 | G90: =SUM(G66:G89) -> 17452542 | H90: =SUM(H66:H89) -> 17043612 | I90: =SUM(I66:I89) -> 23333677 | J90: =SUM(J66:J89) -> 23610038 | ... AE90: =SUM(AE66:AE89) -> 0 | AF90: =SUM(B90:AE90) -> 5.154571e+08
A92: TOTAL GENERAL | B92: =B64+B90 -> 22125480 | C92: =C64+C90 -> 16398544 | D92: =D64+D90 -> 2355501.4 | E92: =E64+E90 -> 8871467.3 | F92: =F64+F90 -> 25457547 | G92: =G64+G90 -> 19895044 | H92: =H64+H90 -> 21384560 | I92: =I64+I90 -> 28809561 | ... AF92: =AF64+AF90 -> 7.5130928e+08
A93: Fase II | B93: 0 | C93: 0 | D93: 0 | E93: 0 | F93: 0 | G93: 0 | H93: 0 | I93: 0 | J93: 0 | K93: 3000000 | L93: 3000000 | M93: 5000000 | N93: 6017854.7 | O93: 10422492 | P93: 67360376 | Q93: 48536814 | R93: 42863066 | S93: 59770811 | T93: 75630539 | U93: 42327288 | V93: 49106009 | W93: 55804109 | X93: 50348190 | Y93: 50612198 | Z93: 29520263 | AA93: 24597664 | AB93: 28533771 | AC93: 20113034 | AD93: 1274860.8 | AE93: 637430.39 | AF93: =SUM(B93:AE93) -> 6.7447677e+08
A94: Total Fase I y Fase II | B94: =B92+B93 -> 22125480 | C94: =C92+C93 -> 16398544 | D94: =D92+D93 -> 2355501.4 | E94: =E92+E93 -> 8871467.3 | F94: =F92+F93 -> 25457547 | G94: =G92+G93 -> 19895044 | H94: =H92+H93 -> 21384560 | I94: =I92+I93 -> 28809561 | ... AF94: =AF92+AF93 -> 1.4257861e+09

Sheet Resumen
A1: ARAYA Fase I — Comparación Flujo Presupuestado vs. Gasto Real
A2: Periodo analizado: Dic-2025 a Jul-2026 · Fuente: Flujo semanal (proyectado) y Mayor de Cuentas (real)
A4: Concepto | B4: Presupuestado | C4: Real | D4: Variación | E4: Variación %
A5: Urbanismo (Dic-25 a Jul-26) | B5: 27978635 | C5: 40298238 | D5: =B5-C5 -> -12319603 | E5: =IFERROR(D5/B5,0) -> -0.44032182
A6: Edificios (Dic-25 a Jul-26) | B6: 1.9760368e+08 | C6: 1.1460928e+08 | D6: =B6-C6 -> 82994397 | E6: =IFERROR(D6/B6,0) -> 0.42000431
A7: TOTAL | B7: =SUM(B5:B6) -> 2.2558232e+08 | C7: =SUM(C5:C6) -> 1.5490752e+08 | D7: =B7-C7 -> 70674794 | E7: =IFERROR(D7/B7,0) -> 0.31329936
A9: Lectura del periodo
A10: • Urbanismo gastó RD$40.3M reales contra RD$28.0M presupuestados (Dic-25 a Jul-26) — un sobregiro de ~RD$12.3M, explicado principalmente por el pago adelantado del contrato de Movimiento de Tierra en diciembre 2025. En julio, Urbanismo también se sobregiró (RD$8.1M reales vs RD$2.2M presupuestados), por el arranque de partidas de infraestructura pendientes.
A11: • Edificios gastó RD$114.6M reales contra RD$197.6M presupuestados — un remanente de ~RD$83.0M no ejecutado, consistente con los atrasos de estructura y acabados. En julio el remanente individual fue de ~RD$18.5M.
A12: • Reprogramación de julio: la variación acumulada real de Dic-25 a Jul-26 (Urbanismo y Edificios) se redistribuyó íntegramente entre agosto y septiembre 2026 (mitad y mitad por categoría), sin modificar el resto del flujo futuro. Ver hoja "Reprogramación".
A13: • Los gastos de Terreno, Diseño, Gerencia de Construcción, Indirectos, Inspección Técnica, Permisos y Gastos Financieros no forman parte del flujo de obra analizado; se excluyen de esta comparación por estar fuera del alcance de Urbanismo/Edificios.

Sheet Comparación Mensual
A1: Comparación Mensual — Presupuestado vs. Real
A2: Urbanismo y Edificios · Dic-2025 a Jul-2026
A4: Mes | B4: Urb. Presupuestado | C4: Urb. Real | D4: Urb. Variación | E4: Urb. Var. Acum. | F4: Edi. Presupuestado | G4: Edi. Real | H4: Edi. Variación | I4: Edi. Var. Acum. | J4: Total Presupuestado | K4: Total Real | L4: Total Variación
A5: Dic-25 | B5: 1121587.8 | C5: 15407306 | D5: =B5-C5 -> -14285719 | E5: =D5 -> -14285719 | F5: 1387237.5 | G5: 991237.18 | H5: =F5-G5 -> 396000.35 | I5: =H5 -> 396000.35 | J5: =B5+F5 -> 2508825.3 | K5: =C5+G5 -> 16398544 | L5: =J5-K5 -> -13889718
A6: Ene-26 | B6: 429788.37 | C6: 222844.91 | D6: =B6-C6 -> 206943.46 | E6: =E5+D6 -> -14078775 | F6: 1387237.5 | G6: 2132656.5 | H6: =F6-G6 -> -745418.92 | I6: =I5+H6 -> -349418.57 | J6: =B6+F6 -> 1817025.9 | K6: =C6+G6 -> 2355501.4 | L6: =J6-K6 -> -538475.46
A7: Feb-26 | B7: 5799618.3 | C7: 2449569.8 | D7: =B7-C7 -> 3350048.5 | E7: =E6+D7 -> -10728727 | F7: 3798163.3 | G7: 6421897.4 | H7: =F7-G7 -> -2623734.1 | I7: =I6+H7 -> -2973152.7 | J7: =B7+F7 -> 9597781.6 | K7: =C7+G7 -> 8871467.3 | L7: =J7-K7 -> 726314.35
A8: Mar-26 | B8: 688406.98 | C8: 1833923.4 | D8: =B8-C8 -> -1145516.4 | E8: =E7+D8 -> -11874243 | F8: 11925251 | G8: 23623624 | H8: =F8-G8 -> -11698373 | I8: =I7+H8 -> -14671525 | J8: =B8+F8 -> 12613658 | K8: =C8+G8 -> 25457547 | L8: =J8-K8 -> -12843889
A9: Abr-26 | B9: 1895547.6 | C9: 2442502.3 | D9: =B9-C9 -> -546954.75 | E9: =E8+D9 -> -12421198 | F9: 29783110 | G9: 17452542 | H9: =F9-G9 -> 12330568 | I9: =I8+H9 -> -2340957.3 | J9: =B9+F9 -> 31678657 | K9: =C9+G9 -> 19895044 | L9: =J9-K9 -> 11783613
A10: May-26 | B10: 4597021 | C10: 4340947.8 | D10: =B10-C10 -> 256073.19 | E10: =E9+D10 -> -12165125 | F10: 38576638 | G10: 17043612 | H10: =F10-G10 -> 21533025 | I10: =I9+H10 -> 19192068 | J10: =B10+F10 -> 43173659 | K10: =C10+G10 -> 21384560 | L10: =J10-K10 -> 21789098
A11: Jun-26 | B11: 11213301 | C11: 5475884.7 | D11: =B11-C11 -> 5737416.2 | E11: =E10+D11 -> -6427708.6 | F11: 68677665 | G11: 23333677 | H11: =F11-G11 -> 45343989 | I11: =I10+H11 -> 64536057 | J11: =B11+F11 -> 79890966 | K11: =C11+G11 -> 28809561 | L11: =J11-K11 -> 51081405
A12: Jul-26 | B12: 2233363.8 | C12: 8125258.5 | D12: =B12-C12 -> -5891894.8 | E12: =E11+D12 -> -12319603 | F12: 42068379 | G12: 23610038 | H12: =F12-G12 -> 18458341 | I12: =I11+H12 -> 82994397 | J12: =B12+F12 -> 44301743 | K12: =C12+G12 -> 31735297 | L12: =J12-K12 -> 12566446
A13: TOTAL | B13: =SUM(B5:B12) -> 27978635 | C13: =SUM(C5:C12) -> 40298238 | D13: =B13-C13 -> -12319603 | E13: =E12 -> -12319603 | F13: =SUM(F5:F12) -> 1.9760368e+08 | G13: =SUM(G5:G12) -> 1.1460928e+08 | H13: =F13-G13 -> 82994397 | I13: =I12 -> 82994397 | J13: =B13+F13 -> 2.2558232e+08 | K13: =C13+G13 -> 1.5490752e+08 | L13: =J13-K13 -> 70674794
A14: Nota: "Var. Acum." es la variación (Presupuestado − Real) acumulada mes a mes; positivo = remanente sin ejecutar, negativo = sobregiro frente al plan.

Sheet Reprogramación
A1: Reprogramación de Julio (Ago-2026 a Jul-2027)
A2: Metodología: junio y julio ya son reales (fuente: Costos_Araya_Dic-25_a_Jun-26.xlsx y Datos_para_informe_Julio_2026.xlsx). La variación acumulada de todo el periodo real (Dic-25 a Jul-26 vs. presupuesto original de esos mismos meses) se redistribuye únicamente entre Ago-26 y Sep-26 (mitad y mitad), de forma que el total reprogramado cierre exacto en el presupuesto total del proyecto. El resto de los meses futuros conserva su presupuesto original sin reescalar.
A4: URBANISMO
A5: Total Proyección (presupuesto total del proyecto) | B5: 2.3585219e+08
A6: Acumulado real anterior a Dic-2025 (según flujo) | B6: 22125480
A7: Real ejecutado Dic-25 a Jul-26 | B7: 40298238
A8: Real total acumulado a la fecha | B8: =B6+B7 -> 62423718
A9: Restante a distribuir (Ago-26 a Jul-27, informativo) | B9: =B5-B8 -> 1.7342847e+08
A11: Mes | B11: Presupuesto Original | C11: Presupuesto Reprogramado | D11: Diferencia
A12: Jun-26 | B12: 11213301 | C12: 5475884.7 | D12: =C12-B12 -> -5737416.2
A13: Jul-26 | B13: 2233363.8 | C13: 8125258.5 | D13: =C13-B13 -> 5891894.8
A14: Ago-26 | B14: 25883233 | C14: =B14+($B$9-SUM($B$14:$B$25))/2 -> 19723431 | D14: =C14-B14 -> -6159801.7
A15: Sep-26 | B15: 19023863 | C15: =B15+($B$9-SUM($B$14:$B$25))/2 -> 12864061 | D15: =C15-B15 -> -6159801.7
A16: Oct-26 | B16: 30184986 | C16: =B16 -> 30184986 | D16: =C16-B16 -> 0
A17: Nov-26 | B17: 22131187 | C17: =B17 -> 22131187 | D17: =C17-B17 -> 0
A18: Dic-26 | B18: 22631604 | C18: =B18 -> 22631604 | D18: =C18-B18 -> 0
A19: Ene-27 | B19: 18550349 | C19: =B19 -> 18550349 | D19: =C19-B19 -> 0
A20: Feb-27 | B20: 14846961 | C20: =B20 -> 14846961 | D20: =C20-B20 -> 0
A21: Mar-27 | B21: 19972418 | C21: =B21 -> 19972418 | D21: =C21-B21 -> 0
A22: Abr-27 | B22: 3961494.6 | C22: =B22 -> 3961494.6 | D22: =C22-B22 -> 0
A23: May-27 | B23: 8561974.3 | C23: =B23 -> 8561974.3 | D23: =C23-B23 -> 0
A24: Jun-27 | B24: 0 | C24: =B24 -> 0 | D24: =C24-B24 -> 0
A25: Jul-27 | B25: 0 | C25: =B25 -> 0 | D25: =C25-B25 -> 0
A26: SUMA (Jun-26 y Jul-26 real + Ago-26 a Jul-27 reprogramado) | B26: =SUM(B12:B25) -> 1.9919474e+08 | C26: =SUM(C12:C25) -> 1.8702961e+08
A27: Variación acumulada Dic-25 a Jul-26 redistribuida (Ago-26 + Sep-26) | B27: =$B$9-SUM($B$14:$B$25) -> -12319603
A28: Verificación: Real acum. a la fecha + Reprogramado (Ago-26 a Jul-27) = Total Proyección | B28: =B8+SUM(C14:C25) -> 2.3585219e+08 | C28: =B5 -> 2.3585219e+08 | D28: =B28-C28 -> 0
A30: EDIFICIOS
A31: Total Proyección (presupuesto total del proyecto) | B31: 5.154571e+08
A32: Acumulado real anterior a Dic-2025 (según flujo) | B32: 0
A33: Real ejecutado Dic-25 a Jul-26 | B33: 1.1460928e+08
A34: Real total acumulado a la fecha | B34: =B32+B33 -> 1.1460928e+08
A35: Restante a distribuir (Ago-26 a Jul-27, informativo) | B35: =B31-B34 -> 4.0084782e+08
A37: Mes | B37: Presupuesto Original | C37: Presupuesto Reprogramado | D37: Diferencia
A38: Jun-26 | B38: 68677665 | C38: 23333677 | D38: =C38-B38 -> -45343989
A39: Jul-26 | B39: 42068379 | C39: 23610038 | D39: =C39-B39 -> -18458341
A40: Ago-26 | B40: 51036207 | C40: =B40+($B$35-SUM($B$40:$B$51))/2 -> 92533406 | D40: =C40-B40 -> 41497199
A41: Sep-26 | B41: 59249226 | C41: =B41+($B$35-SUM($B$40:$B$51))/2 -> 1.0074642e+08 | D41: =C41-B41 -> 41497199
A42: Oct-26 | B42: 42294888 | C42: =B42 -> 42294888 | D42: =C42-B42 -> 0
A43: Nov-26 | B43: 48393363 | C43: =B43 -> 48393363 | D43: =C43-B43 -> 0
A44: Dic-26 | B44: 39868292 | C44: =B44 -> 39868292 | D44: =C44-B44 -> 0
A45: Ene-27 | B45: 14934414 | C45: =B45 -> 14934414 | D45: =C45-B45 -> 0
A46: Feb-27 | B46: 29141067 | C46: =B46 -> 29141067 | D46: =C46-B46 -> 0
A47: Mar-27 | B47: 13907251 | C47: =B47 -> 13907251 | D47: =C47-B47 -> 0
A48: Abr-27 | B48: 13353786 | C48: =B48 -> 13353786 | D48: =C48-B48 -> 0
A49: May-27 | B49: 5413939.2 | C49: =B49 -> 5413939.2 | D49: =C49-B49 -> 0
A50: Jun-27 | B50: 260986.15 | C50: =B50 -> 260986.15 | D50: =C50-B50 -> 0
A51: Jul-27 | B51: 0 | C51: =B51 -> 0 | D51: =C51-B51 -> 0
A52: SUMA (Jun-26 y Jul-26 real + Ago-26 a Jul-27 reprogramado) | B52: =SUM(B38:B51) -> 4.2859946e+08 | C52: =SUM(C38:C51) -> 4.4779153e+08
A53: Variación acumulada Dic-25 a Jul-26 redistribuida (Ago-26 + Sep-26) | B53: =$B$35-SUM($B$40:$B$51) -> 82994397
A54: Verificación: Real acum. a la fecha + Reprogramado (Ago-26 a Jul-27) = Total Proyección | B54: =B34+SUM(C40:C51) -> 5.154571e+08 | C54: =B31 -> 5.154571e+08 | D54: =B54-C54 -> 0
A56: Nota: esta versión concentra TODA la variación real acumulada (Dic-25 a Jul-26) en Ago-26 y Sep-26, para que el total reprogramado cierre exactamente en el presupuesto original del proyecto (SUMA Reprogramado = SUMA Original en cada categoría, y el gran total = RD$751,309,285). El resto de los meses futuros no se toca.

Sheet Detalle Presupuesto x Categoría
A1: Detalle del Flujo Presupuestado por Categoría (Dic-25 a May-26)
A2: Fuente: Flujo_Araya_fase_I. Solo disponible a nivel de categoría en el presupuesto — el gasto real del mayor contable solo distingue Urbanismo vs. Edificios en conjunto.
A4: Categoría | B4: Dic-25 | C4: Ene-26 | D4: Feb-26 | E4: Mar-26 | F4: Abr-26 | G4: May-26 | H4: Total Periodo
A5: URBANISMO
A6: Instalaciones Preliminares | B6: 330400 | C6: 128384 | D6: 1533833.6 | E6: 0 | F6: 0 | G6: 0 | H6: =SUM(B6:G6) -> 1992617.6
A7: Movimiento de Tierra | B7: 0 | C7: 0 | D7: 0 | E7: 0 | F7: 1895547.6 | G7: 4597021 | H7: =SUM(B7:G7) -> 6492568.6
A8: Instalaciones Residual | B8: 0 | C8: 0 | D8: 0 | E8: 0 | F8: 0 | G8: 0 | H8: =SUM(B8:G8) -> 0
A9: Instalaciones Pluvial | B9: 0 | C9: 0 | D9: 0 | E9: 0 | F9: 0 | G9: 0 | H9: =SUM(B9:G9) -> 0
A10: Instalaciones Agua Potable | B10: 0 | C10: 0 | D10: 0 | E10: 0 | F10: 0 | G10: 0 | H10: =SUM(B10:G10) -> 0
A11: Pozo y Tanques | B11: 0 | C11: 0 | D11: 0 | E11: 0 | F11: 0 | G11: 0 | H11: =SUM(B11:G11) -> 0
A12: Escalera | B12: 0 | C12: 0 | D12: 0 | E12: 0 | F12: 0 | G12: 0 | H12: =SUM(B12:G12) -> 0
A13: Planta de Tratamiento | B13: 0 | C13: 0 | D13: 0 | E13: 0 | F13: 0 | G13: 0 | H13: =SUM(B13:G13) -> 0
A14: Electrificacion y Telecom | B14: 0 | C14: 0 | D14: 0 | E14: 0 | F14: 0 | G14: 0 | H14: =SUM(B14:G14) -> 0
A15: Vialidad y Gas | B15: 0 | C15: 0 | D15: 0 | E15: 0 | F15: 0 | G15: 0 | H15: =SUM(B15:G15) -> 0
A16: Cocina | B16: 0 | C16: 0 | D16: 0 | E16: 0 | F16: 0 | G16: 0 | H16: =SUM(B16:G16) -> 0
A17: Paisajismo | B17: 0 | C17: 0 | D17: 0 | E17: 0 | F17: 0 | G17: 0 | H17: =SUM(B17:G17) -> 0
A18: Elementos Urbanos y Obras Ext. | B18: 791187.8 | C18: 301404.37 | D18: 4265784.7 | E18: 688406.98 | F18: 0 | G18: 0 | H18: =SUM(B18:G18) -> 6046783.8
A19: TOTAL URBANISMO | B19: =SUM(B6:B18) -> 1121587.8 | C19: =SUM(C6:C18) -> 429788.37 | D19: =SUM(D6:D18) -> 5799618.3 | E19: =SUM(E6:E18) -> 688406.98 | F19: =SUM(F6:F18) -> 1895547.6 | G19: =SUM(G6:G18) -> 4597021 | H19: =SUM(H6:H18) -> 14531970
A21: EDIFICIOS
A22: Excavaciones y Compactacion | B22: 360773.79 | C22: 360773.79 | D22: 721547.59 | E22: 1443095.2 | F22: 1443095.2 | G22: 1443095.2 | H22: =SUM(B22:G22) -> 5772380.7
A23: Acero en Platea | B23: 446815.89 | C23: 446815.89 | D23: 893631.78 | E23: 1787263.6 | F23: 1787263.6 | G23: 1787263.6 | H23: =SUM(B23:G23) -> 7149054.2
A24: Encofrado en Platea | B24: 44847.285 | C24: 44847.285 | D24: 89694.569 | E24: 179389.14 | F24: 179389.14 | G24: 179389.14 | H24: =SUM(B24:G24) -> 717556.55
A25: Concreto en Platea | B25: 534800.56 | C25: 534800.56 | D25: 1069601.1 | E25: 2139202.2 | F25: 2139202.2 | G25: 2139202.2 | H25: =SUM(B25:G25) -> 8556809
A26: Concreto en Molde | B26: 0 | C26: 0 | D26: 79839.163 | E26: 958069.96 | F26: 2475014.1 | G26: 3353244.9 | H26: =SUM(B26:G26) -> 6866168.1
A27: Encofrado en Molde | B27: 0 | C27: 0 | D27: 344766.8 | E27: 1379067.2 | F27: 2413367.6 | G27: 3447668 | H27: =SUM(B27:G27) -> 7584869.6
A28: Acero en Superestructura | B28: 0 | C28: 0 | D28: 333722.19 | E28: 1668611 | F28: 2669777.5 | G28: 3670944.1 | H28: =SUM(B28:G28) -> 8343054.8
A29: Instalaciones Electricas | B29: 0 | C29: 0 | D29: 88641.51 | E29: 354566.04 | F29: 620490.57 | G29: 886415.1 | H29: =SUM(B29:G29) -> 1950113.2
A30: Aguas Blancas | B30: 0 | C30: 0 | D30: 58435.092 | E30: 233740.37 | F30: 409045.65 | G30: 584350.93 | H30: =SUM(B30:G30) -> 1285572
A31: Aguas Residuales | B31: 0 | C31: 0 | D31: 64617.03 | E31: 258468.12 | F31: 452319.21 | G31: 646170.3 | H31: =SUM(B31:G31) -> 1421574.7
A32: Gas | B32: 0 | C32: 0 | D32: 16494.715 | E32: 65978.86 | F32: 115463.01 | G32: 164947.15 | H32: =SUM(B32:G32) -> 362883.73
A33: Albañileria | B33: 0 | C33: 0 | D33: 0 | E33: 0 | F33: 2658473.8 | G33: 2658473.8 | H33: =SUM(B33:G33) -> 5316947.6
... A45: Remates y Limpieza | B45: 0 | C45: 0 | D45: 0 | E45: 0 | F45: 0 | G45: 0 | H45: =SUM(B45:G45) -> 0
A46: TOTAL EDIFICIOS | B46: =SUM(B22:B45) -> 1387237.5 | C46: =SUM(C22:C45) -> 1387237.5 | D46: =SUM(D22:D45) -> 3798163.3 | E46: =SUM(E22:E45) -> 11925251 | F46: =SUM(F22:F45) -> 29783110 | G46: =SUM(G22:G45) -> 38576638 | H46: =SUM(H22:H45) -> 86857637

Sheet Hoja1
E8: 222844.91 | F8: 2449569.8 | G8: 1833923.4 | H8: 2442502.3 | I8: 4340947.8
E9: 2132656.5 | F9: 6421897.4 | G9: 23623624 | H9: 17452542 | I9: 17043612
E11: =SUM(E8:E10) -> 2355501.4 | F11: =SUM(F8:F10) -> 8871467.3 | G11: =SUM(G8:G10) -> 25457547 | H11: =SUM(H8:H10) -> 19895044 | I11: =SUM(I8:I10) -> 21384560
